Workbook
Name Lenders: 'Roster & Tables'!$I$2:$I$24
Name SalesRoster: 'Roster & Tables'!$C$2:$C$24
Name Makes: 'Roster & Tables'!$L$2:$L$50
Name Type: 'Roster & Tables'!$M$2:$M$8
Name Percent: 'Roster & Tables'!$K$2:$K$21
Name DriveTrain: 'Roster & Tables'!$N$2:$N$6

Sheet Roster & Tables
C1: Sales People | D1: Phone | E1: Confirmed? | F1: Setup | G1: According To Who | I1: Lenders | K1: Percentage | L1: Makes | M1: Type | N1: DriveTrain | P1: Dealership Passwords
B2: 1 | C2: NATE HARDING | E2: Y | I2: 5th/3rd | K2: 1 | L2: Buick | M2: Sedan | N2: FWD | P2: Type | R2: User Name | T2: Password | V2: Email | X2: Challenge Questions
B3: 2 | C3: IRELAND COMBS | E3: Y | I3: Chase | K3: 0.95 | L3: Cadillac | M3: SUV | N3: RWD | P3: ROUTEONE | R3: NATELAMBRECQUE123 | T3: Routeone123 | V3: nate@justdriveevents.com
B4: 3 | C4: TREVON HALL | E4: Y | I4: GM Fin Ret | K4: 0.9 | L4: Chevy | M4: Truck | N4: AWD | P4: DEALER CONNECT
B5: 4 | C5: CHRIS MARTIN | E5: Y | I5: GM Fin LS | K5: 0.85 | L5: Chrysler | M5: Coupe | N5: 4x4 | P5: COX AUTO | R5: Jurso686 | T5: Blauto1200@$$
B6: 5 | C6: NICK WILEY | E6: Y | I6: KeyBank N.A. | K6: 0.8 | L6: Dodge | M6: Hatch | N6: 4x2 | P6: DL VINS | R6: Jurso02 | T6: Elgin222
B7: 6 | C7: HALEY DELUDE | E7: Y | G7: Team Leader | I7: Ally | K7: 0.75 | L7: Ford | M7: Van | P7: Dealer Policy
B8: 7 | C8: MIKE LASHLEY | E8: Y | I8: Mazda | K8: 0.65 | L8: Honda | M8: Other | P8: SECOND PENCIL
B9: 8 | C9: BRYANT ROGERS | E9: Y | I9: BOA | K9: 0.6 | L9: Hyundai | M9: Convertible
B10: 9 | C10: ABDUL AL TABBAH | E10: Y | I10: Gateway | K10: 0.55 | L10: Jeep | M10: Wagon
B11: 10 | C11: JOSE TORRES | E11: Y | I11: NBT | K11: 0.5 | L11: Kia | P11: KEYTRAK | R11: MIKE BRYANT | T11: 42144
B12: 11 | C12: IGOR PLETNOR | E12: Y | I12: Capital One | K12: 0.45 | L12: Lincoln
B13: 12 | C13: MAYCON MIKE GUIMARAES | E13: Y | G13: F&I Manager | I13: Huntington | K13: 0.4 | L13: Mazda | P13: AM1LEADS.COM | R13: F570 | T13: Nate777
B14: 13 | C14: OSSIE SAMPSON | E14: Y | G14: NATE LABRECQUE | I14: TD Auto | K14: 0.35 | L14: Mitsubishi | P14: JDE HQ
B15: 14 | C15: MAKOTO "TOKYO" MACHO | E15: Y | I15: HANSCOM FED | K15: 0.3 | L15: Nissan | P15: computer password | R15: Hyundai1200$
B16: 15 | C16: BRYAN ROGERS | E16: Y | I16: service cu | K16: 0.25 | L16: Pontiac
E17: Y | I17: CASH | K17: 0.2 | L17: Ram | P17: KEY TRACK ADMIN CODE | R17: jde | T17: 4321
G18: CLOSERS | I18: Wells Fargo | K18: 0.15 | L18: Subaru
G19: MICHAEL BARR | K19: 0.1 | L19: Toyota | P19: GAP | R19: 519
G21: MICHAEL BRYANT | K21: 0.05 | L21: VW | P21: Nate's BL Comp Login | R21: nlabrecque@blautogroup.com | T21: BLag2026$$
C24: HOUSE | G24: 4703324926 | L24: -----------
L25: Acura
C26: Dealer Information | I26: Financial Information | L26: Alfa Romeo | N26: $$ LOANED
C27: Sale Start Date | D27: 46069 | I27: Doc Fees. | L27: Aston Martin
C28: End Date | D28: 46074 | I28: TT&L | L28: Audi
C29: Dealer Name | D29: HONDA CITY | I29: Pack | J29: 0 | L29: Bentley
C30: Franchise | D30: HONDA | I30: JDE PAYOUT | J30: 0.35 | L30: BMW
C31: Street Address | D31: 4950 S PULASKI RD | I31: Tax rate | J31: 0.1025 | L31: Ferrari
C32: City | D32: CHICAGO | L32: Fiat
C33: State | D33: ILLINOIS | L33: Freightliner
C34: Zip | D34: 60632 | L34: Genesis
L35: Infiniti
C36: Marketing Information | I36: Dealership Production (Avg. Per Month) | L36: Jaguar
C37: Direct Mail Title | D37: WIN BIG | I37: Used Vehicle Units | L37: Lamborghini
C38: Direct Mail # | I38: New Vehicle Units | L38: Land Rover
C39: CAP Letter # | I39: Front Gross Per Unit | L39: Lexus | N39: LX, SPORT, EX, EX-L, TOURING, ELITE
C40: Total Sales Days | D40: 6 | I40: Back Gross Per Unit | L40: Lotus
C41: Mail Investment | I41: Marketing $ | L41: Maserati
I42: Traffic Per Day | L42: McLaren
I43: Total Gross Used Car | L43: Mercedes-Benz
C44: Commission Information | I44: Total Gross New Car | L44: Mini
C45: Team Leader % | D45: 0.3 | L45: Porsche
C46: Closer 1 % | D46: 0.2 | L46: Rolls-Royce
C47: Closer 2 % | D47: 0.2 | L47: Scion
C48: F&I % | L48: Smart
C49: Spec. Finc % | L49: Tesla
C50: Additional 1 % | L50: Volvo
I55: us patent #46589790

Sheet INVENTORY
A1: HAT | C1: STATUS | D1: Stock # | E1: Year | F1: Make | G1: Model | H1: Class | I1: Color | J1: Odometer | K1: VIN | L1: Series | M1: Age | N1: Drivetrain Type | O1: J.D. Power Trade In Clean | P1: J.D. Power Retail Clean | Q1: Unit Cost | R1: DIFF | S1: 1.15 | T1: 1.15 | U1: 1.2 | V1: 1.2 | W1: 1.25 | X1: 1.25 | Y1: 1.3 | Z1: 1.3
A2: 1 | B2: TRADE | D2: C20657A | E2: 2023 | F2: HONDA | G2: CR-V | H2: SUV | I2: RADIANT RED | J2: 46053 | K2: 7FARS6H5XPE033768 | L2: SPORT HYBRID | M2: 1 | N2: AWD | O2: 24175 | P2: 27675 | Q2: 20850 | R2: =O2-Q2 -> 3325 | S2: =O2*1.15 -> 27801.25 | T2: =S2-Q2 -> 6951.25 | U2: =O2*1.25 -> 30218.75 | V2: =U2-Q2 -> 9368.75 | W2: =O2*1.4 -> 33845 | X2: =W2-Q2 -> 12995 | Y2: =W2*0.0207 -> 700.5915 | Z2: =Y2-Q2 -> -20149.409 | AF2: =P2-Q2 -> 6825 | AH2: 40895 | AI2: 685
A3: 1 | B3: TRADE | D3: DC20851A | E3: 2018 | F3: HONDA | G3: CIVIC | H3: Sedan | I3: GRAY | J3: 32238 | K3: 2HGFC2F59JH577432 | L3: LX | M3: 1 | N3: FWD | O3: 14550 | P3: 17875 | Q3: 14350 | R3: =O3-Q3 -> 200 | S3: =O3*1.15 -> 16732.5 | T3: =S3-Q3 -> 2382.5 | U3: =O3*1.25 -> 18187.5 | V3: =U3-Q3 -> 3837.5 | W3: =O3*1.4 -> 20370 | X3: =W3-Q3 -> 6020 | Y3: =W3*0.0207 -> 421.659 | Z3: =Y3-Q3 -> -13928.341 | AF3: =P3-Q3 -> 3525 | AH3: 33148 | AI3: 685
A4: 1 | B4: TRADE | D4: C20976A | E4: 2024 | F4: KIA | G4: K5 | H4: Sedan | I4: WHITE | J4: 23982 | K4: 5XXG64J21RG246944 | L4: GT-LINE | M4: 2 | N4: FWD | O4: 23175 | P4: 26175 | Q4: 20000 | R4: =O4-Q4 -> 3175 | S4: =O4*1.15 -> 26651.25 | T4: =S4-Q4 -> 6651.25 | U4: =O4*1.25 -> 28968.75 | V4: =U4-Q4 -> 8968.75 | W4: =O4*1.4 -> 32445 | X4: =W4-Q4 -> 12445 | Y4: =W4*0.0207 -> 671.6115 | Z4: =Y4-Q4 -> -19328.389 | AF4: =P4-Q4 -> 6175 | AH4: 11930 | AI4: 685
A5: 1 | B5: TRADE | D5: C20798A | E5: 2014 | F5: TOYOTA | G5: HIGHLANDER | H5: SUV | I5: BLUE | J5: 113124 | K5: 5TDJKRFH7ES038748 | L5: XLE Premium | M5: 1 | N5: 4WD | O5: 13525 | P5: 15725 | Q5: 13350 | R5: =O5-Q5 -> 175 | S5: =O5*1.15 -> 15553.75 | T5: =S5-Q5 -> 2203.75 | U5: =O5*1.25 -> 16906.25 | V5: =U5-Q5 -> 3556.25 | W5: =O5*1.25 -> 16906.25 | X5: =W5-Q5 -> 3556.25 | Y5: =O5*1.3 -> 17582.5 | Z5: =Y5-Q5 -> 4232.5 | AF5: =P5-Q5 -> 2375 | AH5: 24795 | AI5: 685
A6: 1 | B6: TRADE | D6: DC20964B | E6: 2019 | F6: HONDA | G6: PASSPORT | H6: SUV | I6: WHITE | J6: 109541 | K6: 5FNYF8H50KB014422 | L6: EX-L | M6: 1 | N6: AWD | O6: 16050 | P6: 18250 | Q6: 12350 | R6: =O6-Q6 -> 3700
A7: 1 | B7: TRADE | D7: C20968A | E7: 2015 | F7: TOYOTA | G7: CAMRY | H7: Sedan | I7: SILVER | J7: 133865 | K7: 4T4BF1FK4FR466846 | L7: LE | M7: 1 | O7: 7750 | P7: 11700 | Q7: 6250 | R7: =O7-Q7 -> 1500
A8: 1 | B8: TRADE | D8: C20853A | E8: 2022 | F8: HONDA | G8: PILOT | H8: SUV | I8: GRAY | J8: 35540 | K8: 5FNYF6H83NB077078 | L8: TRAILSPORT | M8: 1 | N8: AWD | O8: 29350 | P8: 31075 | Q8: 29250 | R8: =O8-Q8 -> 100
A9: 1 | B9: TRADE | D9: C20673A | E9: 2012 | F9: FORD | G9: FUSION | H9: Sedan | I9: GRAY | J9: 66828 | K9: 3FAHP0JA4CR337318 | L9: SEL | M9: 1 | O9: 4688 | P9: 8363 | Q9: 3550 | R9: =O9-Q9 -> 1138
A10: 1 | B10: TRADE | D10: C20754A | E10: 2025 | F10: JEEP | G10: COMPASS | H10: SUV | I10: BLACK | J10: 4716 | K10: 3C4NJDBNXST528248 | L10: LAT | M10: 1 | N10: 4WD | O10: 22725 | P10: 29250 | Q10: 22250 | R10: =O10-Q10 -> 475
A11: 1 | B11: TRADE | D11: C20689A | E11: 2020 | F11: JEEP | G11: GRAND CHERO | H11: SUV | I11: BLACK | J11: 64473 | K11: 1C4RJFBG4LC255979 | L11: LIMITED | M11: 1 | N11: 4WD | O11: 18525 | P11: 21475 | Q11: 12250 | R11: =O11-Q11 -> 6275
A12: 1 | B12: TRADE | D12: C20976A | E12: 2024 | F12: KIA | G12: K5 | H12: Sedan | I12: WHITE | J12: 23982 | K12: 5XXG64J21RG246944 | L12: GT-LINE | M12: 1 | N12: FWD | O12: 23750 | P12: 26825 | Q12: 21350 | R12: =O12-Q12 -> 2400
A13: 2 | D13: P6234 | E13: 2023 | F13: Acura | G13: MDX | H13: SUV | I13: Black | J13: 40771 | K13: 5J8YE1H83PL014344 | L13: Advance | M13: 83 | N13: AWD | O13: 40850 | P13: 44575 | Q13: 40472 | R13: =O13-Q13 -> 378 | S13: =O13*1.15 -> 46977.5 | T13: =S13-Q13 -> 6505.5 | U13: =O13*1.25 -> 51062.5 | V13: =U13-Q13 -> 10590.5 | W13: =O13*1.25 -> 51062.5 | X13: =W13-Q13 -> 10590.5 | Y13: =O13*1.3 -> 53105 | Z13: =Y13-Q13 -> 12633
A14: 3 | D14: C20912A | E14: 2024 | F14: Acura | G14: Integra | H14: Sedan | I14: Gray | J14: 28823 | K14: 19UDE4H25RA027106 | L14: Base | M14: 8 | N14: FWD | O14: 21925 | P14: 26000 | Q14: 22229 | R14: =O14-Q14 -> -304 | S14: =O14*1.15 -> 25213.75 | T14: =S14-Q14 -> 2984.75 | U14: =O14*1.25 -> 27406.25 | V14: =U14-Q14 -> 5177.25 | W14: =O14*1.25 -> 27406.25 | X14: =W14-Q14 -> 5177.25 | Y14: =O14*1.3 -> 28502.5 | Z14: =Y14-Q14 -> 6273.5 | AH14: 15576 | AI14: 685
A15: 5 | D15: P6284 | E15: 2021 | F15: Honda | G15: Civic | H15: Sedan | I15: Silver | J15: 36102 | K15: 2HGFC2F67MH539193 | L15: LX | M15: 9 | N15: FWD | O15: 16325 | P15: 19175 | Q15: 19278 | R15: =O15-Q15 -> -2953 | S15: =O15*1.15 -> 18773.75 | T15: =S15-Q15 -> -504.25 | U15: =O15*1.25 -> 20406.25 | V15: =U15-Q15 -> 1128.25 | W15: =O15*1.25 -> 20406.25 | X15: =W15-Q15 -> 1128.25 | Y15: =O15*1.3 -> 21222.5 | Z15: =Y15-Q15 -> 1944.5 | AH15: 23802 | AI15: 685
A16: 6 | D16: C20520A | E16: 2021 | F16: Honda | G16: Passport | H16: SUV | I16: Platinum White | J16: 71769 | K16: 5FNYF8H08MB003790 | L16: Elite | M16: 8 | N16: AWD | O16: 25200 | P16: 27600 | Q16: 25751 | R16: =O16-Q16 -> -551 | T16: =S16-Q16 -> -25751 | V16: =U16-Q16 -> -25751 | X16: =W16-Q16 -> -25751 | Z16: =Y16-Q16 -> -25751
A17: 7 | D17: P6282 | E17: 2023 | F17: GMC | G17: Acadia | H17: SUV | I17: Volcanic Red Tintcoat | J17: 60970 | K17: 1GKKNUL43PZ234420 | L17: SLT | M17: 10 | N17: AWD | O17: 23200 | P17: 25500 | Q17: 24541 | R17: =O17-Q17 -> -1341 | S17: =O17*1.15 -> 26680 | T17: =S17-Q17 -> 2139 | U17: =O17*1.25 -> 29000 | V17: =U17-Q17 -> 4459 | W17: =O17*1.25 -> 29000 | X17: =W17-Q17 -> 4459 | Y17: =O17*1.3 -> 30160 | Z17: =Y17-Q17 -> 5619 | AF17: =P17-Q17 -> 959 | AH17: 33702 | AI17: 685
A18: 8 | D18: XP6289 | E18: 2022 | F18: Ford | G18: Escape | H18: SUV | I18: Agate Black Metallic | J18: 53251 | K18: 1FMCU0G63NUB97494 | L18: SE | M18: 3 | N18: FWD | O18: 14875 | P18: 18900 | Q18: 17343 | R18: =O18-Q18 -> -2468 | S18: =O18*1.15 -> 17106.25 | T18: =S18-Q18 -> -236.75 | U18: =O18*1.25 -> 18593.75 | V18: =U18-Q18 -> 1250.75 | W18: =O18*1.25 -> 18593.75 | X18: =W18-Q18 -> 1250.75 | Y18: =O18*1.3 -> 19337.5 | Z18: =Y18-Q18 -> 1994.5 | AH18: 9599 | AI18: 685
A19: 10 | D19: P6286 | E19: 2023 | F19: Honda | G19: HR-V | H19: Hatch | I19: Black | J19: 32113 | K19: 3CZRZ1H35PM709722 | L19: LX | M19: 9 | N19: FWD | O19: 19600 | P19: 21725 | Q19: 22313 | R19: =O19-Q19 -> -2713 | S19: =O19*1.15 -> 22540 | T19: =S19-Q19 -> 227 | U19: =O19*1.25 -> 24500 | V19: =U19-Q19 -> 2187 | W19: =O19*1.25 -> 24500 | X19: =W19-Q19 -> 2187 | Y19: =O19*1.3 -> 25480 | Z19: =Y19-Q19 -> 3167 | AF19: =P19-Q19 -> -588 | AH19: 23399 | AI19: 685
A20: 11 | D20: C20694A | E20: 2010 | F20: Honda | G20: CR-V | H20: SUV | I20: Silver | J20: 189287 | K20: JHLRE3H53AC005299 | L20: EX | M20: 55 | N20: FWD | O20: 4575 | P20: 6725 | Q20: 5993 | R20: =O20-Q20 -> -1418 | S20: =O20*1.15 -> 5261.25 | T20: =S20-Q20 -> -731.75 | U20: =O20*1.25 -> 5718.75 | V20: =U20-Q20 -> -274.25 | W20: =O20*1.25 -> 5718.75 | X20: =W20-Q20 -> -274.25 | Y20: =O20*1.3 -> 5947.5 | Z20: =Y20-Q20 -> -45.5 | AF20: =P20-Q20 -> 732 | AH20: 22898 | AI20: 685
A21: 12 | D21: P6268 | E21: 2024 | F21: Mazda | G21: Mazda3 | H21: Sedan | I21: Jet Black Mica | J21: 53095 | K21: JM1BPAKM5R1700968 | L21: 2.5 S Select Sport | M21: 33 | N21: FWD | O21: 16975 | P21: 20050 | Q21: 19275 | R21: =O21-Q21 -> -2300 | S21: =O21*1.15 -> 19521.25 | T21: =S21-Q21 -> 246.25 | U21: =O21*1.25 -> 21218.75 | V21: =U21-Q21 -> 1943.75 | W21: =O21*1.25 -> 21218.75 | X21: =W21-Q21 -> 1943.75 | Y21: =O21*1.3 -> 22067.5 | Z21: =Y21-Q21 -> 2792.5 | AH21: 33621 | AI21: 685
A22: 13 | D22: XP6248 | E22: 2024 | F22: Ford | G22: Escape | H22: SUV | I22: Gray Metallic | J22: 8482 | K22: 1FMCU9GN9RUB62427 | L22: Active | M22: 62 | N22: AWD | O22: 21200 | P22: 26075 | Q22: 25102 | R22: =O22-Q22 -> -3902 | S22: =O22*1.15 -> 24380 | T22: =S22-Q22 -> -722 | U22: =O22*1.25 -> 26500 | V22: =U22-Q22 -> 1398 | W22: =O22*1.25 -> 26500 | X22: =W22-Q22 -> 1398 | Y22: =O22*1.3 -> 27560 | Z22: =Y22-Q22 -> 2458 | AH22: 22049 | AI22: 685
A23: 14 | D23: C20485A | E23: 2024 | F23: Honda | G23: Civic Si | H23: Sedan | I23: Crystal Black Pearl | J23: 12037 | K23: 2HGFE1E53RH475240 | L23: Base | M23: 93 | N23: FWD | O23: 26600 | P23: 29475 | Q23: 30703 | R23: =O23-Q23 -> -4103 | S23: =O23*1.15 -> 30590 | T23: =S23-Q23 -> -113 | U23: =O23*1.25 -> 33250 | V23: =U23-Q23 -> 2547 | W23: =O23*1.25 -> 33250 | X23: =W23-Q23 -> 2547 | Y23: =O23*1.3 -> 34580 | Z23: =Y23-Q23 -> 3877 | AF23: =P23-Q23 -> -1228 | AH23: 31576 | AI23: 685
A24: 16 | D24: P6264 | E24: 2024 | F24: GMC | G24: Terrain | H24: SUV | I24: Ebony Twilight Metallic | J24: 45361 | K24: 3GKALTEGXRL372517 | L24: SLE | M24: 34 | N24: AWD | O24: 19800 | P24: 23500 | Q24: 22011 | R24: =O24-Q24 -> -2211 | S24: =O24*1.15 -> 22770 | T24: =S24-Q24 -> 759 | U24: =O24*1.25 -> 24750 | V24: =U24-Q24 -> 2739 | W24: =O24*1.4 -> 27720 | X24: =W24-Q24 -> 5709 | Y24: =W24*0.0207 -> 573.804 | Z24: =Y24-Q24 -> -21437.196 | AF24: =P24-Q24 -> 1489 | AH24: 32137 | AI24: 685
A25: 18 | D25: P6275 | E25: 2025 | F25: Mitsubishi | G25: Outlander | H25: SUV | I25: Black | J25: 17786 | K25: JA4J4VA83SZ032749 | L25: SE | M25: 19 | N25: 4WD | O25: 25600 | P25: 30500 | Q25: 27243 | R25: =O25-Q25 -> -1643 | S25: =O25*1.15 -> 29440 | T25: =S25-Q25 -> 2197 | U25: =O25*1.25 -> 32000 | V25: =U25-Q25 -> 4757 | W25: =O25*1.4 -> 35840 | X25: =W25-Q25 -> 8597 | Y25: =W25*0.0207 -> 741.888 | Z25: =Y25-Q25 -> -26501.112 | AF25: =P25-Q25 -> 3257 | AH25: 48869 | AI25: 685
A26: 20 | D26: P6227A | E26: 2015 | F26: Lincoln | G26: MKT | H26: SUV | I26: Ruby Red Metallic | J26: 101181 | K26: 2LMHJ5AT5FBL03014 | L26: EcoBoost | M26: 74 | N26: AWD | O26: 7575 | P26: 10550 | Q26: 7848 | R26: =O26-Q26 -> -273 | S26: =O26*1.15 -> 8711.25 | T26: =S26-Q26 -> 863.25 | U26: =O26*1.25 -> 9468.75 | V26: =U26-Q26 -> 1620.75 | W26: =O26*1.25 -> 9468.75 | X26: =W26-Q26 -> 1620.75 | Y26: =O26*1.3 -> 9847.5 | Z26: =Y26-Q26 -> 1999.5 | AH26: 15858 | AI26: 685
A27: 21 | D27: C20876A | E27: 2024 | F27: Honda | G27: HR-V | H27: Hatch | I27: Crystal Black Pearl | J27: 22362 | K27: 3CZRZ1H51RM730619 | L27: Sport | M27: 32 | N27: FWD | O27: 22025 | P27: 25850 | Q27: 23960 | R27: =O27-Q27 -> -1935 | S27: =O27*1.15 -> 25328.75 | T27: =S27-Q27 -> 1368.75 | U27: =O27*1.25 -> 27531.25 | V27: =U27-Q27 -> 3571.25 | W27: =O27*1.25 -> 27531.25 | X27: =W27-Q27 -> 3571.25 | Y27: =O27*1.3 -> 28632.5 | Z27: =Y27-Q27 -> 4672.5 | AH27: 25933 | AI27: 685
A28: 22 | D28: DC20644A | E28: 2019 | F28: Honda | G28: Insight | H28: SUV | I28: Crystal Black Pearl | J28: 145259 | K28: 19XZE4F97KE033674 | L28: Touring | M28: 60 | N28: FWD | O28: 10525 | P28: 15725 | Q28: 11078 | R28: =O28-Q28 -> -553 | S28: =O28*1.15 -> 12103.75 | T28: =S28-Q28 -> 1025.75 | U28: =O28*1.25 -> 13156.25 | V28: =U28-Q28 -> 2078.25 | W28: =O28*1.25 -> 13156.25 | X28: =W28-Q28 -> 2078.25 | Y28: =O28*1.3 -> 13682.5 | Z28: =Y28-Q28 -> 2604.5 | AH28: 27939 | AI28: 685
A29: 23 | D29: C20844A | E29: 2024 | F29: Honda | G29: Accord | H29: Sedan | I29: Gray Metallic | J29: 9006 | K29: 1HGCY1F28RA063666 | L29: LX | M29: 65 | N29: FWD | O29: 23425 | P29: 27600 | Q29: 23945 | R29: =O29-Q29 -> -520 | S29: =O29*1.15 -> 26938.75 | T29: =S29-Q29 -> 2993.75 | U29: =O29*1.25 -> 29281.25 | V29: =U29-Q29 -> 5336.25 | W29: =O29*1.25 -> 29281.25 | X29: =W29-Q29 -> 5336.25 | Y29: =O29*1.3 -> 30452.5 | Z29: =Y29-Q29 -> 6507.5 | AH29: 30441 | AI29: 685
A30: 24 | D30: P6255 | E30: 2023 | F30: Honda | G30: Odyssey | H30: Van | I30: Modern Steel Metallic | J30: 33823 | K30: 5FNRL6H68PB017117 | L30: EX-L | M30: 58 | N30: FWD | O30: 31175 | P30: 34050 | Q30: 32219 | R30: =O30-Q30 -> -1044 | S30: =O30*1.15 -> 35851.25 | T30: =S30-Q30 -> 3632.25 | U30: =O30*1.25 -> 38968.75 | V30: =U30-Q30 -> 6749.75 | W30: =O30*1.25 -> 38968.75 | X30: =W30-Q30 -> 6749.75 | Y30: =O30*1.3 -> 40527.5 | Z30: =Y30-Q30 -> 8308.5
A31: 25 | D31: RTC20458 | E31: 2025 | F31: Honda | G31: Accord | H31: Sedan | I31: Radiant Red Metallic | J31: 1010 | K31: 1HGCY1F40SA051227 | L31: SE | M31: 38 | N31: FWD | O31: 26175 | P31: 29050 | Q31: 28805 | R31: =O31-Q31 -> -2630 | S31: =O31*1.15 -> 30101.25 | T31: =S31-Q31 -> 1296.25 | U31: =O31*1.25 -> 32718.75 | V31: =U31-Q31 -> 3913.75 | W31: =O31*1.25 -> 32718.75 | X31: =W31-Q31 -> 3913.75 | Y31: =O31*1.3 -> 34027.5 | Z31: =Y31-Q31 -> 5222.5
A32: 25 | D32: P6261 | E32: 2020 | F32: Honda | G32: Civic | H32: Sedan | I32: Black | J32: 61463 | K32: 19XFC1F76LE212750 | L32: EX-L | M32: 37 | N32: FWD | O32: 17300 | P32: 20300 | Q32: 22730 | R32: =O32-Q32 -> -5430 | S32: =O32*1.15 -> 19895 | T32: =S32-Q32 -> -2835 | U32: =O32*1.25 -> 21625 | V32: =U32-Q32 -> -1105 | W32: =O32*1.25 -> 21625 | X32: =W32-Q32 -> -1105 | Y32: =O32*1.3 -> 22490 | Z32: =Y32-Q32 -> -240 | AF32: =P32-Q32 -> -2430 | AH32: 16144 | AI32: 685
A33: 27 | D33: DC20507A | E33: 2023 | F33: Honda | G33: Accord | H33: Sedan | I33: Lunar Silver Metallic | J33: 11732 | K33: 1HGCY1F31PA054863 | L33: EX | M33: 36 | N33: FWD | O33: 24200 | P33: 26925 | Q33: 25817 | R33: =O33-Q33 -> -1617 | S33: =O33*1.15 -> 27830 | T33: =S33-Q33 -> 2013 | U33: =O33*1.25 -> 30250 | V33: =U33-Q33 -> 4433 | W33: =O33*1.25 -> 30250 | X33: =W33-Q33 -> 4433 | Y33: =O33*1.3 -> 31460 | Z33: =Y33-Q33 -> 5643 | AH33: 21709 | AI33: 685
A34: 28 | D34: P6283 | E34: 2024 | F34: Honda | G34: CR-V | H34: SUV | I34: Black | J34: 59737 | K34: 2HKRS4H49RH475291 | L34: EX | M34: 9 | N34: AWD | O34: 25825 | P34: 28950 | Q34: 27270 | R34: =O34-Q34 -> -1445 | T34: =S34-Q34 -> -27270 | V34: =U34-Q34 -> -27270 | X34: =W34-Q34 -> -27270 | Z34: =Y34-Q34 -> -27270
A35: 29 | D35: C20878A | E35: 2015 | F35: Honda | G35: Accord | H35: Sedan | I35: Black | J35: 141213 | K35: 1HGCR2F35FA245137 | L35: LX | M35: 15 | N35: FWD | O35: 6450 | P35: 9500 | Q35: 8676 | R35: =O35-Q35 -> -2226 | S35: =O35*1.15 -> 7417.5 | T35: =S35-Q35 -> -1258.5 | U35: =O35*1.25 -> 8062.5 | V35: =U35-Q35 -> -613.5 | W35: =O35*1.4 -> 9030 | X35: =W35-Q35 -> 354 | Y35: =W35*0.0207 -> 186.921 | Z35: =Y35-Q35 -> -8489.079 | AF35: =P35-Q35 -> 824 | AH35: 16672 | AI35: 685
A36: 30 | D36: XP6258 | E36: 2024 | F36: Toyota | G36: Corolla | H36: Sedan | I36: Silver | J36: 31393 | K36: 5YFB4MDE6RP191601 | L36: LE | M36: 38 | N36: FWD | O36: 17775 | P36: 21175 | Q36: 20672 | R36: =O36-Q36 -> -2897 | S36: =O36*1.15 -> 20441.25 | T36: =S36-Q36 -> -230.75 | U36: =O36*1.25 -> 22218.75 | V36: =U36-Q36 -> 1546.75 | W36: =O36*1.25 -> 22218.75 | X36: =W36-Q36 -> 1546.75 | Y36: =O36*1.3 -> 23107.5 | Z36: =Y36-Q36 -> 2435.5 | AF36: =P36-Q36 -> 503 | AH36: 22527 | AI36: 685
A37: 31 | D37: C20752A | E37: 2025 | F37: Honda | G37: HR-V | H37: Hatch | I37: Modern Steel Metallic | J37: 10095 | K37: 3CZRZ1H34SM737312 | L37: LX | M37: 46 | N37: FWD | O37: 21925 | P37: 26075 | Q37: 22915 | R37: =O37-Q37 -> -990 | S37: =O37*1.15 -> 25213.75 | T37: =S37-Q37 -> 2298.75 | U37: =O37*1.25 -> 27406.25 | V37: =U37-Q37 -> 4491.25 | W37: =O37*1.25 -> 27406.25 | X37: =W37-Q37 -> 4491.25 | Y37: =O37*1.3 -> 28502.5 | Z37: =Y37-Q37 -> 5587.5 | AH37: 40654 | AI37: 685
A38: 32 | D38: P6252 | E38: 2019 | F38: Honda | G38: CR-V | H38: SUV | I38: Blue | J38: 61539 | K38: 7FARW1H83KE031144 | L38: EX-L | M38: 60 | N38: FWD | O38: 19475 | P38: 23350 | Q38: 20396 | R38: =O38-Q38 -> -921 | S38: =O38*1.15 -> 22396.25 | T38: =S38-Q38 -> 2000.25 | U38: =O38*1.25 -> 24343.75 | V38: =U38-Q38 -> 3947.75 | W38: =O38*1.25 -> 24343.75 | X38: =W38-Q38 -> 3947.75 | Y38: =O38*1.3 -> 25317.5 | Z38: =Y38-Q38 -> 4921.5
A39: 33 | D39: C20867A | E39: 2022 | F39: Honda | G39: Pilot | H39: SUV | I39: Obsidian Blue | J39: 34571 | K39: 5FNYF5H52NB009953 | L39: EX-L | M39: 59 | N39: FWD | O39: 27250 | P39: 28925 | Q39: 28286 | R39: =O39-Q39 -> -1036 | S39: =O39*1.15 -> 31337.5 | T39: =S39-Q39 -> 3051.5 | U39: =O39*1.25 -> 34062.5 | V39: =U39-Q39 -> 5776.5 | W39: =O39*1.25 -> 34062.5 | X39: =W39-Q39 -> 5776.5 | Y39: =O39*1.3 -> 35425 | Z39: =Y39-Q39 -> 7139 | AF39: =P39-Q39 -> 639 | AH39: 33610 | AI39: 685
A40: 34 | D40: P6267 | E40: 2023 | F40: Nissan | G40: Altima | H40: Sedan | I40: Super Black Clearcoat | J40: 59123 | K40: 1N4BL4CV4PN357702 | L40: 2.5 SR | M40: 34 | N40: FWD | O40: 17550 | P40: 20075 | Q40: 19712 | R40: =O40-Q40 -> -2162 | S40: =O40*1.15 -> 20182.5 | T40: =S40-Q40 -> 470.5 | U40: =O40*1.25 -> 21937.5 | V40: =U40-Q40 -> 2225.5 | W40: =O40*1.4 -> 24570 | X40: =W40-Q40 -> 4858 | Y40: =W40*0.0207 -> 508.599 | Z40: =Y40-Q40 -> -19203.401 | AH40: 15295 | AI40: 685
A41: 35 | D41: XP6246 | E41: 2022 | F41: Kia | G41: Seltos | H41: SUV | I41: Clear White/Black Roof | J41: 50972 | K41: KNDEUCAA9N7253643 | L41: S | M41: 62 | N41: AWD | O41: 15750 | P41: 18175 | Q41: 18733 | R41: =O41-Q41 -> -2983 | S41: =O41*1.15 -> 18112.5 | T41: =S41-Q41 -> -620.5 | U41: =O41*1.25 -> 19687.5 | V41: =U41-Q41 -> 954.5 | W41: =O41*1.25 -> 19687.5 | X41: =W41-Q41 -> 954.5 | Y41: =O41*1.3 -> 20475 | Z41: =Y41-Q41 -> 1742 | AF41: =P41-Q41 -> -558 | AH41: 22430 | AI41: 685
A42: 36 | D42: C20401A | E42: 2018 | F42: Ford | G42: Edge | H42: SUV | I42: Shadow Black | J42: 104652 | K42: 2FMPK4K96JBB80527 | L42: Titanium | M42: 36 | N42: AWD | O42: 7900 | P42: 10075 | Q42: 10024 | R42: =O42-Q42 -> -2124 | S42: =O42*1.15 -> 9085 | T42: =S42-Q42 -> -939 | U42: =O42*1.25 -> 9875 | V42: =U42-Q42 -> -149 | W42: =O42*1.25 -> 9875 | X42: =W42-Q42 -> -149 | Y42: =O42*1.3 -> 10270 | Z42: =Y42-Q42 -> 246 | AF42: =P42-Q42 -> 51 | AH42: 44982 | AI42: 685
A43: 37 | D43: XP6231 | E43: 2024 | F43: Toyota | G43: RAV4 | H43: SUV | I43: Blueprint | J43: 32240 | K43: 2T3A1RFV2RW437239 | L43: XLE Premium | M43: 96 | N43: AWD | O43: 30600 | P43: 36675 | Q43: 32292 | R43: =O43-Q43 -> -1692 | S43: =O43*1.15 -> 35190 | T43: =S43-Q43 -> 2898 | U43: =O43*1.25 -> 38250 | V43: =U43-Q43 -> 5958 | W43: =O43*1.4 -> 42840 | X43: =W43-Q43 -> 10548 | Y43: =W43*0.0207 -> 886.788 | Z43: =Y43-Q43 -> -31405.212 | AF43: =P43-Q43 -> 4383 | AH43: 28909 | AI43: 685
A44: 38 | D44: C20797A | E44: 2020 | F44: Honda | G44: Civic | H44: Sedan | I44: Platinum White Pearl | J44: 70684 | K44: 2HGFC2F63LH554918 | L44: LX | M44: 12 | N44: FWD | O44: 13850 | P44: 16600 | Q44: 14451 | R44: =O44-Q44 -> -601 | Z44: =Y44-Q44 -> -14451
A45: 39 | D45: P6273 | E45: 2025 | F45: Hyundai | G45: Kona | H45: SUV | I45: Atlas White | J45: 23861 | K45: KM8HBCAB0SU216937 | L45: SEL | M45: 19 | N45: AWD | O45: 20500 | P45: 24400 | Q45: 22238 | R45: =O45-Q45 -> -1738 | S45: =O45*1.15 -> 23575 | T45: =S45-Q45 -> 1337 | U45: =O45*1.25 -> 25625 | V45: =U45-Q45 -> 3387 | W45: =O45*1.25 -> 25625 | X45: =W45-Q45 -> 3387 | Y45: =O45*1.3 -> 26650 | Z45: =Y45-Q45 -> 4412 | AF45: =P45-Q45 -> 2162 | AH45: 20419 | AI45: 685
A46: 41 | D46: XP6249 | E46: 2023 | F46: Hyundai | G46: Tucson | H46: SUV | I46: Calypso Red | J46: 45338 | K46: 5NMJB3AE7PH262294 | L46: SEL | M46: 62 | N46: FWD | O46: 17900 | P46: 22175 | Q46: 21043 | R46: =O46-Q46 -> -3143 | S46: =O46*1.15 -> 20585 | T46: =S46-Q46 -> -458 | U46: =O46*1.25 -> 22375 | V46: =U46-Q46 -> 1332 | W46: =O46*1.25 -> 22375 | X46: =W46-Q46 -> 1332 | Y46: =O46*1.3 -> 23270 | Z46: =Y46-Q46 -> 2227 | AF46: =P46-Q46 -> 1132 | AH46: 20425 | AI46: 685
A47: 42 | D47: P6244 | E47: 2020 | F47: Honda | G47: Civic | H47: Sedan | I47: Gray | J47: 71313 | K47: 2HGFC1F3XLH681875 | L47: EX | M47: 65 | N47: FWD | O47: 16025 | P47: 19075 | Q47: 20471 | R47: =O47-Q47 -> -4446 | S47: =O47*1.15 -> 18428.75 | T47: =S47-Q47 -> -2042.25 | U47: =O47*1.25 -> 20031.25 | V47: =U47-Q47 -> -439.75 | W47: =O47*1.25 -> 20031.25 | X47: =W47-Q47 -> -439.75 | Y47: =O47*1.3 -> 20832.5 | Z47: =Y47-Q47 -> 361.5 | AH47: 24565 | AI47: 685
A48: 44 | D48: P6266 | E48: 2024 | F48: Honda | G48: Civic | H48: Sedan | I48: Crystal Black Pearl | J48: 47522 | K48: 2HGFE2F58RH548333 | L48: Sport | M48: 34 | N48: FWD | O48: 21075 | P48: 23575 | Q48: 24806 | R48: =O48-Q48 -> -3731 | S48: =O48*1.15 -> 24236.25 | T48: =S48-Q48 -> -569.75 | U48: =O48*1.25 -> 26343.75 | V48: =U48-Q48 -> 1537.75 | W48: =O48*1.4 -> 29505 | X48: =W48-Q48 -> 4699 | Y48: =W48*0.0207 -> 610.7535 | Z48: =Y48-Q48 -> -24195.247 | AF48: =P48-Q48 -> -1231 | AH48: 28873 | AI48: 685
A49: 45 | D49: P6281 | E49: 2020 | F49: Honda | G49: Civic | H49: Sedan | I49: Silver | J49: 71386 | K49: 19XFC1F74LE006648 | L49: EX-L | M49: 16 | N49: FWD | O49: 16675 | P49: 19675 | Q49: 21608 | R49: =O49-Q49 -> -4933 | S49: =O49*1.15 -> 19176.25 | T49: =S49-Q49 -> -2431.75 | U49: =O49*1.25 -> 20843.75 | V49: =U49-Q49 -> -764.25 | W49: =O49*1.4 -> 23345 | X49: =W49-Q49 -> 1737 | Y49: =W49*0.0207 -> 483.2415 | Z49: =Y49-Q49 -> -21124.758 | AH49: 47339 | AI49: 685
A50: 49 | D50: P6272 | E50: 2023 | F50: Kia | G50: Sorento | H50: SUV | I50: Sapphire Blue | J50: 60210 | K50: 5XYRL4LC4PG211430 | L50: S | M50: 19 | N50: FWD | O50: 20325 | P50: 22775 | Q50: 22788 | R50: =O50-Q50 -> -2463 | S50: =O50*1.15 -> 23373.75 | T50: =S50-Q50 -> 585.75 | U50: =O50*1.25 -> 25406.25 | V50: =U50-Q50 -> 2618.25 | W50: =O50*1.25 -> 25406.25 | X50: =W50-Q50 -> 2618.25 | Y50: =O50*1.3 -> 26422.5 | Z50: =Y50-Q50 -> 3634.5 | AF50: =P50-Q50 -> -13 | AH50: 29103 | AI50: 685
A51: 50 | D51: P6225A | E51: 2007 | F51: Ford | G51: Edge | H51: SUV | I51: Gray | J51: 94666 | K51: 2FMDK36CX7BB10055 | L51: SE | M51: 4 | N51: FWD | O51: 2338 | P51: 3788 | Q51: 750 | R51: =O51-Q51 -> 1588 | S51: =O51*1.15 -> 2688.7 | T51: =S51-Q51 -> 1938.7 | U51: =O51*1.25 -> 2922.5 | V51: =U51-Q51 -> 2172.5 | W51: =O51*1.4 -> 3273.2 | X51: =W51-Q51 -> 2523.2 | Y51: =W51*0.0207 -> 67.75524
A52: 51 | D52: C20886A | E52: 2020 | F52: Honda | G52: Civic | H52: Sedan | I52: Platinum White Pearl | J52: 81009 | K52: 19XFC1F39LE003984 | L52: EX | M52: 33 | N52: FWD | O52: 15475 | P52: 18525 | Q52: 16306 | R52: =O52-Q52 -> -831 | S52: =O52*1.15 -> 17796.25 | T52: =S52-Q52 -> 1490.25 | U52: =O52*1.25 -> 19343.75 | V52: =U52-Q52 -> 3037.75 | W52: =O52*1.25 -> 19343.75 | X52: =W52-Q52 -> 3037.75 | Y52: =O52*1.3 -> 20117.5 | Z52: =Y52-Q52 -> 3811.5
A53: 52 | D53: P6269 | E53: 2023 | F53: Honda | G53: Accord Hybrid | H53: Sedan | I53: Crystal Black Pearl | J53: 21765 | K53: 1HGCY2F87PA001814 | L53: Touring | M53: 26 | N53: FWD | O53: 29975 | P53: 33550 | Q53: 31272 | R53: =O53-Q53 -> -1297 | S53: =O53*1.15 -> 34471.25 | T53: =S53-Q53 -> 3199.25 | U53: =O53*1.25 -> 37468.75 | V53: =U53-Q53 -> 6196.75 | W53: =O53*1.25 -> 37468.75 | X53: =W53-Q53 -> 6196.75 | Y53: =O53*1.3 -> 38967.5 | Z53: =Y53-Q53 -> 7695.5 | AF53: =P53-Q53 -> 2278 | AH53: 21288 | AI53: 685
A54: 53 | D54: P6262 | E54: 2021 | F54: Honda | G54: Civic | H54: Sedan | I54: Blue | J54: 69305 | K54: 19XFC2F6XME000321 | L54: LX | M54: 37 | N54: FWD | O54: 14300 | P54: 17150 | Q54: 18043 | R54: =O54-Q54 -> -3743 | S54: =O54*1.15 -> 16445 | T54: =S54-Q54 -> -1598 | U54: =O54*1.25 -> 17875 | V54: =U54-Q54 -> -168 | W54: =O54*1.25 -> 17875 | X54: =W54-Q54 -> -168 | Y54: =O54*1.3 -> 18590 | Z54: =Y54-Q54 -> 547 | AF54: =P54-Q54 -> -893 | AH54: 33859 | AI54: 685
A55: 54 | D55: XP6257 | E55: 2023 | F55: Kia | G55: K5 | H55: Sedan | I55: Sapphire Blue | J55: 32944 | K55: 5XXG64J24PG173419 | L55: GT-Line | M55: 39 | N55: AWD | O55: 21950 | P55: 25100 | Q55: 26097 | R55: =O55-Q55 -> -4147 | S55: =O55*1.15 -> 25242.5 | T55: =S55-Q55 -> -854.5 | U55: =O55*1.25 -> 27437.5 | V55: =U55-Q55 -> 1340.5 | W55: =O55*1.25 -> 27437.5 | X55: =W55-Q55 -> 1340.5 | Y55: =O55*1.3 -> 28535 | Z55: =Y55-Q55 -> 2438 | AH55: 21617 | AI55: 685
A56: 56 | D56: C20924A | E56: 2016 | F56: Honda | G56: Odyssey | H56: Van | I56: Black | J56: 117152 | K56: 5FNRL5H47GB074191 | L56: EX | M56: 1 | N56: FWD | O56: - | P56: - | Q56: 5000 | R56: =O56-Q56 -> #VALUE! | S56: =O56*1.15 -> #VALUE! | T56: =S56-Q56 -> #VALUE! | U56: =O56*1.25 -> #VALUE! | V56: =U56-Q56 -> #VALUE! | W56: =O56*1.25 -> #VALUE! | X56: =W56-Q56 -> #VALUE! | Y56: =O56*1.3 -> #VALUE! | Z56: =Y56-Q56 -> #VALUE! | AF56: =P56-Q56 -> #VALUE! | AH56: 32815 | AI56: 685
A57: 57 | D57: C20518A | E57: 2023 | F57: Honda | G57: HR-V | H57: Hatch | I57: Crystal Black Pearl | J57: 27421 | K57: 3CZRZ2H3XPM724660 | L57: LX | M57: 79 | N57: AWD | O57: 20850 | P57: 23700 | Q57: 23619 | R57: =O57-Q57 -> -2769 | S57: =O57*1.15 -> 23977.5 | T57: =S57-Q57 -> 358.5 | U57: =O57*1.25 -> 26062.5 | V57: =U57-Q57 -> 2443.5 | W57: =O57*1.25 -> 26062.5 | X57: =W57-Q57 -> 2443.5 | Y57: =O57*1.3 -> 27105 | Z57: =Y57-Q57 -> 3486 | AH57: 25390 | AI57: 685
A58: 58 | D58: P6274 | E58: 2023 | F58: Nissan | G58: Murano | H58: SUV | I58: Super Black | J58: 55956 | K58: 5N1AZ2BJ9PC133002 | L58: SV | M58: 19 | N58: FWD | O58: 19400 | P58: 20925 | Q58: 21640 | R58: =O58-Q58 -> -2240 | S58: =O58*1.15 -> 22310 | T58: =S58-Q58 -> 670 | U58: =O58*1.25 -> 24250 | V58: =U58-Q58 -> 2610 | W58: =O58*1.25 -> 24250 | X58: =W58-Q58 -> 2610 | Y58: =O58*1.3 -> 25220 | Z58: =Y58-Q58 -> 3580 | AH58: 23273 | AI58: 685
A59: 59 | D59: P6277 | E59: 2023 | F59: Nissan | G59: Rogue | H59: SUV | I59: Caspian Blue Metallic | J59: 63650 | K59: 5N1BT3AA4PC755861 | L59: S | M59: 18 | N59: FWD | O59: 15175 | P59: 18550 | Q59: 18083 | R59: =O59-Q59 -> -2908 | S59: =O59*1.15 -> 17451.25 | T59: =S59-Q59 -> -631.75 | U59: =O59*1.25 -> 18968.75 | V59: =U59-Q59 -> 885.75 | W59: =O59*1.4 -> 21245 | X59: =W59-Q59 -> 3162 | Y59: =W59*0.0207 -> 439.7715 | Z59: =Y59-Q59 -> -17643.229 | AF59: =P59-Q59 -> 467 | AH59: 11034 | AI59: 685
A60: 60 | D60: C20597A | E60: 2017 | F60: Honda | G60: HR-V | H60: Hatch | I60: Blue | J60: 141068 | K60: 3CZRU6H54HG705660 | L60: EX | M60: 61 | N60: AWD | O60: 9750 | P60: 11375 | Q60: 12290 | R60: =O60-Q60 -> -2540 | S60: =O60*1.15 -> 11212.5 | T60: =S60-Q60 -> -1077.5 | U60: =O60*1.25 -> 12187.5 | V60: =U60-Q60 -> -102.5 | W60: =O60*1.25 -> 12187.5 | X60: =W60-Q60 -> -102.5 | Y60: =O60*1.3 -> 12675 | Z60: =Y60-Q60 -> 385
A61: 61 | D61: C20049A | E61: 2024 | F61: Toyota | G61: Corolla | H61: Sedan | I61: Silver | J61: 14869 | K61: 5YFB4MDE9RP226244 | L61: LE | M61: 29 | N61: FWD | O61: 19075 | P61: 22475 | Q61: 20261 | R61: =O61-Q61 -> -1186 | S61: =O61*1.15 -> 21936.25 | T61: =S61-Q61 -> 1675.25 | U61: =O61*1.25 -> 23843.75 | V61: =U61-Q61 -> 3582.75 | W61: =O61*1.25 -> 23843.75 | X61: =W61-Q61 -> 3582.75 | Y61: =O61*1.3 -> 24797.5 | Z61: =Y61-Q61 -> 4536.5
A62: 62 | D62: C20825A | E62: 2023 | F62: Kia | G62: Seltos | H62: Sedan | I62: Cherry Black | J62: 63008 | K62: KNDERCAAXP7436957 | L62: EX | M62: 33 | N62: AWD | O62: 17475 | P62: 20550 | Q62: 19197 | R62: =O62-Q62 -> -1722 | S62: =O62*1.15 -> 20096.25 | T62: =S62-Q62 -> 899.25 | U62: =O62*1.25 -> 21843.75 | V62: =U62-Q62 -> 2646.75 | W62: =O62*1.25 -> 21843.75 | X62: =W62-Q62 -> 2646.75 | Y62: =O62*1.3 -> 22717.5 | Z62: =Y62-Q62 -> 3520.5
A63: 63 | D63: C20610A | E63: 2023 | F63: Honda | G63: Accord | H63: Sedan | I63: Crystal Black Pearl | J63: 54384 | K63: 1HGCY1F36PA006386 | L63: EX | M63: 54 | N63: FWD | O63: 21125 | P63: 23850 | Q63: 22639 | R63: =O63-Q63 -> -1514 | S63: =O63*1.15 -> 24293.75 | T63: =S63-Q63 -> 1654.75 | U63: =O63*1.25 -> 26406.25 | V63: =U63-Q63 -> 3767.25 | W63: =O63*1.25 -> 26406.25 | X63: =W63-Q63 -> 3767.25 | Y63: =O63*1.3 -> 27462.5 | Z63: =Y63-Q63 -> 4823.5 | AH63: 17936 | AI63: 685
A64: 64 | D64: P6183 | E64: 2024 | F64: Audi | G64: A5 Sportback | H64: Sedan | I64: Black | J64: 42641 | K64: WAUFACF56RA008586 | L64: 45 S line Premium Plus | M64: 159 | N64: AWD | O64: 35425 | P64: 39875 | Q64: 29755 | R64: =O64-Q64 -> 5670 | S64: =O64*1.15 -> 40738.75 | T64: =S64-Q64 -> 10983.75 | U64: =O64*1.25 -> 44281.25 | V64: =U64-Q64 -> 14526.25 | W64: =O64*1.25 -> 44281.25 | X64: =W64-Q64 -> 14526.25 | Y64: =O64*1.3 -> 46052.5 | Z64: =Y64-Q64 -> 16297.5 | AH64: 41187 | AI64: 685
A65: 65 | D65: C20809A | E65: 2025 | F65: Honda | G65: Civic | H65: Sedan | I65: Meteorite Gray Metallic | J65: 22578 | K65: 2HGFE2F2XSH558177 | L65: LX | M65: 11 | N65: FWD | O65: 21375 | P65: 23600 | Q65: 24324 | R65: =O65-Q65 -> -2949 | S65: =O65*1.15 -> 24581.25 | T65: =S65-Q65 -> 257.25 | U65: =O65*1.25 -> 26718.75 | V65: =U65-Q65 -> 2394.75 | W65: =O65*1.25 -> 26718.75 | X65: =W65-Q65 -> 2394.75 | Y65: =O65*1.3 -> 27787.5 | Z65: =Y65-Q65 -> 3463.5 | AH65: 21233 | AI65: 685
A66: 66 | D66: C20522A | E66: 2024 | F66: Honda | G66: HR-V | H66: Hatch | I66: Urban Gray Pearl | J66: 18118 | K66: 3CZRZ1H53RM749348 | L66: Sport | M66: 78 | N66: FWD | O66: 22325 | P66: 26150 | Q66: 25010 | R66: =O66-Q66 -> -2685 | S66: =O66*1.15 -> 25673.75 | T66: =S66-Q66 -> 663.75 | U66: =O66*1.25 -> 27906.25 | V66: =U66-Q66 -> 2896.25 | W66: =O66*1.25 -> 27906.25 | X66: =W66-Q66 -> 2896.25 | Y66: =O66*1.3 -> 29022.5 | Z66: =Y66-Q66 -> 4012.5 | AH66: 22255 | AI66: 685
A67: 67 | D67: C20891A | E67: 2023 | F67: Honda | G67: HR-V | H67: Hatch | I67: Modern Steel Metallic | J67: 43085 | K67: 3CZRZ2H71PM729605 | L67: EX-L | M67: 29 | N67: AWD | O67: 22950 | P67: 25725 | Q67: 24534 | R67: =O67-Q67 -> -1584 | S67: =O67*1.15 -> 26392.5 | T67: =S67-Q67 -> 1858.5 | U67: =O67*1.25 -> 28687.5 | V67: =U67-Q67 -> 4153.5 | W67: =O67*1.25 -> 28687.5 | X67: =W67-Q67 -> 4153.5 | Y67: =O67*1.3 -> 29835 | Z67: =Y67-Q67 -> 5301 | AF67: =P67-Q67 -> 1191 | AH67: 34186 | AI67: 685
A68: 68 | D68: P6285 | E68: 2019 | F68: Honda | G68: Passport | H68: SUV | I68: White | J68: 81753 | K68: 5FNYF8H92KB010939 | L68: Touring | M68: 9 | N68: AWD | O68: 19275 | P68: 21825 | Q68: 21553 | R68: =O68-Q68 -> -2278 | S68: =O68*1.15 -> 22166.25 | T68: =S68-Q68 -> 613.25 | U68: =O68*1.25 -> 24093.75 | V68: =U68-Q68 -> 2540.75 | W68: =O68*1.25 -> 24093.75 | X68: =W68-Q68 -> 2540.75 | Y68: =O68*1.3 -> 25057.5 | Z68: =Y68-Q68 -> 3504.5 | AH68: 20959 | AI68: 685
A69: 69 | D69: DC20599A | E69: 2023 | F69: Honda | G69: Pilot | H69: SUV | I69: Gray | J69: 40192 | K69: 5FNYG1H52PB034652 | L69: EX-L | M69: 50 | N69: AWD | O69: 32125 | P69: 35575 | Q69: 32739 | R69: =O69-Q69 -> -614 | S69: =O69*1.15 -> 36943.75 | T69: =S69-Q69 -> 4204.75 | U69: =O69*1.25 -> 40156.25 | V69: =U69-Q69 -> 7417.25 | W69: =O69*1.25 -> 40156.25 | X69: =W69-Q69 -> 7417.25 | Y69: =O69*1.3 -> 41762.5 | Z69: =Y69-Q69 -> 9023.5 | AF69: =P69-Q69 -> 2836 | AH69: 37875 | AI69: 685
A70: 70 | D70: C20167A | E70: 2024 | F70: Honda | G70: Pilot | H70: SUV | I70: Sonic Gray Pearl | J70: 11715 | K70: 5FNYG1H81RB014146 | L70: Elite | M70: 22 | N70: AWD | O70: 42725 | P70: 45775 | Q70: 45484 | R70: =O70-Q70 -> -2759 | S70: =O70*1.15 -> 49133.75 | T70: =S70-Q70 -> 3649.75 | U70: =O70*1.25 -> 53406.25 | V70: =U70-Q70 -> 7922.25 | W70: =O70*1.25 -> 53406.25 | X70: =W70-Q70 -> 7922.25 | Y70: =O70*1.3 -> 55542.5 | Z70: =Y70-Q70 -> 10058.5 | AF70: =P70-Q70 -> 291 | AH70: 25285 | AI70: 685
A71: 71 | C71: B LOT | D71: C20555A | E71: 2023 | F71: Honda | G71: Ridgeline | H71: Truck | I71: Radiant Red Metallic II | J71: 25703 | K71: 5FPYK3F10PB049992 | L71: Sport | M71: 83 | N71: AWD | O71: 27600 | P71: 32550 | Q71: 29501 | R71: =O71-Q71 -> -1901 | S71: =O71*1.15 -> 31740 | T71: =S71-Q71 -> 2239 | U71: =O71*1.25 -> 34500 | V71: =U71-Q71 -> 4999 | W71: =O71*1.25 -> 34500 | X71: =W71-Q71 -> 4999 | Y71: =O71*1.3 -> 35880 | Z71: =Y71-Q71 -> 6379 | AF71: =P71-Q71 -> 3049 | AH71: 23378 | AI71: 685
A72: 72 | C72: B LOT | D72: C20707A | E72: 2020 | F72: Honda | G72: CR-V | H72: SUV | I72: Radiant Red Metallic | J72: 46433 | K72: 5J6RW2H2XLL004156 | L72: LX | M72: 25 | N72: AWD | O72: 18425 | P72: 21750 | Q72: 20853 | R72: =O72-Q72 -> -2428 | S72: =O72*1.15 -> 21188.75 | T72: =S72-Q72 -> 335.75 | U72: =O72*1.25 -> 23031.25 | V72: =U72-Q72 -> 2178.25 | W72: =O72*1.25 -> 23031.25 | X72: =W72-Q72 -> 2178.25 | Y72: =O72*1.3 -> 23952.5 | Z72: =Y72-Q72 -> 3099.5
A73: 73 | C73: B LOT | D73: C20681A | E73: 2024 | F73: Honda | G73: CR-V Hybrid | H73: SUV | I73: Gray | J73: 84668 | K73: 7FARS6H59RE025826 | L73: Sport | M73: 18 | N73: AWD | O73: 25775 | P73: 29400 | Q73: 26113 | R73: =O73-Q73 -> -338 | S73: =O73*1.15 -> 29641.25 | T73: =S73-Q73 -> 3528.25 | U73: =O73*1.25 -> 32218.75 | V73: =U73-Q73 -> 6105.75 | W73: =O73*1.25 -> 32218.75 | X73: =W73-Q73 -> 6105.75 | Y73: =O73*1.3 -> 33507.5 | Z73: =Y73-Q73 -> 7394.5 | AF73: =P73-Q73 -> 3287 | AH73: 22126 | AI73: 685
A74: 74 | C74: B LOT | D74: P6253 | E74: 2023 | F74: Honda | G74: Odyssey | H74: Van | I74: White | J74: 14660 | K74: 5FNRL6H91PB026705 | L74: Elite | M74: 58 | N74: FWD | O74: 37825 | P74: 40900 | Q74: 41559 | R74: =O74-Q74 -> -3734 | S74: =O74*1.15 -> 43498.75 | T74: =S74-Q74 -> 1939.75 | U74: =O74*1.25 -> 47281.25 | V74: =U74-Q74 -> 5722.25 | W74: =O74*1.25 -> 47281.25 | X74: =W74-Q74 -> 5722.25 | Y74: =O74*1.3 -> 49172.5 | Z74: =Y74-Q74 -> 7613.5 | AH74: 19255 | AI74: 685
A75: 75 | C75: B LOT | D75: C20856A | E75: 2012 | F75: Honda | G75: Accord | H75: Sedan | I75: Black | J75: 139583 | K75: 1HGCP3F81CA014643 | L75: EX-L | M75: 47 | N75: FWD | O75: 6525 | P75: 9700 | Q75: 6606 | R75: =O75-Q75 -> -81 | S75: =O75*1.15 -> 7503.75 | T75: =S75-Q75 -> 897.75 | U75: =O75*1.25 -> 8156.25 | V75: =U75-Q75 -> 1550.25 | W75: =O75*1.25 -> 8156.25 | X75: =W75-Q75 -> 1550.25 | Y75: =O75*1.3 -> 8482.5 | Z75: =Y75-Q75 -> 1876.5 | AF75: =P75-Q75 -> 3094 | AH75: 15866 | AI75: 685
A76: 76 | D76: P6287 | E76: 2024 | F76: Honda | G76: HR-V | H76: Hatch | I76: White | J76: 34283 | K76: 3CZRZ2H37RM715904 | L76: LX | M76: 9 | N76: AWD | O76: 20975 | P76: 24650 | Q76: 23218 | R76: =O76-Q76 -> -2243 | S76: =O76*1.15 -> 24121.25 | T76: =S76-Q76 -> 903.25 | U76: =O76*1.25 -> 26218.75 | V76: =U76-Q76 -> 3000.75 | W76: =O76*1.25 -> 26218.75 | X76: =W76-Q76 -> 3000.75 | Y76: =O76*1.3 -> 27267.5 | Z76: =Y76-Q76 -> 4049.5 | AF76: =P76-Q76 -> 1432 | AH76: 24007 | AI76: 685
A77: 77 | D77: P6232 | E77: 2023 | F77: Toyota | G77: Corolla | H77: Sedan | I77: White | J77: 59520 | K77: 5YFB4MDE8PP003111 | L77: LE | M77: 93 | N77: FWD | O77: 16175 | P77: 18850 | Q77: 19259 | R77: =O77-Q77 -> -3084 | S77: =O77*1.15 -> 18601.25 | T77: =S77-Q77 -> -657.75 | U77: =O77*1.25 -> 20218.75 | V77: =U77-Q77 -> 959.75 | W77: =O77*1.25 -> 20218.75 | X77: =W77-Q77 -> 959.75 | Y77: =O77*1.3 -> 21027.5 | Z77: =Y77-Q77 -> 1768.5 | AF77: =P77-Q77 -> -409 | AH77: 25101 | AI77: 685
A78: 78 | D78: P6263 | E78: 2019 | F78: Honda | G78: Pilot | H78: SUV | I78: Gray | J78: 74562 | K78: 5FNYF6H54KB082176 | L78: EX-L | M78: 37 | N78: AWD | O78: 18150 | P78: 20325 | Q78: 24206 | R78: =O78-Q78 -> -6056 | S78: =O78*1.15 -> 20872.5 | T78: =S78-Q78 -> -3333.5 | U78: =O78*1.25 -> 22687.5 | V78: =U78-Q78 -> -1518.5 | W78: =O78*1.25 -> 22687.5 | X78: =W78-Q78 -> -1518.5 | Y78: =O78*1.3 -> 23595 | Z78: =Y78-Q78 -> -611 | AF78: =P78-Q78 -> -3881 | AH78: 33714 | AI78: 685
A79: 79 | D79: C20618A | E79: 2024 | F79: Honda | G79: Prologue | H79: Hatch | I79: White | J79: 7162 | K79: 3GPKHZRJ6RS514957 | L79: Elite | M79: 17 | N79: AWD | O79: 26675 | P79: 29925 | Q79: 27046 | R79: =O79-Q79 -> -371 | S79: =O79*1.15 -> 30676.25 | T79: =S79-Q79 -> 3630.25 | U79: =O79*1.25 -> 33343.75 | V79: =U79-Q79 -> 6297.75 | W79: =O79*1.25 -> 33343.75 | X79: =W79-Q79 -> 6297.75 | Y79: =O79*1.3 -> 34677.5 | Z79: =Y79-Q79 -> 7631.5 | AF79: =P79-Q79 -> 2879 | AH79: 23879 | AI79: 685
A80: 200 | B80: WS LOT | D80: C20573A | E80: 2023 | F80: Honda | G80: Pilot | H80: SUV | I80: Crystal Black Pearl | J80: 10390 | K80: 5FNYG2H41PB014325 | L80: EX-L | M80: 36 | N80: FWD | O80: 32600 | P80: 35875 | Q80: 36950 | R80: =O80-Q80 -> -4350 | S80: =O80*1.15 -> 37490 | T80: =S80-Q80 -> 540 | U80: =O80*1.25 -> 40750 | V80: =U80-Q80 -> 3800 | W80: =O80*1.25 -> 40750 | X80: =W80-Q80 -> 3800 | Y80: =O80*1.3 -> 42380 | Z80: =Y80-Q80 -> 5430 | AH80: 23221 | AI80: 685
A81: 200 | B81: OVERFLOW | D81: C20880A | E81: 2023 | F81: Honda | G81: CR-V | H81: SUV | I81: Crystal Black Pearl | J81: 15237 | K81: 7FARS4H73PE014114 | L81: EX-L | M81: 37 | N81: AWD | O81: 29100 | P81: 32125 | Q81: 30434 | R81: =O81-Q81 -> -1334 | S81: =O81*1.15 -> 33465 | T81: =S81-Q81 -> 3031 | U81: =O81*1.25 -> 36375 | V81: =U81-Q81 -> 5941 | W81: =O81*1.25 -> 36375 | X81: =W81-Q81 -> 5941 | Y81: =O81*1.3 -> 37830 | Z81: =Y81-Q81 -> 7396 | AF81: =P81-Q81 -> 1691 | AH81: 18606 | AI81: 685
A82: 200 | B82: OVERFLOW | D82: P6242 | E82: 2024 | F82: Toyota | G82: Camry | H82: Sedan | I82: Black | J82: 66427 | K82: 4T1G11AK9RU193140 | L82: SE | M82: 72 | N82: FWD | O82: 20650 | P82: 23550 | Q82: 23099 | R82: =O82-Q82 -> -2449 | S82: =O82*1.15 -> 23747.5 | T82: =S82-Q82 -> 648.5 | U82: =O82*1.25 -> 25812.5 | V82: =U82-Q82 -> 2713.5 | W82: =O82*1.25 -> 25812.5 | X82: =W82-Q82 -> 2713.5 | Y82: =O82*1.3 -> 26845 | Z82: =Y82-Q82 -> 3746 | AH82: 25772 | AI82: 685
A83: 2047 | C83: SOLD | D83: C20540A | E83: 2022 | F83: Honda | G83: HR-V | H83: Hatch | I83: Midnight Amethyst | J83: 25701 | K83: 3CZRU6H77NM705778 | L83: EX-L | M83: 61 | N83: AWD | O83: 21575 | P83: 24175 | Q83: 21072 | R83: =O83-Q83 -> 503 | S83: =O83*1.15 -> 24811.25 | T83: =S83-Q83 -> 3739.25 | U83: =O83*1.25 -> 26968.75 | V83: =U83-Q83 -> 5896.75 | W83: =O83*1.25 -> 26968.75 | X83: =W83-Q83 -> 5896.75 | Y83: =O83*1.3 -> 28047.5 | Z83: =Y83-Q83 -> 6975.5 | AH83: 30172 | AI83: 685
A84: 5001 | C84: SOLD | D84: C20630A | E84: 2021 | F84: Mazda | G84: CX-5 | H84: SUV | I84: Soul Red Crystal Metallic | J84: 80482 | K84: JM3KFBCM3M1336427 | L84: Touring | M84: 46 | N84: AWD | O84: 16575 | P84: 19225 | Q84: 15264 | R84: =O84-Q84 -> 1311 | S84: =O84*1.15 -> 19061.25 | T84: =S84-Q84 -> 3797.25 | U84: =O84*1.25 -> 20718.75 | V84: =U84-Q84 -> 5454.75 | W84: =O84*1.25 -> 20718.75 | X84: =W84-Q84 -> 5454.75 | Y84: =O84*1.3 -> 21547.5 | Z84: =Y84-Q84 -> 6283.5
A85: 5009 | C85: SOLD | D85: XP6290 | E85: 2021 | F85: Hyundai | G85: Tucson | H85: SUV | I85: Dusk Blue | J85: 40763 | K85: KM8J3CAL6MU363029 | L85: Sport | M85: 3 | N85: AWD | O85: 17825 | P85: 22900 | Q85: 18893 | R85: =O85-Q85 -> -1068 | S85: =O85*1.15 -> 20498.75 | T85: =S85-Q85 -> 1605.75 | U85: =O85*1.25 -> 22281.25 | V85: =U85-Q85 -> 3388.25 | W85: =O85*1.4 -> 24955 | X85: =W85-Q85 -> 6062 | Y85: =W85*0.0207 -> 516.5685 | Z85: =Y85-Q85 -> -18376.431 | AF85: =P85-Q85 -> 4007 | AH85: 14786 | AI85: 685
A86: 5015 | C86: sold | D86: C20931A | E86: 2025 | F86: Honda | G86: HR-V | H86: SUV | I86: R-548p | J86: 14618 | K86: 3CZRZ2H58SM739345 | L86: Sport | M86: 5 | N86: AWD | O86: 24850 | P86: 29300 | Q86: 24677 | R86: =O86-Q86 -> 173 | S86: =O86*1.15 -> 28577.5 | T86: =S86-Q86 -> 3900.5 | U86: =O86*1.25 -> 31062.5 | V86: =U86-Q86 -> 6385.5 | W86: =O86*1.4 -> 34790 | X86: =W86-Q86 -> 10113 | Y86: =W86*0.0207 -> 720.153 | Z86: =Y86-Q86 -> -23956.847 | AF86: =P86-Q86 -> 4623 | AH86: 18425 | AI86: 685
A87: 5017 | C87: SOLD | D87: C20237A | E87: 2023 | F87: Subaru | G87: Outback | H87: SUV | I87: Crystal Black Silica | J87: 51826 | K87: 4S4BTGUD2P3144613 | L87: Wilderness | M87: 85 | N87: AWD | O87: 25450 | P87: 28450 | Q87: 25966 | R87: =O87-Q87 -> -516 | S87: =O87*1.15 -> 29267.5 | T87: =S87-Q87 -> 3301.5 | U87: =O87*1.25 -> 31812.5 | V87: =U87-Q87 -> 5846.5 | W87: =O87*1.25 -> 31812.5 | X87: =W87-Q87 -> 5846.5 | Y87: =O87*1.3 -> 33085 | Z87: =Y87-Q87 -> 7119 | AH87: 11329 | AI87: 685
A88: 5019 | C88: SOLD | D88: C20654A | E88: 2022 | F88: Chevrolet | G88: Silverado 1500 LTD | H88: Truck | I88: Shadow Gray Metallic | J88: 19329 | K88: 1GCPYFEL1NZ209151 | L88: LT Trail Boss | M88: 88 | N88: 4WD | O88: 41650 | P88: 49350 | Q88: 39338 | R88: =O88-Q88 -> 2312 | S88: =O88*1.15 -> 47897.5 | T88: =S88-Q88 -> 8559.5 | U88: =O88*1.2 -> 49980 | V88: =U88-Q88 -> 10642 | W88: =O88*1.25 -> 52062.5 | X88: =W88-Q88 -> 12724.5 | Y88: =O88*1.3 -> 54145 | Z88: =Y88-Q88 -> 14807
A89: 5043 | B89: SOLD | C89: SOLD | D89: P6256 | E89: 2022 | F89: Honda | G89: Pilot | H89: SUV | I89: Crystal Black Pearl | J89: 35750 | K89: 5FNYF6H66NB083942 | L89: Touring | M89: 41 | N89: AWD | O89: 30675 | P89: 32450 | Q89: 33154 | R89: =O89-Q89 -> -2479 | S89: =O89*1.15 -> 35276.25 | T89: =S89-Q89 -> 2122.25 | U89: =O89*1.25 -> 38343.75 | V89: =U89-Q89 -> 5189.75 | W89: =O89*1.25 -> 38343.75 | X89: =W89-Q89 -> 5189.75 | Y89: =O89*1.3 -> 39877.5 | Z89: =Y89-Q89 -> 6723.5 | AF89: =P89-Q89 -> -704 | AH89: 19845 | AI89: 685
A90: 5048 | C90: SOLD | D90: P6239 | E90: 2022 | F90: Honda | G90: Civic | H90: Sedan | I90: Boost Blue Pearl | J90: 20051 | K90: 19XFL2H84NE018054 | L90: Sport | M90: 74 | N90: FWD | O90: 21600 | P90: 24725 | Q90: 23627 | R90: =O90-Q90 -> -2027 | S90: =O90*1.15 -> 24840 | T90: =S90-Q90 -> 1213 | U90: =O90*1.25 -> 27000 | V90: =U90-Q90 -> 3373 | W90: =O90*1.25 -> 27000 | X90: =W90-Q90 -> 3373 | Y90: =O90*1.3 -> 28080 | Z90: =Y90-Q90 -> 4453 | AH90: 17999 | AI90: 685
D91: P6185 | E91: 2024 | F91: Honda | G91: Odyssey | H91: Van | I91: Black | J91: 60653 | K91: 5FNRL6H68RB050203 | L91: EX-L | M91: 157 | N91: FWD | O91: 30850 | P91: 33250 | Q91: 35688 | R91: =O91-Q91 -> -4838 | S91: =O91*1.15 -> 35477.5 | T91: =S91-Q91 -> -210.5 | U91: =O91*1.25 -> 38562.5 | V91: =U91-Q91 -> 2874.5 | W91: =O91*1.25 -> 38562.5 | X91: =W91-Q91 -> 2874.5 | Y91: =O91*1.3 -> 40105 | Z91: =Y91-Q91 -> 4417 | AH91: 17846 | AI91: 685
C92: sold | D92: RTC19587A | E92: 2025 | F92: Honda | G92: CR-V | H92: SUV | I92: Crystal Black Pearl | J92: 12243 | K92: 2HKRS4H21SH494518 | L92: LX | M92: 31 | N92: AWD | O92: 27475 | P92: 30550 | Q92: 28686 | R92: =O92-Q92 -> -1211 | S92: =O92*1.15 -> 31596.25 | T92: =S92-Q92 -> 2910.25 | U92: =O92*1.25 -> 34343.75 | V92: =U92-Q92 -> 5657.75 | W92: =O92*1.25 -> 34343.75 | X92: =W92-Q92 -> 5657.75 | Y92: =O92*1.3 -> 35717.5 | Z92: =Y92-Q92 -> 7031.5 | AF92: =P92-Q92 -> 1864 | AH92: 24327 | AI92: 685
D93: RTC19872 | E93: 2025 | F93: Honda | G93: HR-V | H93: Hatch | I93: Platinum White Pearl | J93: 1780 | K93: 3CZRZ2H33SM766631 | L93: LX | M93: 38 | N93: AWD | O93: 23575 | P93: 27875 | Q93: 25124 | R93: =O93-Q93 -> -1549 | S93: =O93*1.15 -> 27111.25 | T93: =S93-Q93 -> 1987.25 | U93: =O93*1.25 -> 29468.75 | V93: =U93-Q93 -> 4344.75 | W93: =O93*1.25 -> 29468.75 | X93: =W93-Q93 -> 4344.75 | Y93: =O93*1.3 -> 30647.5 | Z93: =Y93-Q93 -> 5523.5 | AH93: 7500 | AI93: 685
B94: FIND | D94: DC20982A | E94: 2024 | F94: Honda | G94: HR-V | H94: Hatch | I94: Nh-912 | J94: 31935 | K94: 3CZRZ2H31RM751779 | L94: LX | M94: 1 | N94: AWD | O94: 21025 | P94: 24700 | Q94: 20000 | R94: =O94-Q94 -> 1025 | S94: =O94*1.15 -> 24178.75 | T94: =S94-Q94 -> 4178.75 | U94: =O94*1.25 -> 26281.25 | V94: =U94-Q94 -> 6281.25 | W94: =O94*1.4 -> 29435 | X94: =W94-Q94 -> 9435 | Y94: =W94*0.0207 -> 609.3045 | Z94: =Y94-Q94 -> -19390.696 | AH94: 34955 | AI94: 685
D95: P6270 | E95: 2023 | F95: Toyota | G95: Camry | H95: Sedan | I95: Black | J95: 100903 | K95: 4T1C11AK8PU152896 | L95: LE | M95: 26 | N95: FWD | O95: 16150 | P95: 18725 | Q95: 18259 | R95: =O95-Q95 -> -2109 | S95: =O95*1.15 -> 18572.5 | T95: =S95-Q95 -> 313.5 | U95: =O95*1.25 -> 20187.5 | V95: =U95-Q95 -> 1928.5 | W95: =O95*1.4 -> 22610 | X95: =W95-Q95 -> 4351 | Y95: =W95*0.0207 -> 468.027 | Z95: =Y95-Q95 -> -17790.973 | AF95: =P95-Q95 -> 466 | AH95: 31402 | AI95: 685
D96: C20022B | E96: 2020 | F96: Chevrolet | G96: Camaro | H96: Coupe | I96: Shadow Gray Metallic | J96: 88711 | K96: 1G1FD1RS4L0105873 | L96: 2LT | M96: 19 | N96: RWD | O96: 16950 | P96: 22525 | Q96: 14174 | R96: =O96-Q96 -> 2776 | S96: =O96*1.15 -> 19492.5 | T96: =S96-Q96 -> 5318.5 | U96: =O96*1.25 -> 21187.5 | V96: =U96-Q96 -> 7013.5 | W96: =O96*1.25 -> 21187.5 | X96: =W96-Q96 -> 7013.5 | Y96: =O96*1.3 -> 22035 | Z96: =Y96-Q96 -> 7861 | AF96: =P96-Q96 -> 8351 | AH96: 22319 | AI96: 685
D97: C20927A | E97: 2016 | F97: Honda | G97: HR-V | H97: Hatch | I97: Black | J97: 33621 | K97: 3CZRU6H72GM753627 | L97: EX-L | M97: 6 | N97: AWD | O97: 16500 | P97: 17450 | Q97: 8543 | R97: =O97-Q97 -> 7957 | S97: =O97*1.15 -> 18975 | T97: =S97-Q97 -> 10432 | U97: =O97*1.25 -> 20625 | V97: =U97-Q97 -> 12082 | W97: =O97*1.25 -> 20625 | X97: =W97-Q97 -> 12082 | Y97: =O97*1.3 -> 21450 | Z97: =Y97-Q97 -> 12907 | AF97: =P97-Q97 -> 8907 | AH97: 24460 | AI97: 685
D98: DC20905A | E98: 2011 | F98: Hyundai | G98: Elantra | H98: Sedan | I98: Radiant Silver Metallic | J98: 105268 | K98: 5NPDH4AEXBH035839 | L98: GLS | M98: 12 | N98: FWD | O98: 4013 | P98: 7288 | Q98: 2762 | R98: =O98-Q98 -> 1251 | S98: =O98*1.15 -> 4614.95 | T98: =S98-Q98 -> 1852.95 | U98: =O98*1.25 -> 5016.25 | V98: =U98-Q98 -> 2254.25 | W98: =O98*1.4 -> 5618.2 | X98: =W98-Q98 -> 2856.2 | Y98: =W98*0.0207 -> 116.29674 | Z98: =Y98-Q98 -> -2645.7033 | AH98: 19455 | AI98: 685
D99: C20639B | E99: 2003 | F99: Dodge | G99: Ram 1500 | H99: Truck | I99: Red | J99: 190368 | K99: 1D7HA18D33S359824 | L99: SLT | M99: 2 | N99: RWD | O99: - | P99: - | Q99: 1000 | R99: =O99-Q99 -> #VALUE! | S99: =O99*1.15 -> #VALUE! | T99: =S99-Q99 -> #VALUE! | U99: =O99*1.25 -> #VALUE! | V99: =U99-Q99 -> #VALUE! | W99: =O99*1.4 -> #VALUE! | X99: =W99-Q99 -> #VALUE! | Y99: =W99*0.0207 -> #VALUE! | Z99: =Y99-Q99 -> #VALUE! | AH99: 35062 | AI99: 685
R100: =O100-Q100 -> 0 | S100: =O100*1.15 -> 0 | T100: =S100-Q100 -> 0 | U100: =O100*1.25 -> 0 | V100: =U100-Q100 -> 0 | W100: =O100*1.25 -> 0 | X100: =W100-Q100 -> 0 | Y100: =O100*1.3 -> 0 | Z100: =Y100-Q100 -> 0 | AH100: 24111 | AI100: 685
...

Sheet DEAL LOG
E1: $$? | G1: DEAL# | H1: STOCK# | I1: CUSTOMER | J1: WORK DONE | K1: NEW/USED | L1: YEAR | M1: MAKE | N1: MODEL | O1: COST | P1: AGE | Q1: YEAR | R1: MAKE | S1: MODEL | T1: MILES | U1: ACV | V1: PAYOFF | W1: SALESPERSON | X1: 2ND SALESPERSON | Y1: FRONT GROSS | Z1: LENDER | AA1: RATE | AB1: RESERVE | AC1: WARRANTY | AD1: AFT 1 | AE1: GAP | AF1: F&I TOOLS | AG1: TOTAL GROSS | AH1: DAILY GROSS | AI1: ADD GROSS | AJ1: DLR GROSS | AK1: JDE PAY | AL1: NOTES
F2: 1 | G2: TODAY'S DATE | I2: 2/16/26-2/21/26 | K2: UPS | AA2: =SUM(M2:Z2) -> 0 | AM2: DELIVERY % | AN2: FRONT PVR | AO2: BACK PVR | AP2: TOT PVR
F3: 1 | G3: DEALERSHIP | I3: HONDA CITY | K3: NEW | N3: 0 | O3: 0 | Q3: 0 | R3: 0 | S3: 2 | AA3: =SUM(M3:Z3) -> 2 | AC3: CLOSING | AL3: Sale Log | AM3: =(AA4+AA3)/AA2 -> #DIV/0! | AN3: =Y118/AB4 -> #VALUE! | AO3: =AF119/AB4 -> #VALUE! | AP3: =AN3+AO3 -> #VALUE!
K4: USED | AA4: =SUM(M4:Z4) -> 0 | AB4: =AA3+AA4 -> 2 | AC4: =AB4/AA2 -> #DIV/0!
M5: =M3+M4 -> #VALUE! | N5: =N3+N4 -> #VALUE! | O5: =O3+O4 -> #VALUE! | Q5: =Q3+Q4 -> #VALUE! | R5: =R3+R4 -> #VALUE! | S5: =S3+S4 -> #VALUE! | T5: =T3+T4 -> 0 | U5: =U3+U4 -> 0 | W5: =W3+W4 -> 0 | X5: =X3+X4 -> 0 | Y5: =Y3+Y4 -> 0 | Z5: =Z3+Z4 -> 0
AA6: =SUM(M6:Z6) -> 0
E7: $$? | G7: STORE | H7: STOCK# | I7: CUSTOMER | J7: ZIPCODE | K7: NEW/USED | L7: YEAR | M7: MAKE | N7: MODEL | O7: COST | P7: AGE | Q7: YEAR | R7: MAKE | S7: MODEL | T7: MILES | U7: ACV | V7: PAYOFF | W7: SALESPERSON | X7: 2ND SALESPERSON | Y7: FRONT GROSS | Z7: LENDER | AA7: RATE | AB7: RESERVE | AC7: WARRANTY | AD7: AFT 1 | AE7: GAP | AF7: FI TOTALS | AG7: TOTAL GROSS | AH7: DAILY GROSS | AI7: HOLDBACK | AJ7: DLR GROSS | AK7: JDE PAY | AL7: NOTES
C10: 1 | D10: 1 | H10: C20931A | I10: ESCALONA | J10: 60443 | K10: Used | L10: 2025 | M10: HONDA | N10: HR-V | O10: 24677 | P10: 7 | W10: BRYAN ROGERS | X10: NICK WILEY | Y10: 5113.2 | Z10: HONDA | AA10: 13.74 | AB10: 1092.42 | AC10: 1837 | AE10: 762 | AF10: =SUM(AB10:AE10) -> 3691.42 | AG10: =Y10+AF10 -> 8804.62
C11: 2 | D11: 2 | H11: RTC19587A | I11: NINO BARON | J11: 60153 | K11: Used | L11: 2025 | M11: HONDA | N11: CR-V | O11: 28686.44 | P11: 32 | W11: HOUSE | Y11: 4237.56 | Z11: HONDA | AA11: 7.29 | AB11: 1709.32 | AC11: 2459 | AD11: 1488 | AF11: =SUM(AB11:AE11) -> 5656.32 | AG11: =Y11+AF11 -> 9893.88
C12: 3 | D12: 3 | H12: C20657 | I12: RAMOS RAMOS | J12: 60625 | K12: New | L12: 2026 | M12: HONDA | N12: CR-V | O12: 38663 | P12: 165 | Q12: 2023 | R12: HONDA | S12: CRV | T12: 46053 | U12: 19500 | V12: 25608 | W12: HOUSE | Y12: 2247.31 | Z12: CAP 1 | AA12: 12.65 | AB12: 2822.92 | AE12: 631 | AF12: =SUM(AB12:AE12) -> 3453.92 | AG12: =Y12+AF12 -> 5701.23 | AI12: 785.1 | AL12: 785.10 HB
AF13: =SUM(AB13:AE13) -> 0 | AG13: =Y13+AF13 -> 0 | AH13: =SUM(AG10:AG12) -> 24399.73
C14: 1 | D14: 4 | H14: C20630A | I14: TOVAR | J14: 60609 | K14: Used | L14: 2021 | M14: MAZDA | N14: CX5 | O14: 19203 | P14: 48 | Q14: 2005 | R14: CHRYSLER | S14: PACIFICA | U14: 500 | W14: CHRIS MARTIN | Y14: 3175.92 | Z14: GLOBAL | AA14: 26.2 | AB14: 386.24 | AC14: 1328.24 | AF14: =SUM(AB14:AE14) -> 1714.48 | AG14: =Y14+AF14 -> 4890.4
C15: 2 | D15: 5 | H15: C20879 | I15: DIAZ | J15: 60652 | K15: New | L15: 2026 | M15: HONDA | N15: CIVIC | O15: 24757 | P15: 57 | W15: JOSE TORRES | Y15: 5723.22 | Z15: CHASE | AA15: 7.34 | AB15: 370.99 | AC15: 1687 | AF15: =SUM(AB15:AE15) -> 2057.99 | AG15: =Y15+AF15 -> 7781.21 | AI15: 491.9 | AL15: 491.90 HB
C16: 3 | D16: 6 | H16: DC20851 | I16: CHILE | J16: 60653 | K16: New | L16: 2026 | M16: HONDA | N16: HR-V | O16: 26549 | P16: 45 | Q16: 2018 | R16: HONDA | S16: CIVIC | T16: 32238 | U16: 13000 | V16: 18607 | W16: MAYCON MIKE GUIMARAES | Y16: 0 | Z16: HONDA | AA16: 4.49 | AB16: 200 | AF16: =SUM(AB16:AE16) -> 200 | AG16: =Y16+AF16 -> 200
C17: 4 | D17: 7 | H17: C20535 | I17: PARRA | J17: 60623 | K17: New | L17: 2025 | M17: HONDA | N17: PILOT | O17: 48573.99 | P17: 201 | W17: HOUSE | Y17: 0 | Z17: ALLY | AA17: LS | AB17: 2908.92 | AC17: 622 | AF17: =SUM(AB17:AE17) -> 3530.92 | AG17: =Y17+AF17 -> 3530.92 | AI17: 997.1 | AL17: 997.10 HB
AG18: =Y18+AF18 -> 0 | AH18: =SUM(AG14:AG17) -> 16402.53
D19: 8 | H19: C20754 | I19: MORENO | J19: 60804 | K19: New | L19: 2026 | M19: HONDA | N19: CR-V | O19: 39583.3 | P19: 125 | Q19: 2025 | R19: JEEP | S19: COMPASS | T19: 4716 | U19: 21000 | V19: 29950 | W19: JOSE TORRES | X19: OSSIE SAMPSON | Y19: 4459.53 | Z19: HONDA | AA19: 7.89 | AB19: 3995.46 | AC19: 5910 | AE19: 681 | AF19: =SUM(AB19:AE19) -> 10586.46 | AG19: =Y19+AF19 -> 15045.99 | AI19: 804.5 | AL19: AVP CREDITED TO BACK END
D20: 9 | H20: XP6290 | I20: EARL | J20: 60609 | K20: Used | L20: 2021 | M20: HYUNDAI | N20: TUCSON | O20: 19141.9 | P20: 6 | W20: MIKE LASHLEY | Y20: 2000 | Z20: CHASE | AA20: 10.04 | AB20: 1215.91 | AC20: 697 | AF20: =SUM(AB20:AE20) -> 1912.91 | AG20: =Y20+AF20 -> 3912.91
D21: 10 | H21: C20944 | I21: MORALES | J21: 60629 | K21: New | L21: 2026 | M21: HONDA | N21: CIVIC | O21: 24852.81 | P21: 19 | W21: HOUSE | Y21: 5562.42 | Z21: HONDA | AA21: 7.64 | AB21: 2458.89 | AC21: 4159 | AE21: 376 | AF21: =SUM(AB21:AE21) -> 6993.89 | AG21: =Y21+AF21 -> 12556.31 | AI21: 493.9 | AL21: 493.90 HB
D22: 11 | H22: C20699 | I22: PULIDO | J22: 60501 | K22: New | L22: 2025 | M22: HONDA | N22: PILOT | O22: 48038 | P22: 125 | W22: BRYAN ROGERS | Y22: 9464.81 | Z22: HONDA | AA22: 7.64 | AB22: 4518.99 | AC22: 3885 | AD22: 2954 | AE22: 681 | AF22: =SUM(AB22:AE22) -> 12038.99 | AG22: =Y22+AF22 -> 21503.8 | AI22: 1030 | AL22: 1030 HB
D23: 12 | H23: C20911 | I23: TELLEZ | J23: 60632 | K23: New | L23: 2026 | M23: HONDA | N23: HR-V | O23: 28022 | P23: 30 | Q23: 2004 | R23: NISSAN | S23: QUEST | T23: 59954 | U23: 500 | W23: ABDUL AL TABBAH | Y23: 0 | Z23: HONDA | AA23: 7.29 | AB23: 1537.38 | AD23: RO | AF23: =SUM(AB23:AE23) -> 1537.38 | AG23: =Y23+AF23 -> 1537.38 | AI23: 560 | AL23: 560 HB
AF24: =SUM(AB24:AE24) -> 0 | AG24: =Y24+AF24 -> 0 | AH24: =SUM(AG19:AG23) -> 54556.39
C25: 1 | D25: 13 | H25: C20976 | I25: DELATORRE | J25: 60632 | K25: New | L25: 2026 | M25: HONDA | N25: CR-V | O25: 37266.23 | P25: 7 | Q25: 2024 | R25: KIA | S25: K5 | T25: 23982 | U25: 22000 | W25: NICK WILEY | X25: JOSE TORRES | Y25: 4589.8 | Z25: HONDA | AA25: 7.64 | AB25: 3100.86 | AC25: 3545 | AE25: 681 | AF25: =SUM(AB25:AE25) -> 7326.86 | AG25: =Y25+AF25 -> 11916.66 | AI25: 751.7 | AL25: 751.70 HB
C26: 2 | D26: 14 | H26: C20540A | I26: DEER/PHILLIPS | J26: 60609 | K26: Used | L26: 2022 | M26: HONDA | N26: HR-V | O26: 21072.39 | P26: 65 | W26: JOSE TORRES | X26: NICK WILEY | Y26: 2157 | Z26: WFDS | AA26: 10.24 | AB26: 1473.06 | AC26: 1219 | AF26: =SUM(AB26:AE26) -> 2692.06 | AG26: =Y26+AF26 -> 4849.06
C27: 3 | D27: 15 | H27: C20237A | I27: MONDRAGON | J27: 60623 | K27: Used | L27: 2023 | M27: SUBARU | N27: OUTBACK | O27: 25965.69 | P27: 89 | Q27: 2012 | R27: HYUNDAI | S27: ACCENT | T27: 144000 | U27: 500 | W27: BRYAN ROGERS | Y27: 3758.31 | Z27: WFDS | AA27: 11.74 | AB27: 1695 | AE27: 681 | AF27: =SUM(AB27:AE27) -> 2376 | AG27: =Y27+AF27 -> 6134.31
C28: 4 | D28: 16 | H28: C20935 | I28: BAHENA | J28: 60623 | K28: New | L28: 2026 | M28: HONDA | N28: CIVIC | O28: 24852 | P28: 21 | W28: HOUSE | Y28: 3826.42 | Z28: CAP 1 | AA28: 11.95 | AB28: 1684.62 | AC28: 2691 | AE28: 681 | AF28: =SUM(AB28:AE28) -> 5056.62 | AG28: =Y28+AF28 -> 8883.04 | AI28: 493.9 | AL28: 493.90 HB
C29: 5 | D29: 17 | H29: C20654A | I29: MONDRAGON | J29: 60623 | K29: Used | L29: 2022 | M29: CHEVY | N29: 1500 | O29: 39338 | P29: 88 | Q29: 1999 | R29: DODGE | S29: DURANGO | U29: 1 | W29: BRYAN ROGERS | Y29: 6061.7 | Z29: CAP 1 | AA29: 13.26 | AB29: 241.5 | AC29: 1137 | AF29: =SUM(AB29:AE29) -> 1378.5 | AG29: =Y29+AF29 -> 7440.2
C30: 6 | D30: 18 | H30: C20340 | I30: ROJAS AGUDELO | J30: 60632 | K30: New | L30: 2026 | M30: HONDA | N30: CRV | O30: 32453 | P30: 248 | W30: ABDUL AL TABBAH | X30: JOSE TORRES | Y30: 0 | Z30: HONDA | AA30: 5.99 | AB30: 200 | AE30: 367 | AF30: =SUM(AB30:AE30) -> 567 | AG30: =Y30+AF30 -> 567 | AI30: 648.4 | AL30: 648.40 HB
AF31: =SUM(AB31:AE31) -> 0 | AG31: =Y31+AF31 -> 0 | AH31: =SUM(AG25:AG30) -> 39790.27
C32: 1 | D32: 19 | H32: C20885 | I32: CORTEZ | J32: 60634 | K32: New | L32: 2026 | M32: HONDA | N32: CIVIC | O32: 25190 | P32: 56 | W32: HOUSE | Y32: 0 | Z32: ALLY | AA32: 8.99 | AB32: 0 | AE32: 0 | AF32: =SUM(AB32:AE32) -> 0 | AG32: =Y32+AF32 -> 0 | AI32: 501
C33: 2 | D33: 20 | H33: C20928 | I33: CASTRO FIGUEROA | J33: 60609 | K33: New | L33: 2026 | M33: HONDA | N33: CIVIC | O33: 30352 | P33: 23 | W33: HOUSE | Y33: 2319.19 | Z33: CAP 1 | AA33: 11.01 | AB33: 1644.64 | AF33: =SUM(AB33:AE33) -> 1644.64 | AG33: =Y33+AF33 -> 3963.83 | AI33: 611.9
C34: 3 | D34: 21 | H34: C20673 | I34: DITTMANN | J34: 60603 | K34: New | L34: 2026 | M34: HONDA | N34: HR-V | O34: 29997 | P34: 151 | Q34: 2012 | R34: FORD | S34: FUSION | T34: 66828 | U34: 3000 | V34: 0 | W34: BRYANT ROGERS | X34: BRYAN ROGERS | Y34: 6124.05 | Z34: HONDA | AA34: 2.49 | AB34: 100 | AC34: 1647 | AF34: =SUM(AB34:AE34) -> 1747 | AG34: =Y34+AF34 -> 7871.05 | AI34: 599.1
C35: 4 | D35: 22 | H35: C20926 | I35: ALONSO HERRERA | J35: 60636 | K35: New | L35: 2026 | M35: HONDA | N35: CR-V | O35: 40936.4 | P35: 23 | Q35: 2017 | R35: HONDA | S35: CR-V | T35: 160676 | U35: 6000 | W35: HOUSE | Y35: 7189.56 | Z35: HONDA | AA35: 7.64 | AB35: 2761.29 | AF35: =SUM(AB35:AE35) -> 2761.29 | AG35: =Y35+AF35 -> 9950.85 | AI35: 851
C36: 5 | D36: 23 | H36: C20677 | I36: SERRANO RAMOS | J36: 60632 | K36: New | L36: 2026 | M36: HONDA | N36: CR-V | O36: 38232.4 | P36: 154 | W36: HOUSE | Y36: 5392.93 | Z36: HONDA | AA36: 7.89 | AB36: 3199.14 | AC36: 2311 | AE36: 481 | AF36: =SUM(AB36:AE36) -> 5991.14 | AG36: =Y36+AF36 -> 11384.07 | AI36: 776
C37: 6 | D37: 24 | H37: C20968 | I37: SEGURA | J37: 60632 | K37: New | L37: 2026 | M37: HONDA | N37: CIVIC | O37: 30785 | P37: 10 | Q37: 2015 | R37: TOYOTA | S37: CAMRY | T37: 133865 | U37: 6000 | W37: NATE HARDING | Y37: 8111.67 | Z37: HONDA | AA37: 7.49 | AB37: 1749.94 | AD37: 1000 | AF37: =SUM(AB37:AE37) -> 2749.94 | AG37: =Y37+AF37 -> 10861.61 | AI37: 621
C38: 7 | D38: 25 | H38: DC20964A | I38: ORTEGA | J38: 60629 | K38: Used | L38: 2020 | M38: HONDA | N38: PILOT | O38: 30918.42 | P38: 4 | Q38: 2019 | R38: HONDA | S38: PASSPORT | T38: 109562 | U38: 11000 | V38: 12992 | W38: HOUSE | Y38: 2921.58 | Z38: ALLY | AA38: 10.89 | AB38: 1118.77 | AC38: 1846 | AE38: 981 | AF38: =SUM(AB38:AE38) -> 3945.77 | AG38: 3433
C39: 8 | D39: 26 | H39: C20689 | I39: ZENG | J39: 60632 | K39: New | L39: 2026 | M39: HONDA | N39: CR-V | O39: 39583.3 | P39: 150 | Q39: 2020 | R39: JEEP | S39: GR CHEROKEE | T39: 64000 | U39: 11000 | V39: 0 | W39: BRYANT ROGERS | X39: BRYAN ROGERS | Y39: 5791.53 | Z39: HONDA | AA39: 4.49 | AB39: 200 | AC39: 1363 | AF39: =SUM(AB39:AE39) -> 1563 | AG39: =Y39+AF39 -> 7354.53 | AI39: 804.5
C40: 9 | D40: 27 | H40: C20853 | I40: RUAN | J40: 60632 | K40: New | L40: 2026 | M40: HONDA | N40: CR-V | O40: 39583.3 | P40: 71 | Q40: 2022 | R40: HONDA | S40: PILOT | T40: 35540 | U40: 28000 | V40: 14550 | W40: BRYAN ROGERS | X40: BRYANT ROGERS | Y40: 7291.53 | Z40: HONDA | AA40: 4.49 | AB40: 200 | AD40: 1600 | AF40: =SUM(AB40:AE40) -> 1800 | AG40: =Y40+AF40 -> 9091.53 | AI40: 804.5
C41: 10 | D41: 28 | H41: P6256 | I41: FOSTER | J41: 60617 | K41: Used | L41: 2022 | M41: HONDA | N41: PILOT | O41: 33154 | P41: 46 | Q41: 2008 | R41: MERCEDES | S41: E300 | T41: 156629 | U41: 1 | V41: 0 | W41: BRYANT ROGERS | X41: HALEY DELUDE | Y41: 2000 | Z41: CAP 1 | AA41: 5.99 | AB41: 372 | AC41: 854 | AE41: 148 | AF41: =SUM(AB41:AE41) -> 1374 | AG41: =Y41+AF41 -> 3374
AF42: =SUM(AB42:AE42) -> 0 | AG42: =Y42+AF42 -> 0 | AH42: =SUM(AG32:AG41) -> 67284.47
C43: 1 | D43: 29 | H43: P6268 | I43: ORTIZ | J43: 60608 | K43: Used | L43: 2024 | M43: MAZDA | N43: 3 | O43: 19586 | P43: 94 | W43: HOUSE | Y43: 2000 | Z43: CAP 1 | AA43: 16.69 | AB43: 1303.41 | AC43: 2118 | AF43: =SUM(AB43:AE43) -> 3421.41 | AG43: =Y43+AF43 -> 5421.41
C44: 2 | D44: 30 | H44: PC20880A | I44: GOMEZ | J44: 60629 | K44: Used | L44: 2023 | M44: HONDA | N44: CR-V | O44: 30433 | P44: 39 | W44: HOUSE | Y44: 2000 | Z44: HONDA | AA44: 1.49 | AB44: 200 | AC44: 846 | AF44: =SUM(AB44:AE44) -> 1046 | AG44: =Y44+AF44 -> 3046
C45: . | D45: 31 | H45: C20518A | I45: LUNA | J45: 60623 | K45: Used | L45: 2023 | M45: HONDA | N45: HR-V | O45: 23618 | P45: 43 | W45: HOUSE | Y45: 2470.16 | Z45: CAP 1 | AA45: 16.69 | AB45: 1994.63 | AC45: 1564 | AE45: 331 | AF45: =SUM(AB45:AE45) -> 3889.63 | AG45: =Y45+AF45 -> 6359.79
C46: 4 | D46: 32 | H46: C20927A | I46: DIAZ | J46: 60629 | K46: Used | L46: 2016 | M46: HONDA | N46: HR-V | O46: 12126 | P46: 12 | W46: HOUSE | Y46: 8162.69 | Z46: CAP 1 | AA46: 20.56 | AB46: 1515.34 | AC46: 1853 | AF46: =SUM(AB46:AE46) -> 3368.34 | AG46: =Y46+AF46 -> 11531.03
C47: 5 | D47: 33 | H47: XP6231 | I47: BEAMON | J47: 46322 | K47: Used | L47: 2024 | M47: TOYOTA | N47: RAV 4 | O47: 32291 | P47: 102 | W47: HALEY DELUDE | X47: BRYAN ROGERS | Y47: 2000 | Z47: PNC | AA47: 7.85 | AB47: 2149.35 | AC47: 3338 | AE47: 681 | AF47: =SUM(AB47:AE47) -> 6168.35 | AG47: =Y47+AF47 -> 8168.35
C48: 6 | D48: 34 | H48: DC20936 | I48: ACOSTA SANDOVAL | J48: 60629 | K48: New | L48: 2026 | M48: HONDA | N48: CIVIC | O48: 29208 | P48: 10 | W48: CHRIS MARTIN | X48: JOSE TORRES | Y48: 4117.56 | Z48: GLOBAL | AA48: 15.2 | AB48: 1435.43 | AC48: 1022 | AF48: =SUM(AB48:AE48) -> 2457.43 | AG48: =Y48+AF48 -> 6574.99 | AI48: 613
C49: 7 | D49: 35 | H49: C20886A | I49: ARCE | J49: 60609 | K49: Used | L49: 2020 | M49: HONDA | N49: CIVIC | O49: 16305 | P49: 39 | W49: NICK WILEY | Y49: 2000 | Z49: ALLY | AA49: 16.94 | AB49: 1024.63 | AC49: 846 | AF49: =SUM(AB49:AE49) -> 1870.63 | AG49: =Y49+AF49 -> 3870.63
C50: 8 | D50: 36 | H50: C20522A | I50: RODRIGUEZ | J50: 60623 | K50: Used | L50: 2024 | M50: HONDA | N50: HR-V | O50: 25010 | P50: 84 | W50: HOUSE | Y50: 2927.75 | Z50: HONDA | AA50: 8.64 | AB50: 1805.76 | AC50: 2181 | AE50: 762 | AF50: =SUM(AB50:AE50) -> 4748.76 | AG50: =Y50+AF50 -> 7676.51
C51: 9 | D51: 37 | H51: C20875 | I51: TAYLOR | J51: 60623 | K51: New | L51: 2026 | M51: HONDA | N51: CR-V | O51: 36431 | P51: 64 | W51: CHRIS MARTIN | X51: JOSE TORRES | Y51: 6856.13 | Z51: HONDA | AA51: 7.64 | AB51: 3404.52 | AC51: 2065 | AE51: 681 | AF51: =SUM(AB51:AE51) -> 6150.52 | AG51: =Y51+AF51 -> 13006.65 | AI51: 738
C52: 10 | D52: 38 | H52: C20449 | I52: ORTEGA | J52: 60609 | K52: New | L52: 2026 | M52: HONDA | N52: CR-V | O52: 39528 | P52: 224 | W52: HOUSE | Y52: 7100.15 | Z52: HONDA | AA52: 4.49 | AB52: 300 | AC52: 4308 | AE52: 681 | AF52: =SUM(AB52:AE52) -> 5289 | AG52: =Y52+AF52 -> 12389.15 | AI52: 804.5
C53: 11 | D53: 39 | H53: C20960 | I53: WINTER | J53: 60455 | K53: New | L53: 2026 | M53: HONDA | N53: CIVIC | O53: 26410 | P53: 12 | W53: BRYANT ROGERS | Y53: 902.89 | Z53: HONDA | AA53: 10.74 | AB53: 200 | AF53: =SUM(AB53:AE53) -> 200 | AG53: =Y53+AF53 -> 1102.89 | AI53: 533.9
Y54: =SUM(Y10:Y53) -> 150056.57 | AF54: =SUM(AF10:AF53) -> 134958.57 | AG54: =SUM(AG10:AG53) -> 281580.79 | AH54: =SUM(AG43:AG53) -> 79147.4
I55: 23 NEW | AF55: =SUM(AB55:AE55) -> 0 | AG55: =Y55+AF55 -> 0
I56: 16 USED | AF56: =SUM(AB56:AE56) -> 0 | AG56: =Y56+AF56 -> 0
AF57: =SUM(AB57:AE57) -> 0 | AG57: =Y57+AF57 -> 0 | AH57: =SUM(AH13:AH54) -> 281580.79
AF58: =SUM(AB58:AE58) -> 0 | AG58: =Y58+AF58 -> 0
AF59: =SUM(AB59:AE59) -> 0 | AG59: =Y59+AF59 -> 0
AF60: =SUM(AB60:AE60) -> 0 | AG60: =Y60+AF60 -> 0
AF61: =SUM(AB61:AE61) -> 0 | AG61: =Y61+AF61 -> 0
AF62: =SUM(AB62:AE62) -> 0 | AG62: =Y62+AF62 -> 0
AF63: =SUM(AB63:AE63) -> 0 | AG63: =Y63+AF63 -> 0
AF64: =SUM(AB64:AE64) -> 0 | AG64: =Y64+AF64 -> 0
AF65: =SUM(AB65:AE65) -> 0 | AG65: =Y65+AF65 -> 0
AF66: =SUM(AB66:AE66) -> 0 | AG66: =Y66+AF66 -> 0
AF67: =SUM(AB67:AE67) -> 0 | AG67: =Y67+AF67 -> 0
AF68: =SUM(AB68:AE68) -> 0 | AG68: =Y68+AF68 -> 0
AF69: =SUM(AB69:AE69) -> 0 | AG69: =Y69+AF69 -> 0
... AF89: =SUM(AB89:AE89) -> 0 | AG89: =Y89+AF89 -> 0
A90: 37N | AF90: =SUM(AB90:AE90) -> 0 | AG90: =Y90+AF90 -> 0
AK96: =SUM(AH15:AH96) -> 538761.85
AF101: =SUM(AB101:AE101) -> 0 | AG101: =SUM(Y101+AF101) -> 0
AF102: =SUM(AB102:AE102) -> 0 | AG102: =SUM(Y102+AF102) -> 0
AF103: =SUM(AB103:AE103) -> 0 | AG103: =SUM(Y103+AF103) -> 0
AF104: =SUM(AB104:AE104) -> 0 | AG104: =SUM(Y104+AF104) -> 0
G105: BILLED $1100 TO JDE ONLY MUST CHECK NEXT SALE TO SEE WHAT TOTAL RO WAS ZERO EXPENSE TO THE REP | AF105: =SUM(AB105:AE105) -> 0 | AG105: =SUM(Y105+AF105) -> 0
G106: HOLLEY DEAL, ONE ? ONE Y CLEARED THE Y AS IT WAS THE ? WAS HER TRADE WHICH WAS SOLD BACK TO HER FOR A PROFIT +1100 NEXT SALE | AF106: =SUM(AB106:AE106) -> 0 | AG106: =SUM(Y106+AF106) -> 0
G107: P1162A HAD OPEN FOR $942 W OUT BRAKES EXPENSED - ADDED $1100 AS PER ABOVE REP NOT CHARGED | AF107: =SUM(AB107:AE107) -> 0 | AG107: =SUM(Y107+AF107) -> 0
G108: MK2373A ADDITIONAL 1200+/- RO FOR CHECK ENG LIGHT, DEDUCTED FOR JDE, AND TOOK REPS OUT OF JDE AS WELL | AF108: =SUM(AB108:AE108) -> 0 | AG108: =SUM(Y108+AF108) -> 0
G109: FLEMING MF1065A HAD $333 PENDING DID NOT INCLUDE BRAKES, ADDED $1100 PER ABOVE | AF109: =SUM(AB109:AE109) -> 0 | AG109: =SUM(Y109+AF109) -> 0
G110: P1198A RENFRO 821.73 FRONT 3438.67 BACK 4260.40 TOTAL ADDED TO NEXT SALE | AF110: =SUM(AB110:AE110) -> 0 | AG110: =SUM(Y110+AF110) -> 0
AF111: =SUM(AB111:AE111) -> 0 | AG111: =SUM(Y111+AF111) -> 0
AF112: =SUM(AB112:AE112) -> 0 | AG112: =SUM(Y112+AF112) -> 0
AF113: =SUM(AB113:AE113) -> 0 | AG113: =SUM(Y113+AF113) -> 0
AF114: =SUM(AB114:AE114) -> 0 | AG114: =SUM(Y114+AF114) -> 0
AF115: =SUM(AB115:AE115) -> 0 | AG115: =SUM(Y115+AF115) -> 0
AF116: =SUM(AB116:AE116) -> 0 | AG116: =SUM(Y116+AF116) -> 0
AF117: =SUM(AB117:AE117) -> 0 | AG117: =SUM(Y117+AF117) -> 0
AF118: =SUM(AB118:AE118) -> 0
J121: DO NOT TOUCH - Columns in RED or in headings, these are locked cells. Headings in YELLOW will fill in automatically based on HAT # if the vehicle had one assigned on the inventory list. All columns with GRAY headings require you to fill them in.

Sheet MAIL TRACKING
F2: MON | G2: TUES | H2: WED | I2: THURS | J2: FRI | K2: SAT
D3: UPS | F3: =F15 -> 37 | G3: =G15 -> 16 | H3: =H15 -> 36 | I3: =I15 -> 50 | J3: =J15 -> 78 | K3: =K15 -> 100
A4: PIECES SENT | B4: RESPONSES | C4: TOWN | D4: ZIP | E4: ZIP TOTAL | F4: DAY 1 | G4: DAY 2 | H4: DAY 3 | I4: DAY 4 | J4: DAY 5 | K4: DAY 6
A5: 9777 | B5: =E5/A5 -> 0.0043980771 | C5: CHICAGO, IL | D5: 60608 | E5: =SUM(F5:K5) -> 43 | I5: 4 | J5: 19 | K5: 20
A6: 10462 | B6: =E6/A6 -> 0.0068820493 | C6: CHICAGO, IL | D6: 60609 | E6: =SUM(F6:K6) -> 72 | F6: 16 | G6: 8 | H6: 12 | I6: 12 | J6: 14 | K6: 10
A7: 10434 | B7: =E7/A7 -> 0.0057504313 | C7: CHICAGO, IL | D7: 60623 | E7: =SUM(F7:K7) -> 60 | H7: 5 | I7: 9 | J7: 16 | K7: 30
A8: 9773 | B8: =E8/A8 -> 0.0096183362 | C8: CHICAGO, IL | D8: 60632 | E8: =SUM(F8:K8) -> 94 | F8: 16 | G8: 7 | H8: 13 | I8: 17 | J8: 17 | K8: 24
A9: 9621 | B9: =E9/A9 -> 0.0049890864 | C9: CICERO, IL | D9: 60804 | E9: =SUM(F9:K9) -> 48 | F9: 5 | G9: 1 | H9: 6 | I9: 8 | J9: 12 | K9: 16
A12: =SUM(A5:A9) -> 50067
D14: NON FLYER
D15: TOTAL | F15: =SUM(F5:F14) -> 37 | G15: =SUM(G5:G14) -> 16 | H15: =SUM(H5:H14) -> 36 | I15: =SUM(I5:I14) -> 50 | J15: =SUM(J5:J14) -> 78 | K15: =SUM(K5:K14) -> 100 | L15: =SUM(L5:L14) -> 0 | M15: =SUM(M5:M14) -> 0 | ... O15: =SUM(O5:O14) -> 0 | P15: =SUM(P5:P8) -> 0 | Q15: =SUM(Q5:Q13) -> 0
A17: TOTAL | D17: =SUM(F15:K15) -> 317 | K17: =SUM(F15:K15) -> 317
C20: JIM | D20: 200

Sheet SLSPERSON WASHOUT
A1: F
E5: 25% COMMISSION
D7: BRYAN ROGERS
D9: Deal # | E9: Stock # | F9: Customer | G9: Customer Zip Code | H9: Source | I9: New/Used | J9: Purchase | M9: NOTES | N9: 2nd Sales Person | O9: Front Gross | P9: PACK | Q9: COMM % | R9: COMMISSION | S9: SPLIT
C11: 1 | E11: C20931A | F11: ESCALONA | I11: Used | J11: 2025 | K11: HONDA | L11: HR-V | M11: SPLIT NICK WILEY | O11: 5113.2 | P11: 0 | Q11: 0.125 | R11: =O11*Q11 -> 639.15 | S11: 0
C12: 2 | E12: C20699 | F12: PULIDO | I12: New | J12: 2025 | K12: HONDA | L12: PILOT | O12: 9464.81 | P12: 0 | Q12: 0.25 | R12: =O12*Q12 -> 2366.2025 | S12: 0
C13: 3 | E13: C20237A | F13: MONDRAGON | I13: Used | J13: 2023 | K13: SUBARU | L13: OUTBACK | O13: 3758.31 | P13: 0 | Q13: 0.25 | R13: =O13*Q13 -> 939.5775 | S13: 0
P14: 0 | Q14: 0.25 | R14: =O14*Q14 -> 0 | S14: =R14/2 -> 0
P15: 0 | Q15: 0.25 | R15: =SUM(O15-P15)*0.25 -> 0 | S15: 0
Q16: 0.25 | R16: =SUM(O16-P16)*0.25 -> 0 | S16: 0
Q17: 0.25 | R17: =SUM(O17-P17)*0.25 -> 0 | S17: 0
Q18: 0.25 | R18: =SUM(O18-P18)*0.25 -> 0 | S18: =(O18*0.25)/2 -> 0
Q19: 0.25 | R19: =SUM(O19-P19)*0.25 -> 0 | S19: =(O19*0.25)/2 -> 0
Q20: 0.25 | R20: =SUM(O20-P20)*0.25 -> 0 | S20: =(O20*0.25)/2 -> 0
Q21: 0.25 | R21: =SUM(O21-P21)*0.25 -> 0 | S21: =(O21*0.25)/2 -> 0
Q22: 0.25 | R22: =SUM(O22-P22)*0.25 -> 0 | S22: =(O22*0.25)/2 -> 0
Q23: 0.25 | R23: =SUM(O23-P23)*0.25 -> 0 | S23: =(O23*0.25)/2 -> 0
Q24: 0.25 | R24: =SUM(O24-P24)*0.25 -> 0 | S24: =(O24*0.25)/2 -> 0
Q25: 0.25 | R25: =SUM(O25-P25)*0.25 -> 0 | S25: =(O25*0.25)/2 -> 0
Q26: 0.25 | R26: =SUM(O26-P26)*0.25 -> 0 | S26: =(O26*0.25)/2 -> 0
Q27: 0.25 | R27: =(O27*0.25)/2 -> 0 | S27: =(O27*0.25)/2 -> 0
C28: 4 | E28: C20654A | F28: MONDRAGON | I28: Used | J28: 2022 | K28: CHEVY | L28: 1500 | O28: 6061.7 | Q28: 0.25 | R28: =O28*Q28 -> 1515.425 | S28: 0
C29: 5 | E29: C20689 | F29: ZENG | I29: New | J29: 2026 | K29: HONDA | L29: CR-V | M29: SPLIT BRYANT ROGERS | O29: 5791.53 | P29: 0 | Q29: 0.125 | R29: =O29*Q29 -> 723.94125 | S29: 0
C30: 6 | E30: C20853 | F30: RUAN | I30: New | J30: 2026 | K30: HONDA | L30: CR-V | M30: SPLIT BRYANT ROGERS | O30: 7291.53 | P30: 0 | Q30: 0.125 | R30: =O30*Q30 -> 911.44125 | S30: 0
C31: 7 | E31: XP6231 | F31: BEAMON | I31: Used | J31: 2024 | K31: TOYOTA | L31: RAV 4 | M31: SPLIT HALEY DELUDE | O31: 2000 | P31: 0 | Q31: 0.125 | R31: =O31*Q31 -> 250 | S31: 0
E32: C20673 | F32: DITTMANN | I32: New | J32: 2026 | K32: HONDA | L32: HR-V | M32: SPLIT BRYAN ROGERS | O32: 6124.05 | P32: 0 | Q32: 0.125 | R32: =(O32*0.25)/2 -> 765.50625 | S32: =(O32*0.25)/2 -> 765.50625
Q33: 0.25 | R33: =(O33*0.25)/2 -> 0 | S33: =(O33*0.25)/2 -> 0
Q34: 0.25 | R34: 0 | S34: 0
Q35: 0.25 | R35: =(O35*0.25)/2 -> 0 | S35: =(O35*0.25)/2 -> 0
O36: =SUM(O11:O35) -> 45605.13 | R36: =SUM(R11:R34) -> 8111.2437
C37: =SUM(C11:C35) -> 28 | N37: PVR
D41: NICK WILEY
D43: Deal # | E43: Stock # | F43: Customer | G43: Customer Zip Code | H43: Source | I43: New/Used | J43: Purchase | M43: NOTES | N43: 2nd Sales Person | O43: Front Gross | P43: PACK | Q43: COMM % | R43: COMMISSION | S43: SPLIT
J44: Year | K44: Make | L44: Model
C45: 1 | E45: C20931A | F45: ESCALONA | I45: Used | J45: 2025 | K45: HONDA | L45: HR-V | M45: SPLIT BRYAN ROGERS | O45: 5113.2 | P45: 0 | Q45: 0.125 | R45: =O45*Q45 -> 639.15 | S45: 0
C46: 2 | E46: C20976 | F46: DELATORRE | I46: New | J46: 2026 | K46: HONDA | L46: CR-V | M46: SPLIT JOSE TORRES | O46: 4589.8 | P46: 0 | Q46: 0.125 | R46: =O46*Q46 -> 573.725 | S46: 0
C47: 3 | E47: C20540A | F47: DEER/PHILLIPS | I47: Used | J47: 2022 | K47: HONDA | L47: HR-V | M47: SPLIT JOSE TORRES | O47: 2157 | P47: 0 | Q47: 0.125 | R47: =O47*Q47 -> 269.625 | S47: 0
C48: 4 | E48: C20886A | F48: ARCE | I48: Used | J48: 2020 | K48: HONDA | L48: CIVIC | O48: 2000 | P48: 0 | Q48: 0.25 | R48: =O48*Q48 -> 500
P49: 0 | Q49: 0.25 | R49: =O49*Q49 -> 0 | S49: 0
Q50: 0.25 | R50: =O50*Q50 -> 0 | S50: =R50 -> 0
Q51: 0.25 | R51: =O51*Q51 -> 0 | S51: 0
Q52: 0.25 | R52: =O52*Q52 -> 0 | S52: 0
Q53: 0.25 | R53: =O53*Q53 -> 0 | S53: =(O53*0.25)/2 -> 0
Q54: 0.25 | R54: =O54*Q54 -> 0 | S54: =(O54*0.25)/2 -> 0
Q55: 0.25 | R55: =O55*Q55 -> 0 | S55: =(O55*0.25)/2 -> 0
Q56: 0.25 | R56: =O56*Q56 -> 0 | S56: =(O56*0.25)/2 -> 0
Q57: 0.25 | R57: =O57*Q57 -> 0 | S57: =(O57*0.25)/2 -> 0
Q58: 0.25 | R58: =O58*Q58 -> 0 | S58: =(O58*0.25)/2 -> 0
Q59: 0.25 | R59: =O59*Q59 -> 0 | S59: =(O59*0.25)/2 -> 0
Q60: 0.25 | R60: =O60*Q60 -> 0 | S60: =(O60*0.25)/2 -> 0
P61: 0 | Q61: 0.25 | R61: =O61*Q61 -> 0 | S61: =(O61*0.25)/2 -> 0
P62: 0 | Q62: 0.25 | R62: =O62*Q62 -> 0 | S62: =(O62*0.25)/2 -> 0
Q63: 0.25 | R63: =O63*Q63 -> 0 | S63: =(O63*0.25)/2 -> 0
Q64: 0.25 | R64: =O64*Q64 -> 0 | S64: =(O64*0.25)/2 -> 0
Q65: 0.25 | R65: =O65*Q65 -> 0 | S65: =(O65*0.25)/2 -> 0
Q66: 0.25 | R66: =(O66*0.25)/2 -> 0 | S66: =(O66*0.25)/2 -> 0
Q67: 0.25 | R67: =(O67*0.25)/2 -> 0 | S67: =(O67*0.25)/2 -> 0
Q68: 0.25 | R68: =(O68*0.25)/2 -> 0 | S68: =(O68*0.25)/2 -> 0
Q69: 0.25 | R69: =(O69*0.25)/2 -> 0 | S69: =(O69*0.25)/2 -> 0
Q70: 0.25 | R70: =(O70*0.25)/2 -> 0 | S70: =(O70*0.25)/2 -> 0
O71: =SUM(O45:O70) -> 13860 | R71: =SUM(R45:R54) -> 1982.5 | S71: =SUM(S45:S70) -> 0
C72: =SUM(C45:C70) -> 10 | N72: PVR
D76: CHRIS MARTIN
E78: STOCK | F78: CUSTOMER | I78: N/U | J78: Purchase | M78: NOTES | O78: FRONT GROSS | P78: PACK | Q78: COMM % | R78: COMMISSION | S78: SPLIT
J79: Year | K79: Make | L79: Model
C80: 1 | E80: C20630A | F80: TOVAR | I80: Used | J80: 2021 | K80: MAZDA | L80: CX5 | O80: 3175.92 | P80: 0 | Q80: 0.25 | R80: =O80*Q80 -> 793.98 | S80: 0
C81: 2 | E81: DC20936 | F81: ACOSTA SANDOVAL | I81: New | J81: 2026 | K81: HONDA | L81: CIVIC | M81: SPLIT JOSE TORRES | O81: 4117.56 | P81: 0 | Q81: 0.125 | R81: =O81*Q81 -> 514.695 | S81: 0
C82: 3 | E82: C20875 | F82: TAYLOR | I82: New | J82: 2026 | K82: HONDA | L82: CR-V | M82: split with jose | O82: 6856.13 | P82: 0 | Q82: 0.125 | R82: =O82*Q82 -> 857.01625 | S82: 0
C83: 4 | S83: 0
P84: 0 | Q84: 0.25 | R84: =O84*Q84 -> 0 | S84: 0
P85: 0 | Q85: 0.25 | R85: =O85*Q85 -> 0 | S85: 0
P86: 0 | Q86: 0.25 | R86: =O86*Q86 -> 0
C88: 7 | P88: 0 | Q88: 0.25 | R88: =O88*Q88 -> 0
C89: 7 | P89: 0 | Q89: 0.25 | R89: =O89*Q89 -> 0
C90: 7 | Q90: 0.25 | R90: =O90*Q90 -> 0
C91: 7 | Q91: 0.25 | R91: =O91*Q91 -> 0
C92: 7 | Q92: 0.25 | R92: =SUM(O92-P92)*0.25 -> 0 | S92: =(O92*0.25)/2 -> 0
C93: 7 | Q93: 0.25 | R93: =SUM(O93-P93)*0.25 -> 0 | S93: =(O93*0.25)/2 -> 0
C94: 7 | Q94: 0.25 | R94: =SUM(O94-P94)*0.25 -> 0 | S94: =(O94*0.25)/2 -> 0
C95: 7 | Q95: 0.25 | R95: =SUM(O95-P95)*0.25 -> 0 | S95: =(O95*0.25)/2 -> 0
C96: 7 | Q96: 0.25 | R96: =SUM(O96-P96)*0.25 -> 0 | S96: =(O96*0.25)/2 -> 0
C97: 7 | Q97: 0.25 | R97: =SUM(O97-P97)*0.25 -> 0 | S97: =(O97*0.25)/2 -> 0
C98: 7 | Q98: 0.25 | R98: =SUM(O98-P98)*0.25 -> 0 | S98: =(O98*0.25)/2 -> 0
C99: 7 | Q99: 0.25 | R99: =SUM(O99-P99)*0.25 -> 0 | S99: =(O99*0.25)/2 -> 0
C100: 7 | Q100: 0.25 | R100: =SUM(O100-P100)*0.25 -> 0 | S100: =(O100*0.25)/2 -> 0
C101: 7 | Q101: 0.25 | R101: =SUM(O101-P101)*0.25 -> 0 | S101: =(O101*0.25)/2 -> 0
C102: 7 | Q102: 0.25 | R102: =SUM(O102-P102)*0.25 -> 0 | S102: =(O102*0.25)/2 -> 0
C103: 7 | Q103: 0.25 | R103: =SUM(O103-P103)*0.25 -> 0 | S103: =(O103*0.25)/2 -> 0
C104: 7 | Q104: 0.25 | R104: =SUM(O104-P104)*0.25 -> 0 | S104: =(O104*0.25)/2 -> 0
C105: 7 | Q105: 0.25 | R105: =(O105*0.25)/2 -> 0 | S105: =(O105*0.25)/2 -> 0
C106: 7 | Q106: 0.25 | R106: =(O106*0.25)/2 -> 0 | S106: =(O106*0.25)/2 -> 0
C107: 7 | Q107: 0.25 | R107: =(O107*0.25)/2 -> 0 | S107: =(O107*0.25)/2 -> 0
C108: 7 | Q108: 0.25 | R108: =(O108*0.25)/2 -> 0 | S108: =(O108*0.25)/2 -> 0
C109: 7 | Q109: 0.25 | R109: =(O109*0.25)/2 -> 0 | S109: =(O109*0.25)/2 -> 0
C110: 7 | Q110: 0.25 | R110: =(O110*0.25)/2 -> 0 | S110: =(O110*0.25)/2 -> 0
C111: 7 | Q111: 0.25 | R111: =(O111*0.25)/2 -> 0 | S111: =(O111*0.25)/2 -> 0
O112: =SUM(O80:O111) -> 14149.61 | R112: =SUM(R80:R111) -> 2165.6912 | S112: =SUM(S80:S111) -> 0
N113: PVR
D118: JOSE TORRES
D120: Deal # | E120: Stock # | F120: Customer | G120: Customer Zip Code | H120: Source | I120: New/Used | J120: Purchase | M120: NOTES | N120: 2nd Sales Person | O120: Front Gross | P120: PACK | Q120: COMM % | R120: COMMISSION | S120: SPLIT
...

Sheet RECAP
J2: SALES PEOPLE SUMMARY
B3: CHICAGO NORTHSIDE TOYOTA | J3: ='SLSPERSON WASHOUT'!D7 -> BRYAN ROGERS | P3: ='SLSPERSON WASHOUT'!R36 -> 8111.2437
B4: 46054 | J4: ='SLSPERSON WASHOUT'!D41 -> NICK WILEY | P4: ='SLSPERSON WASHOUT'!R71 -> 1982.5
J5: ='SLSPERSON WASHOUT'!D76 -> CHRIS MARTIN | P5: ='SLSPERSON WASHOUT'!R112 -> 2165.6912
C6: TOTAL COMMISSIONABLE GROSS | G6: ='DEAL LOG'!AH57 -> 281580.79 | J6: ='SLSPERSON WASHOUT'!D118 -> JOSE TORRES | P6: ='SLSPERSON WASHOUT'!R148 -> 3596.2913
J7: ='SLSPERSON WASHOUT'!D154 -> MAYCON MIKE GUIMARAES | P7: ='SLSPERSON WASHOUT'!R184 -> 250
C8: JDE COMMISSION 35% | F8: - | G8: =G6*0.35 -> 98553.277 | J8: ='SLSPERSON WASHOUT'!D190 -> MIKE LASHLEY | P8: ='SLSPERSON WASHOUT'!R222 -> 500
J9: ='SLSPERSON WASHOUT'!D226 -> OSSIE SAMPSON | P9: ='SLSPERSON WASHOUT'!R258 -> 557.44125
C10: MARKETING COST | F10: - | G10: 0 | J10: ='SLSPERSON WASHOUT'!D262 -> ABDUL AL TABBAH | P10: ='SLSPERSON WASHOUT'!R292 -> 500
J11: ='SLSPERSON WASHOUT'!D297 -> BRYANT ROGERS | P11: ='SLSPERSON WASHOUT'!R327 -> 2900.8888
C12: NON COMM GROSS- | F12: + | G12: 24664 | J12: ='SLSPERSON WASHOUT'!D335 -> NATE HARDING | P12: ='SLSPERSON WASHOUT'!R353 -> 2027.9175
C13: 600 USED 376 DOC | J13: ='SLSPERSON WASHOUT'!F335 -> IRELAND BARE | P13: ='SLSPERSON WASHOUT'!R353 -> 2027.9175
C14: TOTAL SALE GROSS | G14: =G6+G12 -> 306244.79 | J14: ='SLSPERSON WASHOUT'!D359 -> HALEY DELUDE | P14: ='SLSPERSON WASHOUT'!R389 -> 500
C16: REPS COMMISSIONS | F16: - | G16: =P28 -> 25119.891
C18: VARIABLE NET | F18: - | G18: =G14-G8 -> 207691.51
C20: TOTAL NET | G20: =G14-G8-G16-G22 -> 182571.62
C22: MIS EXPENSES | G22: 0
C23: HELIUM/PRIZE GIVEAWAYS ETC
C25: JDE COMMISSION | G25: =G8 -> 98553.277
C27: 23 NEW 16 USED
J28: TOTAL REPS | P28: =SUM(P3:Q19) -> 25119.891

Sheet REG $ FORM
D1: GIFT REGISTRATION FORM
B3: DATE:
B5: SLS PERSON | C5: FIRST / LAST NAME | D5: CITY | E5: STATE | F5: $$ GIVEN

Sheet PLATE LOG
E2: LIST PLATES BELOW
B3: 395 K | C3: 395 U | D3: 395 O | E3: 395 J | F3: 395 V | G3: 395 T | H3: 395 E
B5: SLS PERSON | C5: CUSTOMER | D5: VEHICLE | E5: PLATE NUMBER | F5: TIME OUT | G5: TIME IN | H5: COMMENTS

Sheet Washout
A1: Salesman: | B1: CHARLIE WINTERS | M1: DANETTE
A2: DEAL# | B2: CUSTOMER | C2: YEAR | D2: MAKE | E2: MODEL | F2: SOURCE | G2: SPLIT | H2: F GROSS | I2: % COMM | J2: PACK | K2: COMM $
K3: =H3*0.25 -> 0 | L3: Full Deals
K4: 500
A5: {=IFERROR(SMALL(IF('Sale Rollup'!$L$2:$L$240=$B$1,ROW('Sale Rollup'!$L$2:$L$240)),ROW(3:3))," ")}
A6: {=IFERROR(SMALL(IF('Sale Rollup'!$L$2:$L$240=$B$1,ROW('Sale Rollup'!$L$2:$L$240)),ROW(4:4))," ")}
A11: {=IFERROR(SMALL(IF('Sale Rollup'!$L$2:$L$240=$B$1,ROW('Sale Rollup'!$L$2:$L$240)),ROW(9:9))," ")}
A12: {=IFERROR(SMALL(IF('Sale Rollup'!$L$2:$L$240=$B$1,ROW('Sale Rollup'!$L$2:$L$240)),ROW(10:10))," ")}
A13: {=IFERROR(SMALL(IF('Sale Rollup'!$L$2:$L$240=$B$1,ROW('Sale Rollup'!$L$2:$L$240)),ROW(11:11))," ")}
A14: {=IFERROR(SMALL(IF('Sale Rollup'!$L$2:$L$240=$B$1,ROW('Sale Rollup'!$L$2:$L$240)),ROW(12:12))," ")}
A15: {=IFERROR(SMALL(IF('Sale Rollup'!$L$2:$L$240=$B$1,ROW('Sale Rollup'!$L$2:$L$240)),ROW(13:13))," ")}
A16: {=IFERROR(SMALL(IF('Sale Rollup'!$L$2:$L$240=$B$1,ROW('Sale Rollup'!$L$2:$L$240)),ROW(14:14))," ")}
A17: {=IFERROR(SMALL(IF('Sale Rollup'!$L$2:$L$240=$B$1,ROW('Sale Rollup'!$L$2:$L$240)),ROW(15:15))," ")}
A18: {=IFERROR(SMALL(IF('Sale Rollup'!$L$2:$L$240=$B$1,ROW('Sale Rollup'!$L$2:$L$240)),ROW(16:16))," ")}
A19: {=IFERROR(SMALL(IF('Sale Rollup'!$L$2:$L$240=$B$1,ROW('Sale Rollup'!$L$2:$L$240)),ROW(17:17))," ")}
A20: {=IFERROR(SMALL(IF('Sale Rollup'!$L$2:$L$240=$B$1,ROW('Sale Rollup'!$L$2:$L$240)),ROW(18:18))," ")}
A21: {=IFERROR(SMALL(IF('Sale Rollup'!$L$2:$L$240=$B$1,ROW('Sale Rollup'!$L$2:$L$240)),ROW(19:19))," ")}
A22: {=IFERROR(SMALL(IF('Sale Rollup'!$L$2:$L$240=$B$1,ROW('Sale Rollup'!$L$2:$L$240)),ROW(20:20))," ")}
A23: {=IFERROR(SMALL(IF('Sale Rollup'!$O$2:$O$240=$B$1,ROW('Sale Rollup'!$L$2:$L$240)),ROW(1:1))," ")} | L23: Split Deals
A24: {=IFERROR(SMALL(IF('Sale Rollup'!$O$2:$O$240=$B$1,ROW('Sale Rollup'!$L$2:$L$240)),ROW(2:2))," ")}
A25: {=IFERROR(SMALL(IF('Sale Rollup'!$O$2:$O$240=$B$1,ROW('Sale Rollup'!$L$2:$L$240)),ROW(3:3))," ")}
A26: {=IFERROR(SMALL(IF('Sale Rollup'!$O$2:$O$240=$B$1,ROW('Sale Rollup'!$L$2:$L$240)),ROW(4:4))," ")}
A27: {=IFERROR(SMALL(IF('Sale Rollup'!$O$2:$O$240=$B$1,ROW('Sale Rollup'!$L$2:$L$240)),ROW(5:5))," ")}
A28: {=IFERROR(SMALL(IF('Sale Rollup'!$O$2:$O$240=$B$1,ROW('Sale Rollup'!$L$2:$L$240)),ROW(6:6))," ")}
A29: {=IFERROR(SMALL(IF('Sale Rollup'!$O$2:$O$240=$B$1,ROW('Sale Rollup'!$L$2:$L$240)),ROW(7:7))," ")}
A30: {=IFERROR(SMALL(IF('Sale Rollup'!$O$2:$O$240=$B$1,ROW('Sale Rollup'!$L$2:$L$240)),ROW(8:8))," ")}
A31: {=IFERROR(SMALL(IF('Sale Rollup'!$O$2:$O$240=$B$1,ROW('Sale Rollup'!$L$2:$L$240)),ROW(9:9))," ")}
A32: {=IFERROR(SMALL(IF('Sale Rollup'!$O$2:$O$240=$B$1,ROW('Sale Rollup'!$L$2:$L$240)),ROW(10:10))," ")}
A33: Deals
A34: =IF('Roster & Tables'!J29=0,"","Pack") | B34: Full | C34: 0 | E34: Split | F34: 8 | K34: =IF('Roster & Tables'!J29=0,"",((C34*'Roster & Tables'!J29)+(F34*('Roster & Tables'!J29/2))))
A35: Total Commission | K35: =SUM(K3:K7) -> 500 | M35: 1572.08
A37: Salesman: | B37: GARY/MIKE
A38: DEAL # | B38: CUSTOMER | C38: YEAR | D38: MAKE | E38: MODEL | F38: SOURCE | G38: SPLIT | H38: F GROSS | I38: % COMM | J38: PACK | K38: COMM $
K39: =H39*0.25 -> 0 | L39: Full Deals
K40: =H40*0.25 -> 0
K41: =(H41*0.65)*0.25 -> 0 | M41: =(H41*0.35)*0.25 -> 0 | N41: DANETTE
K42: =H42*0.25 -> 0
K43: =H43*0.25 -> 0
K44: =H44*0.25 -> 0
K45: =(H45*0.65)*0.25 -> 0 | M45: =(H45*0.35)*0.25 -> 0 | N45: DANETTE
K46: =H46*0.25 -> 0
K47: =H47*0.25 -> 0
K48: =H48*0.25 -> 0
K49: 500
K50: 500
K51: =H51*0.25 -> 0
K52: =H52*0.25 -> 0
K53: =H53*0.25 -> 0
K54: =H54*0.25 -> 0
K55: =H55*0.25 -> 0
K56: =H56*0.25 -> 0
K57: =H57*0.25 -> 0
K58: =H58*0.25 -> 0
K59: =H59*0.25 -> 0 | L59: Split Deals
K60: =H60*0.25 -> 0
K61: =H61*0.25 -> 0
K62: =H62*0.25 -> 0
K63: =H63*0.25 -> 0
K64: =H64*0.25 -> 0
K65: =H65*0.25 -> 0
K66: =H66*0.25 -> 0
K67: =H67*0.25 -> 0
K68: =H68*0.25 -> 0
K69: =H69*0.25 -> 0
A70: =IF('Roster & Tables'!J29=0,"","Pack") | B70: Full | C70: =COUNTIFS('Sale Rollup'!L2:L240,B37,'Sale Rollup'!K2:K240,"No") -> 0 | E70: Split | F70: =COUNTIF('Sale Rollup'!O2:O240,B37)+COUNTIFS('Sale Rollup'!L2:L240,B37,'Sale Rollup'!K2:K240,"Yes") -> 0 | K70: =IF('Roster & Tables'!J29=0,"",((C70*'Roster & Tables'!J29)+(F70*('Roster & Tables'!J29/2))))
A71: Total Commission | K71: =SUM(K39:K68) -> 1000 | M71: 5041.38
A73: Salesman: | B73: ='Roster & Tables'!C4 -> TREVON HALL
A74: Row | B74: Deal # | C74: Customer Name | D74: Year | E74: Make | F74: Model | G74: Source | H74: Front Gross | I74: % Comm | J74: Pack | K74: Comm. $
A75: {=IFERROR(SMALL(IF('Sale Rollup'!$L$2:$L$240=$B$73,ROW('Sale Rollup'!$L$2:$L$240)),ROW(1:1))," ")} | L75: Full Deals
A76: {=IFERROR(SMALL(IF('Sale Rollup'!$L$2:$L$240=$B$73,ROW('Sale Rollup'!$L$2:$L$240)),ROW(2:2))," ")} | B76: {=IFERROR(INDEX('Sale Rollup'!$B$2:$AA$240,SMALL(IF('Sale Rollup'!$L$2:$L$240=$B$73,ROW('Sale Rollup'!$L$2:$L$240)),ROW(2:2))-1,1)," ")} | C76: {=IFERROR(INDEX('Sale Rollup'!$B$2:$AA$240,SMALL(IF('Sale Rollup'!$L$2:$L$240=$B$73,ROW('Sale Rollup'!$L$2:$L$240)),ROW(2:2))-1,2)," ")} | D76: {=IFERROR(INDEX('Sale Rollup'!$B$2:$AA$240,SMALL(IF('Sale Rollup'!$L$2:$L$240=$B$73,ROW('Sale Rollup'!$L$2:$L$240)),ROW(2:2))-1,5)," ")} | E76: {=IFERROR( INDEX('Sale Rollup'!$B$2:$AA$240,SMALL(IF('Sale Rollup'!$L$2:$L$240=$B$73,ROW('Sale Rollup'!$L$2:$L$240)),ROW(2:2))-1,6)," ")} | F76: {=IFERROR(INDEX('Sale Rollup'!$B$2:$AA$240,SMALL(IF('Sale Rollup'!$L$2:$L$240=$B$73,ROW('Sale Rollup'!$L$2:$L$240)),ROW(2:2))-1,7)," ")} | G76: {=IFERROR(INDEX('Sale Rollup'!$B$2:$AA$240,SMALL(IF('Sale Rollup'!$L$2:$L$240=$B$73,ROW('Sale Rollup'!$L$2:$L$240)),ROW(2:2))-1,3)," ")} | H76: {=IFERROR(INDEX('Sale Rollup'!$B$2:$AA$240,SMALL(IF('Sale Rollup'!$L$2:$L$240=$B$73,ROW('Sale Rollup'!$L$2:$L$240)),ROW(2:2))-1,8)," ")} | I76: {=IFERROR(INDEX('Sale Rollup'!$B$2:$AA$240,SMALL(IF('Sale Rollup'!$L$2:$L$240=$B$73,ROW('Sale Rollup'!$L$2:$L$240)),ROW(2:2))-1,12)," ")}
A77: {=IFERROR(SMALL(IF('Sale Rollup'!$L$2:$L$240=$B$73,ROW('Sale Rollup'!$L$2:$L$240)),ROW(3:3))," ")} | B77: {=IFERROR(INDEX('Sale Rollup'!$B$2:$AA$240,SMALL(IF('Sale Rollup'!$L$2:$L$240=$B$73,ROW('Sale Rollup'!$L$2:$L$240)),ROW(3:3))-1,1)," ")} | C77: {=IFERROR(INDEX('Sale Rollup'!$B$2:$AA$240,SMALL(IF('Sale Rollup'!$L$2:$L$240=$B$73,ROW('Sale Rollup'!$L$2:$L$240)),ROW(3:3))-1,2)," ")} | D77: {=IFERROR(INDEX('Sale Rollup'!$B$2:$AA$240,SMALL(IF('Sale Rollup'!$L$2:$L$240=$B$73,ROW('Sale Rollup'!$L$2:$L$240)),ROW(3:3))-1,5)," ")} | E77: {=IFERROR( INDEX('Sale Rollup'!$B$2:$AA$240,SMALL(IF('Sale Rollup'!$L$2:$L$240=$B$73,ROW('Sale Rollup'!$L$2:$L$240)),ROW(3:3))-1,6)," ")} | F77: {=IFERROR(INDEX('Sale Rollup'!$B$2:$AA$240,SMALL(IF('Sale Rollup'!$L$2:$L$240=$B$73,ROW('Sale Rollup'!$L$2:$L$240)),ROW(3:3))-1,7)," ")} | G77: {=IFERROR(INDEX('Sale Rollup'!$B$2:$AA$240,SMALL(IF('Sale Rollup'!$L$2:$L$240=$B$73,ROW('Sale Rollup'!$L$2:$L$240)),ROW(3:3))-1,3)," ")} | H77: {=IFERROR(INDEX('Sale Rollup'!$B$2:$AA$240,SMALL(IF('Sale Rollup'!$L$2:$L$240=$B$73,ROW('Sale Rollup'!$L$2:$L$240)),ROW(3:3))-1,8)," ")} | I77: {=IFERROR(INDEX('Sale Rollup'!$B$2:$AA$240,SMALL(IF('Sale Rollup'!$L$2:$L$240=$B$73,ROW('Sale Rollup'!$L$2:$L$240)),ROW(3:3))-1,12)," ")} | K77: {=IFERROR(INDEX('Sale Rollup'!$B$2:$AA$240,SMALL(IF('Sale Rollup'!$L$2:$L$240=$B$73,ROW('Sale Rollup'!$L$2:$L$240)),ROW(3:3))-1,13)," ")}
A78: {=IFERROR(SMALL(IF('Sale Rollup'!$L$2:$L$240=$B$73,ROW('Sale Rollup'!$L$2:$L$240)),ROW(4:4))," ")} | B78: {=IFERROR(INDEX('Sale Rollup'!$B$2:$AA$240,SMALL(IF('Sale Rollup'!$L$2:$L$240=$B$73,ROW('Sale Rollup'!$L$2:$L$240)),ROW(4:4))-1,1)," ")} | C78: {=IFERROR(INDEX('Sale Rollup'!$B$2:$AA$240,SMALL(IF('Sale Rollup'!$L$2:$L$240=$B$73,ROW('Sale Rollup'!$L$2:$L$240)),ROW(4:4))-1,2)," ")} | D78: {=IFERROR(INDEX('Sale Rollup'!$B$2:$AA$240,SMALL(IF('Sale Rollup'!$L$2:$L$240=$B$73,ROW('Sale Rollup'!$L$2:$L$240)),ROW(4:4))-1,5)," ")} | E78: {=IFERROR( INDEX('Sale Rollup'!$B$2:$AA$240,SMALL(IF('Sale Rollup'!$L$2:$L$240=$B$73,ROW('Sale Rollup'!$L$2:$L$240)),ROW(4:4))-1,6)," ")} | F78: {=IFERROR(INDEX('Sale Rollup'!$B$2:$AA$240,SMALL(IF('Sale Rollup'!$L$2:$L$240=$B$73,ROW('Sale Rollup'!$L$2:$L$240)),ROW(4:4))-1,7)," ")} | G78: {=IFERROR(INDEX('Sale Rollup'!$B$2:$AA$240,SMALL(IF('Sale Rollup'!$L$2:$L$240=$B$73,ROW('Sale Rollup'!$L$2:$L$240)),ROW(4:4))-1,3)," ")} | H78: {=IFERROR(INDEX('Sale Rollup'!$B$2:$AA$240,SMALL(IF('Sale Rollup'!$L$2:$L$240=$B$73,ROW('Sale Rollup'!$L$2:$L$240)),ROW(4:4))-1,8)," ")} | I78: {=IFERROR(INDEX('Sale Rollup'!$B$2:$AA$240,SMALL(IF('Sale Rollup'!$L$2:$L$240=$B$73,ROW('Sale Rollup'!$L$2:$L$240)),ROW(4:4))-1,12)," ")} | K78: {=IFERROR(INDEX('Sale Rollup'!$B$2:$AA$240,SMALL(IF('Sale Rollup'!$L$2:$L$240=$B$73,ROW('Sale Rollup'!$L$2:$L$240)),ROW(4:4))-1,13)," ")}
A79: {=IFERROR(SMALL(IF('Sale Rollup'!$L$2:$L$240=$B$73,ROW('Sale Rollup'!$L$2:$L$240)),ROW(5:5))," ")} | B79: {=IFERROR(INDEX('Sale Rollup'!$B$2:$AA$240,SMALL(IF('Sale Rollup'!$L$2:$L$240=$B$73,ROW('Sale Rollup'!$L$2:$L$240)),ROW(5:5))-1,1)," ")} | C79: {=IFERROR(INDEX('Sale Rollup'!$B$2:$AA$240,SMALL(IF('Sale Rollup'!$L$2:$L$240=$B$73,ROW('Sale Rollup'!$L$2:$L$240)),ROW(5:5))-1,2)," ")} | D79: {=IFERROR(INDEX('Sale Rollup'!$B$2:$AA$240,SMALL(IF('Sale Rollup'!$L$2:$L$240=$B$73,ROW('Sale Rollup'!$L$2:$L$240)),ROW(5:5))-1,5)," ")} | E79: {=IFERROR( INDEX('Sale Rollup'!$B$2:$AA$240,SMALL(IF('Sale Rollup'!$L$2:$L$240=$B$73,ROW('Sale Rollup'!$L$2:$L$240)),ROW(5:5))-1,6)," ")} | F79: {=IFERROR(INDEX('Sale Rollup'!$B$2:$AA$240,SMALL(IF('Sale Rollup'!$L$2:$L$240=$B$73,ROW('Sale Rollup'!$L$2:$L$240)),ROW(5:5))-1,7)," ")} | G79: {=IFERROR(INDEX('Sale Rollup'!$B$2:$AA$240,SMALL(IF('Sale Rollup'!$L$2:$L$240=$B$73,ROW('Sale Rollup'!$L$2:$L$240)),ROW(5:5))-1,3)," ")} | H79: {=IFERROR(INDEX('Sale Rollup'!$B$2:$AA$240,SMALL(IF('Sale Rollup'!$L$2:$L$240=$B$73,ROW('Sale Rollup'!$L$2:$L$240)),ROW(5:5))-1,8)," ")} | I79: {=IFERROR(INDEX('Sale Rollup'!$B$2:$AA$240,SMALL(IF('Sale Rollup'!$L$2:$L$240=$B$73,ROW('Sale Rollup'!$L$2:$L$240)),ROW(5:5))-1,12)," ")} | K79: {=IFERROR(INDEX('Sale Rollup'!$B$2:$AA$240,SMALL(IF('Sale Rollup'!$L$2:$L$240=$B$73,ROW('Sale Rollup'!$L$2:$L$240)),ROW(5:5))-1,13)," ")}
A80: {=IFERROR(SMALL(IF('Sale Rollup'!$L$2:$L$240=$B$73,ROW('Sale Rollup'!$L$2:$L$240)),ROW(6:6))," ")} | B80: {=IFERROR(INDEX('Sale Rollup'!$B$2:$AA$240,SMALL(IF('Sale Rollup'!$L$2:$L$240=$B$73,ROW('Sale Rollup'!$L$2:$L$240)),ROW(6:6))-1,1)," ")} | C80: {=IFERROR(INDEX('Sale Rollup'!$B$2:$AA$240,SMALL(IF('Sale Rollup'!$L$2:$L$240=$B$73,ROW('Sale Rollup'!$L$2:$L$240)),ROW(6:6))-1,2)," ")} | D80: {=IFERROR(INDEX('Sale Rollup'!$B$2:$AA$240,SMALL(IF('Sale Rollup'!$L$2:$L$240=$B$73,ROW('Sale Rollup'!$L$2:$L$240)),ROW(6:6))-1,5)," ")} | E80: {=IFERROR( INDEX('Sale Rollup'!$B$2:$AA$240,SMALL(IF('Sale Rollup'!$L$2:$L$240=$B$73,ROW('Sale Rollup'!$L$2:$L$240)),ROW(6:6))-1,6)," ")} | F80: {=IFERROR(INDEX('Sale Rollup'!$B$2:$AA$240,SMALL(IF('Sale Rollup'!$L$2:$L$240=$B$73,ROW('Sale Rollup'!$L$2:$L$240)),ROW(6:6))-1,7)," ")} | G80: {=IFERROR(INDEX('Sale Rollup'!$B$2:$AA$240,SMALL(IF('Sale Rollup'!$L$2:$L$240=$B$73,ROW('Sale Rollup'!$L$2:$L$240)),ROW(6:6))-1,3)," ")} | H80: {=IFERROR(INDEX('Sale Rollup'!$B$2:$AA$240,SMALL(IF('Sale Rollup'!$L$2:$L$240=$B$73,ROW('Sale Rollup'!$L$2:$L$240)),ROW(6:6))-1,8)," ")} | I80: {=IFERROR(INDEX('Sale Rollup'!$B$2:$AA$240,SMALL(IF('Sale Rollup'!$L$2:$L$240=$B$73,ROW('Sale Rollup'!$L$2:$L$240)),ROW(6:6))-1,12)," ")} | K80: {=IFERROR(INDEX('Sale Rollup'!$B$2:$AA$240,SMALL(IF('Sale Rollup'!$L$2:$L$240=$B$73,ROW('Sale Rollup'!$L$2:$L$240)),ROW(6:6))-1,13)," ")}
A81: {=IFERROR(SMALL(IF('Sale Rollup'!$L$2:$L$240=$B$73,ROW('Sale Rollup'!$L$2:$L$240)),ROW(7:7))," ")} | B81: {=IFERROR(INDEX('Sale Rollup'!$B$2:$AA$240,SMALL(IF('Sale Rollup'!$L$2:$L$240=$B$73,ROW('Sale Rollup'!$L$2:$L$240)),ROW(7:7))-1,1)," ")} | C81: {=IFERROR(INDEX('Sale Rollup'!$B$2:$AA$240,SMALL(IF('Sale Rollup'!$L$2:$L$240=$B$73,ROW('Sale Rollup'!$L$2:$L$240)),ROW(7:7))-1,2)," ")} | D81: {=IFERROR(INDEX('Sale Rollup'!$B$2:$AA$240,SMALL(IF('Sale Rollup'!$L$2:$L$240=$B$73,ROW('Sale Rollup'!$L$2:$L$240)),ROW(7:7))-1,5)," ")} | E81: {=IFERROR( INDEX('Sale Rollup'!$B$2:$AA$240,SMALL(IF('Sale Rollup'!$L$2:$L$240=$B$73,ROW('Sale Rollup'!$L$2:$L$240)),ROW(7:7))-1,6)," ")} | F81: {=IFERROR(INDEX('Sale Rollup'!$B$2:$AA$240,SMALL(IF('Sale Rollup'!$L$2:$L$240=$B$73,ROW('Sale Rollup'!$L$2:$L$240)),ROW(7:7))-1,7)," ")} | G81: {=IFERROR(INDEX('Sale Rollup'!$B$2:$AA$240,SMALL(IF('Sale Rollup'!$L$2:$L$240=$B$73,ROW('Sale Rollup'!$L$2:$L$240)),ROW(7:7))-1,3)," ")} | H81: {=IFERROR(INDEX('Sale Rollup'!$B$2:$AA$240,SMALL(IF('Sale Rollup'!$L$2:$L$240=$B$73,ROW('Sale Rollup'!$L$2:$L$240)),ROW(7:7))-1,8)," ")} | I81: {=IFERROR(INDEX('Sale Rollup'!$B$2:$AA$240,SMALL(IF('Sale Rollup'!$L$2:$L$240=$B$73,ROW('Sale Rollup'!$L$2:$L$240)),ROW(7:7))-1,12)," ")} | K81: {=IFERROR(INDEX('Sale Rollup'!$B$2:$AA$240,SMALL(IF('Sale Rollup'!$L$2:$L$240=$B$73,ROW('Sale Rollup'!$L$2:$L$240)),ROW(7:7))-1,13)," ")}
A82: {=IFERROR(SMALL(IF('Sale Rollup'!$L$2:$L$240=$B$73,ROW('Sale Rollup'!$L$2:$L$240)),ROW(8:8))," ")} | B82: {=IFERROR(INDEX('Sale Rollup'!$B$2:$AA$240,SMALL(IF('Sale Rollup'!$L$2:$L$240=$B$73,ROW('Sale Rollup'!$L$2:$L$240)),ROW(8:8))-1,1)," ")} | C82: {=IFERROR(INDEX('Sale Rollup'!$B$2:$AA$240,SMALL(IF('Sale Rollup'!$L$2:$L$240=$B$73,ROW('Sale Rollup'!$L$2:$L$240)),ROW(8:8))-1,2)," ")} | D82: {=IFERROR(INDEX('Sale Rollup'!$B$2:$AA$240,SMALL(IF('Sale Rollup'!$L$2:$L$240=$B$73,ROW('Sale Rollup'!$L$2:$L$240)),ROW(8:8))-1,5)," ")} | E82: {=IFERROR( INDEX('Sale Rollup'!$B$2:$AA$240,SMALL(IF('Sale Rollup'!$L$2:$L$240=$B$73,ROW('Sale Rollup'!$L$2:$L$240)),ROW(8:8))-1,6)," ")} | F82: {=IFERROR(INDEX('Sale Rollup'!$B$2:$AA$240,SMALL(IF('Sale Rollup'!$L$2:$L$240=$B$73,ROW('Sale Rollup'!$L$2:$L$240)),ROW(8:8))-1,7)," ")} | G82: {=IFERROR(INDEX('Sale Rollup'!$B$2:$AA$240,SMALL(IF('Sale Rollup'!$L$2:$L$240=$B$73,ROW('Sale Rollup'!$L$2:$L$240)),ROW(8:8))-1,3)," ")} | H82: {=IFERROR(INDEX('Sale Rollup'!$B$2:$AA$240,SMALL(IF('Sale Rollup'!$L$2:$L$240=$B$73,ROW('Sale Rollup'!$L$2:$L$240)),ROW(8:8))-1,8)," ")} | I82: {=IFERROR(INDEX('Sale Rollup'!$B$2:$AA$240,SMALL(IF('Sale Rollup'!$L$2:$L$240=$B$73,ROW('Sale Rollup'!$L$2:$L$240)),ROW(8:8))-1,12)," ")} | K82: {=IFERROR(INDEX('Sale Rollup'!$B$2:$AA$240,SMALL(IF('Sale Rollup'!$L$2:$L$240=$B$73,ROW('Sale Rollup'!$L$2:$L$240)),ROW(8:8))-1,13)," ")}
A83: {=IFERROR(SMALL(IF('Sale Rollup'!$L$2:$L$240=$B$73,ROW('Sale Rollup'!$L$2:$L$240)),ROW(9:9))," ")} | B83: {=IFERROR(INDEX('Sale Rollup'!$B$2:$AA$240,SMALL(IF('Sale Rollup'!$L$2:$L$240=$B$73,ROW('Sale Rollup'!$L$2:$L$240)),ROW(9:9))-1,1)," ")} | C83: {=IFERROR(INDEX('Sale Rollup'!$B$2:$AA$240,SMALL(IF('Sale Rollup'!$L$2:$L$240=$B$73,ROW('Sale Rollup'!$L$2:$L$240)),ROW(9:9))-1,2)," ")} | D83: {=IFERROR(INDEX('Sale Rollup'!$B$2:$AA$240,SMALL(IF('Sale Rollup'!$L$2:$L$240=$B$73,ROW('Sale Rollup'!$L$2:$L$240)),ROW(9:9))-1,5)," ")} | E83: {=IFERROR( INDEX('Sale Rollup'!$B$2:$AA$240,SMALL(IF('Sale Rollup'!$L$2:$L$240=$B$73,ROW('Sale Rollup'!$L$2:$L$240)),ROW(9:9))-1,6)," ")} | F83: {=IFERROR(INDEX('Sale Rollup'!$B$2:$AA$240,SMALL(IF('Sale Rollup'!$L$2:$L$240=$B$73,ROW('Sale Rollup'!$L$2:$L$240)),ROW(9:9))-1,7)," ")} | G83: {=IFERROR(INDEX('Sale Rollup'!$B$2:$AA$240,SMALL(IF('Sale Rollup'!$L$2:$L$240=$B$73,ROW('Sale Rollup'!$L$2:$L$240)),ROW(9:9))-1,3)," ")} | H83: {=IFERROR(INDEX('Sale Rollup'!$B$2:$AA$240,SMALL(IF('Sale Rollup'!$L$2:$L$240=$B$73,ROW('Sale Rollup'!$L$2:$L$240)),ROW(9:9))-1,8)," ")} | I83: {=IFERROR(INDEX('Sale Rollup'!$B$2:$AA$240,SMALL(IF('Sale Rollup'!$L$2:$L$240=$B$73,ROW('Sale Rollup'!$L$2:$L$240)),ROW(9:9))-1,12)," ")} | K83: {=IFERROR(INDEX('Sale Rollup'!$B$2:$AA$240,SMALL(IF('Sale Rollup'!$L$2:$L$240=$B$73,ROW('Sale Rollup'!$L$2:$L$240)),ROW(9:9))-1,13)," ")}
A84: {=IFERROR(SMALL(IF('Sale Rollup'!$L$2:$L$240=$B$73,ROW('Sale Rollup'!$L$2:$L$240)),ROW(10:10))," ")} | B84: {=IFERROR(INDEX('Sale Rollup'!$B$2:$AA$240,SMALL(IF('Sale Rollup'!$L$2:$L$240=$B$73,ROW('Sale Rollup'!$L$2:$L$240)),ROW(10:10))-1,1)," ")} | C84: {=IFERROR(INDEX('Sale Rollup'!$B$2:$AA$240,SMALL(IF('Sale Rollup'!$L$2:$L$240=$B$73,ROW('Sale Rollup'!$L$2:$L$240)),ROW(10:10))-1,2)," ")} | D84: {=IFERROR(INDEX('Sale Rollup'!$B$2:$AA$240,SMALL(IF('Sale Rollup'!$L$2:$L$240=$B$73,ROW('Sale Rollup'!$L$2:$L$240)),ROW(10:10))-1,5)," ")} | E84: {=IFERROR( INDEX('Sale Rollup'!$B$2:$AA$240,SMALL(IF('Sale Rollup'!$L$2:$L$240=$B$73,ROW('Sale Rollup'!$L$2:$L$240)),ROW(10:10))-1,6)," ")} | F84: {=IFERROR(INDEX('Sale Rollup'!$B$2:$AA$240,SMALL(IF('Sale Rollup'!$L$2:$L$240=$B$73,ROW('Sale Rollup'!$L$2:$L$240)),ROW(10:10))-1,7)," ")} | G84: {=IFERROR(INDEX('Sale Rollup'!$B$2:$AA$240,SMALL(IF('Sale Rollup'!$L$2:$L$240=$B$73,ROW('Sale Rollup'!$L$2:$L$240)),ROW(10:10))-1,3)," ")} | H84: {=IFERROR(INDEX('Sale Rollup'!$B$2:$AA$240,SMALL(IF('Sale Rollup'!$L$2:$L$240=$B$73,ROW('Sale Rollup'!$L$2:$L$240)),ROW(10:10))-1,8)," ")} | I84: {=IFERROR(INDEX('Sale Rollup'!$B$2:$AA$240,SMALL(IF('Sale Rollup'!$L$2:$L$240=$B$73,ROW('Sale Rollup'!$L$2:$L$240)),ROW(10:10))-1,12)," ")} | K84: {=IFERROR(INDEX('Sale Rollup'!$B$2:$AA$240,SMALL(IF('Sale Rollup'!$L$2:$L$240=$B$73,ROW('Sale Rollup'!$L$2:$L$240)),ROW(10:10))-1,13)," ")}
A85: {=IFERROR(SMALL(IF('Sale Rollup'!$L$2:$L$240=$B$73,ROW('Sale Rollup'!$L$2:$L$240)),ROW(11:11))," ")} | B85: {=IFERROR(INDEX('Sale Rollup'!$B$2:$AA$240,SMALL(IF('Sale Rollup'!$L$2:$L$240=$B$73,ROW('Sale Rollup'!$L$2:$L$240)),ROW(11:11))-1,1)," ")} | C85: {=IFERROR(INDEX('Sale Rollup'!$B$2:$AA$240,SMALL(IF('Sale Rollup'!$L$2:$L$240=$B$73,ROW('Sale Rollup'!$L$2:$L$240)),ROW(11:11))-1,2)," ")} | D85: {=IFERROR(INDEX('Sale Rollup'!$B$2:$AA$240,SMALL(IF('Sale Rollup'!$L$2:$L$240=$B$73,ROW('Sale Rollup'!$L$2:$L$240)),ROW(11:11))-1,5)," ")} | E85: {=IFERROR( INDEX('Sale Rollup'!$B$2:$AA$240,SMALL(IF('Sale Rollup'!$L$2:$L$240=$B$73,ROW('Sale Rollup'!$L$2:$L$240)),ROW(11:11))-1,6)," ")} | F85: {=IFERROR(INDEX('Sale Rollup'!$B$2:$AA$240,SMALL(IF('Sale Rollup'!$L$2:$L$240=$B$73,ROW('Sale Rollup'!$L$2:$L$240)),ROW(11:11))-1,7)," ")} | G85: {=IFERROR(INDEX('Sale Rollup'!$B$2:$AA$240,SMALL(IF('Sale Rollup'!$L$2:$L$240=$B$73,ROW('Sale Rollup'!$L$2:$L$240)),ROW(11:11))-1,3)," ")} | H85: {=IFERROR(INDEX('Sale Rollup'!$B$2:$AA$240,SMALL(IF('Sale Rollup'!$L$2:$L$240=$B$73,ROW('Sale Rollup'!$L$2:$L$240)),ROW(11:11))-1,8)," ")} | I85: {=IFERROR(INDEX('Sale Rollup'!$B$2:$AA$240,SMALL(IF('Sale Rollup'!$L$2:$L$240=$B$73,ROW('Sale Rollup'!$L$2:$L$240)),ROW(11:11))-1,12)," ")} | K85: {=IFERROR(INDEX('Sale Rollup'!$B$2:$AA$240,SMALL(IF('Sale Rollup'!$L$2:$L$240=$B$73,ROW('Sale Rollup'!$L$2:$L$240)),ROW(11:11))-1,13)," ")}
A86: {=IFERROR(SMALL(IF('Sale Rollup'!$L$2:$L$240=$B$73,ROW('Sale Rollup'!$L$2:$L$240)),ROW(12:12))," ")} | B86: {=IFERROR(INDEX('Sale Rollup'!$B$2:$AA$240,SMALL(IF('Sale Rollup'!$L$2:$L$240=$B$73,ROW('Sale Rollup'!$L$2:$L$240)),ROW(12:12))-1,1)," ")} | C86: {=IFERROR(INDEX('Sale Rollup'!$B$2:$AA$240,SMALL(IF('Sale Rollup'!$L$2:$L$240=$B$73,ROW('Sale Rollup'!$L$2:$L$240)),ROW(12:12))-1,2)," ")} | D86: {=IFERROR(INDEX('Sale Rollup'!$B$2:$AA$240,SMALL(IF('Sale Rollup'!$L$2:$L$240=$B$73,ROW('Sale Rollup'!$L$2:$L$240)),ROW(12:12))-1,5)," ")} | E86: {=IFERROR( INDEX('Sale Rollup'!$B$2:$AA$240,SMALL(IF('Sale Rollup'!$L$2:$L$240=$B$73,ROW('Sale Rollup'!$L$2:$L$240)),ROW(12:12))-1,6)," ")} | F86: {=IFERROR(INDEX('Sale Rollup'!$B$2:$AA$240,SMALL(IF('Sale Rollup'!$L$2:$L$240=$B$73,ROW('Sale Rollup'!$L$2:$L$240)),ROW(12:12))-1,7)," ")} | G86: {=IFERROR(INDEX('Sale Rollup'!$B$2:$AA$240,SMALL(IF('Sale Rollup'!$L$2:$L$240=$B$73,ROW('Sale Rollup'!$L$2:$L$240)),ROW(12:12))-1,3)," ")} | H86: {=IFERROR(INDEX('Sale Rollup'!$B$2:$AA$240,SMALL(IF('Sale Rollup'!$L$2:$L$240=$B$73,ROW('Sale Rollup'!$L$2:$L$240)),ROW(12:12))-1,8)," ")} | I86: {=IFERROR(INDEX('Sale Rollup'!$B$2:$AA$240,SMALL(IF('Sale Rollup'!$L$2:$L$240=$B$73,ROW('Sale Rollup'!$L$2:$L$240)),ROW(12:12))-1,12)," ")} | K86: {=IFERROR(INDEX('Sale Rollup'!$B$2:$AA$240,SMALL(IF('Sale Rollup'!$L$2:$L$240=$B$73,ROW('Sale Rollup'!$L$2:$L$240)),ROW(12:12))-1,13)," ")}
A87: {=IFERROR(SMALL(IF('Sale Rollup'!$L$2:$L$240=$B$73,ROW('Sale Rollup'!$L$2:$L$240)),ROW(13:13))," ")} | B87: {=IFERROR(INDEX('Sale Rollup'!$B$2:$AA$240,SMALL(IF('Sale Rollup'!$L$2:$L$240=$B$73,ROW('Sale Rollup'!$L$2:$L$240)),ROW(13:13))-1,1)," ")} | C87: {=IFERROR(INDEX('Sale Rollup'!$B$2:$AA$240,SMALL(IF('Sale Rollup'!$L$2:$L$240=$B$73,ROW('Sale Rollup'!$L$2:$L$240)),ROW(13:13))-1,2)," ")} | D87: {=IFERROR(INDEX('Sale Rollup'!$B$2:$AA$240,SMALL(IF('Sale Rollup'!$L$2:$L$240=$B$73,ROW('Sale Rollup'!$L$2:$L$240)),ROW(13:13))-1,5)," ")} | E87: {=IFERROR( INDEX('Sale Rollup'!$B$2:$AA$240,SMALL(IF('Sale Rollup'!$L$2:$L$240=$B$73,ROW('Sale Rollup'!$L$2:$L$240)),ROW(13:13))-1,6)," ")} | F87: {=IFERROR(INDEX('Sale Rollup'!$B$2:$AA$240,SMALL(IF('Sale Rollup'!$L$2:$L$240=$B$73,ROW('Sale Rollup'!$L$2:$L$240)),ROW(13:13))-1,7)," ")} | G87: {=IFERROR(INDEX('Sale Rollup'!$B$2:$AA$240,SMALL(IF('Sale Rollup'!$L$2:$L$240=$B$73,ROW('Sale Rollup'!$L$2:$L$240)),ROW(13:13))-1,3)," ")} | H87: {=IFERROR(INDEX('Sale Rollup'!$B$2:$AA$240,SMALL(IF('Sale Rollup'!$L$2:$L$240=$B$73,ROW('Sale Rollup'!$L$2:$L$240)),ROW(13:13))-1,8)," ")} | I87: {=IFERROR(INDEX('Sale Rollup'!$B$2:$AA$240,SMALL(IF('Sale Rollup'!$L$2:$L$240=$B$73,ROW('Sale Rollup'!$L$2:$L$240)),ROW(13:13))-1,12)," ")} | K87: {=IFERROR(INDEX('Sale Rollup'!$B$2:$AA$240,SMALL(IF('Sale Rollup'!$L$2:$L$240=$B$73,ROW('Sale Rollup'!$L$2:$L$240)),ROW(13:13))-1,13)," ")}
A88: {=IFERROR(SMALL(IF('Sale Rollup'!$L$2:$L$240=$B$73,ROW('Sale Rollup'!$L$2:$L$240)),ROW(14:14))," ")} | B88: {=IFERROR(INDEX('Sale Rollup'!$B$2:$AA$240,SMALL(IF('Sale Rollup'!$L$2:$L$240=$B$73,ROW('Sale Rollup'!$L$2:$L$240)),ROW(14:14))-1,1)," ")} | C88: {=IFERROR(INDEX('Sale Rollup'!$B$2:$AA$240,SMALL(IF('Sale Rollup'!$L$2:$L$240=$B$73,ROW('Sale Rollup'!$L$2:$L$240)),ROW(14:14))-1,2)," ")} | D88: {=IFERROR(INDEX('Sale Rollup'!$B$2:$AA$240,SMALL(IF('Sale Rollup'!$L$2:$L$240=$B$73,ROW('Sale Rollup'!$L$2:$L$240)),ROW(14:14))-1,5)," ")} | E88: {=IFERROR( INDEX('Sale Rollup'!$B$2:$AA$240,SMALL(IF('Sale Rollup'!$L$2:$L$240=$B$73,ROW('Sale Rollup'!$L$2:$L$240)),ROW(14:14))-1,6)," ")} | F88: {=IFERROR(INDEX('Sale Rollup'!$B$2:$AA$240,SMALL(IF('Sale Rollup'!$L$2:$L$240=$B$73,ROW('Sale Rollup'!$L$2:$L$240)),ROW(14:14))-1,7)," ")} | G88: {=IFERROR(INDEX('Sale Rollup'!$B$2:$AA$240,SMALL(IF('Sale Rollup'!$L$2:$L$240=$B$73,ROW('Sale Rollup'!$L$2:$L$240)),ROW(14:14))-1,3)," ")} | H88: {=IFERROR(INDEX('Sale Rollup'!$B$2:$AA$240,SMALL(IF('Sale Rollup'!$L$2:$L$240=$B$73,ROW('Sale Rollup'!$L$2:$L$240)),ROW(14:14))-1,8)," ")} | I88: {=IFERROR(INDEX('Sale Rollup'!$B$2:$AA$240,SMALL(IF('Sale Rollup'!$L$2:$L$240=$B$73,ROW('Sale Rollup'!$L$2:$L$240)),ROW(14:14))-1,12)," ")} | K88: {=IFERROR(INDEX('Sale Rollup'!$B$2:$AA$240,SMALL(IF('Sale Rollup'!$L$2:$L$240=$B$73,ROW('Sale Rollup'!$L$2:$L$240)),ROW(14:14))-1,13)," ")}
A89: {=IFERROR(SMALL(IF('Sale Rollup'!$L$2:$L$240=$B$73,ROW('Sale Rollup'!$L$2:$L$240)),ROW(15:15))," ")} | B89: {=IFERROR(INDEX('Sale Rollup'!$B$2:$AA$240,SMALL(IF('Sale Rollup'!$L$2:$L$240=$B$73,ROW('Sale Rollup'!$L$2:$L$240)),ROW(15:15))-1,1)," ")} | C89: {=IFERROR(INDEX('Sale Rollup'!$B$2:$AA$240,SMALL(IF('Sale Rollup'!$L$2:$L$240=$B$73,ROW('Sale Rollup'!$L$2:$L$240)),ROW(15:15))-1,2)," ")} | D89: {=IFERROR(INDEX('Sale Rollup'!$B$2:$AA$240,SMALL(IF('Sale Rollup'!$L$2:$L$240=$B$73,ROW('Sale Rollup'!$L$2:$L$240)),ROW(15:15))-1,5)," ")} | E89: {=IFERROR( INDEX('Sale Rollup'!$B$2:$AA$240,SMALL(IF('Sale Rollup'!$L$2:$L$240=$B$73,ROW('Sale Rollup'!$L$2:$L$240)),ROW(15:15))-1,6)," ")} | F89: {=IFERROR(INDEX('Sale Rollup'!$B$2:$AA$240,SMALL(IF('Sale Rollup'!$L$2:$L$240=$B$73,ROW('Sale Rollup'!$L$2:$L$240)),ROW(15:15))-1,7)," ")} | G89: {=IFERROR(INDEX('Sale Rollup'!$B$2:$AA$240,SMALL(IF('Sale Rollup'!$L$2:$L$240=$B$73,ROW('Sale Rollup'!$L$2:$L$240)),ROW(15:15))-1,3)," ")} | H89: {=IFERROR(INDEX('Sale Rollup'!$B$2:$AA$240,SMALL(IF('Sale Rollup'!$L$2:$L$240=$B$73,ROW('Sale Rollup'!$L$2:$L$240)),ROW(15:15))-1,8)," ")} | I89: {=IFERROR(INDEX('Sale Rollup'!$B$2:$AA$240,SMALL(IF('Sale Rollup'!$L$2:$L$240=$B$73,ROW('Sale Rollup'!$L$2:$L$240)),ROW(15:15))-1,12)," ")} | K89: {=IFERROR(INDEX('Sale Rollup'!$B$2:$AA$240,SMALL(IF('Sale Rollup'!$L$2:$L$240=$B$73,ROW('Sale Rollup'!$L$2:$L$240)),ROW(15:15))-1,13)," ")}
A90: {=IFERROR(SMALL(IF('Sale Rollup'!$L$2:$L$240=$B$73,ROW('Sale Rollup'!$L$2:$L$240)),ROW(16:16))," ")} | B90: {=IFERROR(INDEX('Sale Rollup'!$B$2:$AA$240,SMALL(IF('Sale Rollup'!$L$2:$L$240=$B$73,ROW('Sale Rollup'!$L$2:$L$240)),ROW(16:16))-1,1)," ")} | C90: {=IFERROR(INDEX('Sale Rollup'!$B$2:$AA$240,SMALL(IF('Sale Rollup'!$L$2:$L$240=$B$73,ROW('Sale Rollup'!$L$2:$L$240)),ROW(16:16))-1,2)," ")} | D90: {=IFERROR(INDEX('Sale Rollup'!$B$2:$AA$240,SMALL(IF('Sale Rollup'!$L$2:$L$240=$B$73,ROW('Sale Rollup'!$L$2:$L$240)),ROW(16:16))-1,5)," ")} | E90: {=IFERROR( INDEX('Sale Rollup'!$B$2:$AA$240,SMALL(IF('Sale Rollup'!$L$2:$L$240=$B$73,ROW('Sale Rollup'!$L$2:$L$240)),ROW(16:16))-1,6)," ")} | F90: {=IFERROR(INDEX('Sale Rollup'!$B$2:$AA$240,SMALL(IF('Sale Rollup'!$L$2:$L$240=$B$73,ROW('Sale Rollup'!$L$2:$L$240)),ROW(16:16))-1,7)," ")} | G90: {=IFERROR(INDEX('Sale Rollup'!$B$2:$AA$240,SMALL(IF('Sale Rollup'!$L$2:$L$240=$B$73,ROW('Sale Rollup'!$L$2:$L$240)),ROW(16:16))-1,3)," ")} | H90: {=IFERROR(INDEX('Sale Rollup'!$B$2:$AA$240,SMALL(IF('Sale Rollup'!$L$2:$L$240=$B$73,ROW('Sale Rollup'!$L$2:$L$240)),ROW(16:16))-1,8)," ")} | I90: {=IFERROR(INDEX('Sale Rollup'!$B$2:$AA$240,SMALL(IF('Sale Rollup'!$L$2:$L$240=$B$73,ROW('Sale Rollup'!$L$2:$L$240)),ROW(16:16))-1,12)," ")} | K90: {=IFERROR(INDEX('Sale Rollup'!$B$2:$AA$240,SMALL(IF('Sale Rollup'!$L$2:$L$240=$B$73,ROW('Sale Rollup'!$L$2:$L$240)),ROW(16:16))-1,13)," ")}
A91: {=IFERROR(SMALL(IF('Sale Rollup'!$L$2:$L$240=$B$73,ROW('Sale Rollup'!$L$2:$L$240)),ROW(17:17))," ")} | B91: {=IFERROR(INDEX('Sale Rollup'!$B$2:$AA$240,SMALL(IF('Sale Rollup'!$L$2:$L$240=$B$73,ROW('Sale Rollup'!$L$2:$L$240)),ROW(17:17))-1,1)," ")} | C91: {=IFERROR(INDEX('Sale Rollup'!$B$2:$AA$240,SMALL(IF('Sale Rollup'!$L$2:$L$240=$B$73,ROW('Sale Rollup'!$L$2:$L$240)),ROW(17:17))-1,2)," ")} | D91: {=IFERROR(INDEX('Sale Rollup'!$B$2:$AA$240,SMALL(IF('Sale Rollup'!$L$2:$L$240=$B$73,ROW('Sale Rollup'!$L$2:$L$240)),ROW(17:17))-1,5)," ")} | E91: {=IFERROR( INDEX('Sale Rollup'!$B$2:$AA$240,SMALL(IF('Sale Rollup'!$L$2:$L$240=$B$73,ROW('Sale Rollup'!$L$2:$L$240)),ROW(17:17))-1,6)," ")} | F91: {=IFERROR(INDEX('Sale Rollup'!$B$2:$AA$240,SMALL(IF('Sale Rollup'!$L$2:$L$240=$B$73,ROW('Sale Rollup'!$L$2:$L$240)),ROW(17:17))-1,7)," ")} | G91: {=IFERROR(INDEX('Sale Rollup'!$B$2:$AA$240,SMALL(IF('Sale Rollup'!$L$2:$L$240=$B$73,ROW('Sale Rollup'!$L$2:$L$240)),ROW(17:17))-1,3)," ")} | H91: {=IFERROR(INDEX('Sale Rollup'!$B$2:$AA$240,SMALL(IF('Sale Rollup'!$L$2:$L$240=$B$73,ROW('Sale Rollup'!$L$2:$L$240)),ROW(17:17))-1,8)," ")} | I91: {=IFERROR(INDEX('Sale Rollup'!$B$2:$AA$240,SMALL(IF('Sale Rollup'!$L$2:$L$240=$B$73,ROW('Sale Rollup'!$L$2:$L$240)),ROW(17:17))-1,12)," ")} | K91: {=IFERROR(INDEX('Sale Rollup'!$B$2:$AA$240,SMALL(IF('Sale Rollup'!$L$2:$L$240=$B$73,ROW('Sale Rollup'!$L$2:$L$240)),ROW(17:17))-1,13)," ")}
A92: {=IFERROR(SMALL(IF('Sale Rollup'!$L$2:$L$240=$B$73,ROW('Sale Rollup'!$L$2:$L$240)),ROW(18:18))," ")} | B92: {=IFERROR(INDEX('Sale Rollup'!$B$2:$AA$240,SMALL(IF('Sale Rollup'!$L$2:$L$240=$B$73,ROW('Sale Rollup'!$L$2:$L$240)),ROW(18:18))-1,1)," ")} | C92: {=IFERROR(INDEX('Sale Rollup'!$B$2:$AA$240,SMALL(IF('Sale Rollup'!$L$2:$L$240=$B$73,ROW('Sale Rollup'!$L$2:$L$240)),ROW(18:18))-1,2)," ")} | D92: {=IFERROR(INDEX('Sale Rollup'!$B$2:$AA$240,SMALL(IF('Sale Rollup'!$L$2:$L$240=$B$73,ROW('Sale Rollup'!$L$2:$L$240)),ROW(18:18))-1,5)," ")} | E92: {=IFERROR( INDEX('Sale Rollup'!$B$2:$AA$240,SMALL(IF('Sale Rollup'!$L$2:$L$240=$B$73,ROW('Sale Rollup'!$L$2:$L$240)),ROW(18:18))-1,6)," ")} | F92: {=IFERROR(INDEX('Sale Rollup'!$B$2:$AA$240,SMALL(IF('Sale Rollup'!$L$2:$L$240=$B$73,ROW('Sale Rollup'!$L$2:$L$240)),ROW(18:18))-1,7)," ")} | G92: {=IFERROR(INDEX('Sale Rollup'!$B$2:$AA$240,SMALL(IF('Sale Rollup'!$L$2:$L$240=$B$73,ROW('Sale Rollup'!$L$2:$L$240)),ROW(18:18))-1,3)," ")} | H92: {=IFERROR(INDEX('Sale Rollup'!$B$2:$AA$240,SMALL(IF('Sale Rollup'!$L$2:$L$240=$B$73,ROW('Sale Rollup'!$L$2:$L$240)),ROW(18:18))-1,8)," ")} | I92: {=IFERROR(INDEX('Sale Rollup'!$B$2:$AA$240,SMALL(IF('Sale Rollup'!$L$2:$L$240=$B$73,ROW('Sale Rollup'!$L$2:$L$240)),ROW(18:18))-1,12)," ")} | K92: {=IFERROR(INDEX('Sale Rollup'!$B$2:$AA$240,SMALL(IF('Sale Rollup'!$L$2:$L$240=$B$73,ROW('Sale Rollup'!$L$2:$L$240)),ROW(18:18))-1,13)," ")}
A93: {=IFERROR(SMALL(IF('Sale Rollup'!$L$2:$L$240=$B$73,ROW('Sale Rollup'!$L$2:$L$240)),ROW(19:19))," ")} | B93: {=IFERROR(INDEX('Sale Rollup'!$B$2:$AA$240,SMALL(IF('Sale Rollup'!$L$2:$L$240=$B$73,ROW('Sale Rollup'!$L$2:$L$240)),ROW(19:19))-1,1)," ")} | C93: {=IFERROR(INDEX('Sale Rollup'!$B$2:$AA$240,SMALL(IF('Sale Rollup'!$L$2:$L$240=$B$73,ROW('Sale Rollup'!$L$2:$L$240)),ROW(19:19))-1,2)," ")} | D93: {=IFERROR(INDEX('Sale Rollup'!$B$2:$AA$240,SMALL(IF('Sale Rollup'!$L$2:$L$240=$B$73,ROW('Sale Rollup'!$L$2:$L$240)),ROW(19:19))-1,5)," ")} | E93: {=IFERROR( INDEX('Sale Rollup'!$B$2:$AA$240,SMALL(IF('Sale Rollup'!$L$2:$L$240=$B$73,ROW('Sale Rollup'!$L$2:$L$240)),ROW(19:19))-1,6)," ")} | F93: {=IFERROR(INDEX('Sale Rollup'!$B$2:$AA$240,SMALL(IF('Sale Rollup'!$L$2:$L$240=$B$73,ROW('Sale Rollup'!$L$2:$L$240)),ROW(19:19))-1,7)," ")} | G93: {=IFERROR(INDEX('Sale Rollup'!$B$2:$AA$240,SMALL(IF('Sale Rollup'!$L$2:$L$240=$B$73,ROW('Sale Rollup'!$L$2:$L$240)),ROW(19:19))-1,3)," ")} | H93: {=IFERROR(INDEX('Sale Rollup'!$B$2:$AA$240,SMALL(IF('Sale Rollup'!$L$2:$L$240=$B$73,ROW('Sale Rollup'!$L$2:$L$240)),ROW(19:19))-1,8)," ")} | I93: {=IFERROR(INDEX('Sale Rollup'!$B$2:$AA$240,SMALL(IF('Sale Rollup'!$L$2:$L$240=$B$73,ROW('Sale Rollup'!$L$2:$L$240)),ROW(19:19))-1,12)," ")} | K93: {=IFERROR(INDEX('Sale Rollup'!$B$2:$AA$240,SMALL(IF('Sale Rollup'!$L$2:$L$240=$B$73,ROW('Sale Rollup'!$L$2:$L$240)),ROW(19:19))-1,13)," ")}
A94: {=IFERROR(SMALL(IF('Sale Rollup'!$L$2:$L$240=$B$73,ROW('Sale Rollup'!$L$2:$L$240)),ROW(20:20))," ")} | B94: {=IFERROR(INDEX('Sale Rollup'!$B$2:$AA$240,SMALL(IF('Sale Rollup'!$L$2:$L$240=$B$73,ROW('Sale Rollup'!$L$2:$L$240)),ROW(20:20))-1,1)," ")} | C94: {=IFERROR(INDEX('Sale Rollup'!$B$2:$AA$240,SMALL(IF('Sale Rollup'!$L$2:$L$240=$B$73,ROW('Sale Rollup'!$L$2:$L$240)),ROW(20:20))-1,2)," ")} | D94: {=IFERROR(INDEX('Sale Rollup'!$B$2:$AA$240,SMALL(IF('Sale Rollup'!$L$2:$L$240=$B$73,ROW('Sale Rollup'!$L$2:$L$240)),ROW(20:20))-1,5)," ")} | E94: {=IFERROR( INDEX('Sale Rollup'!$B$2:$AA$240,SMALL(IF('Sale Rollup'!$L$2:$L$240=$B$73,ROW('Sale Rollup'!$L$2:$L$240)),ROW(20:20))-1,6)," ")} | F94: {=IFERROR(INDEX('Sale Rollup'!$B$2:$AA$240,SMALL(IF('Sale Rollup'!$L$2:$L$240=$B$73,ROW('Sale Rollup'!$L$2:$L$240)),ROW(20:20))-1,7)," ")} | G94: {=IFERROR(INDEX('Sale Rollup'!$B$2:$AA$240,SMALL(IF('Sale Rollup'!$L$2:$L$240=$B$73,ROW('Sale Rollup'!$L$2:$L$240)),ROW(20:20))-1,3)," ")} | H94: {=IFERROR(INDEX('Sale Rollup'!$B$2:$AA$240,SMALL(IF('Sale Rollup'!$L$2:$L$240=$B$73,ROW('Sale Rollup'!$L$2:$L$240)),ROW(20:20))-1,8)," ")} | I94: {=IFERROR(INDEX('Sale Rollup'!$B$2:$AA$240,SMALL(IF('Sale Rollup'!$L$2:$L$240=$B$73,ROW('Sale Rollup'!$L$2:$L$240)),ROW(20:20))-1,12)," ")} | K94: {=IFERROR(INDEX('Sale Rollup'!$B$2:$AA$240,SMALL(IF('Sale Rollup'!$L$2:$L$240=$B$73,ROW('Sale Rollup'!$L$2:$L$240)),ROW(20:20))-1,13)," ")}
A95: {=IFERROR(SMALL(IF('Sale Rollup'!$O$2:$O$240=$B$73,ROW('Sale Rollup'!$L$2:$L$240)),ROW(1:1))," ")} | B95: {=IFERROR(INDEX('Sale Rollup'!$B$2:$AA$240,SMALL(IF('Sale Rollup'!$O$2:$O$240=$B$73,ROW('Sale Rollup'!$L$2:$L$240)),ROW(1:1))-1,1)," ")} | C95: {=IFERROR(INDEX('Sale Rollup'!$B$2:$AA$240,SMALL(IF('Sale Rollup'!$O$2:$O$240=$B$73,ROW('Sale Rollup'!$L$2:$L$240)),ROW(1:1))-1,2)," ")} | D95: {=IFERROR(INDEX('Sale Rollup'!$B$2:$AA$240,SMALL(IF('Sale Rollup'!$O$2:$O$240=$B$73,ROW('Sale Rollup'!$L$2:$L$240)),ROW(1:1))-1,5)," ")} | E95: {=IFERROR( INDEX('Sale Rollup'!$B$2:$AA$240,SMALL(IF('Sale Rollup'!$O$2:$O$240=$B$73,ROW('Sale Rollup'!$L$2:$L$240)),ROW(1:1))-1,6)," ")} | F95: {=IFERROR(INDEX('Sale Rollup'!$B$2:$AA$240,SMALL(IF('Sale Rollup'!$O$2:$O$240=$B$73,ROW('Sale Rollup'!$L$2:$L$240)),ROW(1:1))-1,7)," ")} | G95: {=IFERROR(INDEX('Sale Rollup'!$B$2:$AA$240,SMALL(IF('Sale Rollup'!$O$2:$O$240=$B$73,ROW('Sale Rollup'!$L$2:$L$240)),ROW(1:1))-1,3)," ")} | H95: {=IFERROR(INDEX('Sale Rollup'!$B$2:$AA$240,SMALL(IF('Sale Rollup'!$O$2:$O$240=$B$73,ROW('Sale Rollup'!$L$2:$L$240)),ROW(1:1))-1,8)," ")} | I95: {=IFERROR(INDEX('Sale Rollup'!$B$2:$AA$240,SMALL(IF('Sale Rollup'!$O$2:$O$240=$B$73,ROW('Sale Rollup'!$L$2:$L$240)),ROW(1:1))-1,15)," ")} | K95: {=IFERROR(INDEX('Sale Rollup'!$B$2:$AA$240,SMALL(IF('Sale Rollup'!$O$2:$O$240=$B$73,ROW('Sale Rollup'!$L$2:$L$240)),ROW(1:1))-1,16)," ")} | L95: Split Deals
A96: {=IFERROR(SMALL(IF('Sale Rollup'!$O$2:$O$240=$B$73,ROW('Sale Rollup'!$L$2:$L$240)),ROW(2:2))," ")} | B96: {=IFERROR(INDEX('Sale Rollup'!$B$2:$AA$240,SMALL(IF('Sale Rollup'!$O$2:$O$240=$B$73,ROW('Sale Rollup'!$L$2:$L$240)),ROW(2:2))-1,1)," ")} | C96: {=IFERROR(INDEX('Sale Rollup'!$B$2:$AA$240,SMALL(IF('Sale Rollup'!$O$2:$O$240=$B$73,ROW('Sale Rollup'!$L$2:$L$240)),ROW(2:2))-1,2)," ")} | D96: {=IFERROR(INDEX('Sale Rollup'!$B$2:$AA$240,SMALL(IF('Sale Rollup'!$O$2:$O$240=$B$73,ROW('Sale Rollup'!$L$2:$L$240)),ROW(2:2))-1,5)," ")} | E96: {=IFERROR( INDEX('Sale Rollup'!$B$2:$AA$240,SMALL(IF('Sale Rollup'!$O$2:$O$240=$B$73,ROW('Sale Rollup'!$L$2:$L$240)),ROW(2:2))-1,6)," ")} | F96: {=IFERROR(INDEX('Sale Rollup'!$B$2:$AA$240,SMALL(IF('Sale Rollup'!$O$2:$O$240=$B$73,ROW('Sale Rollup'!$L$2:$L$240)),ROW(2:2))-1,7)," ")} | G96: {=IFERROR(INDEX('Sale Rollup'!$B$2:$AA$240,SMALL(IF('Sale Rollup'!$O$2:$O$240=$B$73,ROW('Sale Rollup'!$L$2:$L$240)),ROW(2:2))-1,3)," ")} | H96: {=IFERROR(INDEX('Sale Rollup'!$B$2:$AA$240,SMALL(IF('Sale Rollup'!$O$2:$O$240=$B$73,ROW('Sale Rollup'!$L$2:$L$240)),ROW(2:2))-1,8)," ")} | I96: {=IFERROR(INDEX('Sale Rollup'!$B$2:$AA$240,SMALL(IF('Sale Rollup'!$O$2:$O$240=$B$73,ROW('Sale Rollup'!$L$2:$L$240)),ROW(2:2))-1,15)," ")} | K96: {=IFERROR(INDEX('Sale Rollup'!$B$2:$AA$240,SMALL(IF('Sale Rollup'!$O$2:$O$240=$B$73,ROW('Sale Rollup'!$L$2:$L$240)),ROW(2:2))-1,16)," ")}
A97: {=IFERROR(SMALL(IF('Sale Rollup'!$O$2:$O$240=$B$73,ROW('Sale Rollup'!$L$2:$L$240)),ROW(3:3))," ")} | B97: {=IFERROR(INDEX('Sale Rollup'!$B$2:$AA$240,SMALL(IF('Sale Rollup'!$O$2:$O$240=$B$73,ROW('Sale Rollup'!$L$2:$L$240)),ROW(3:3))-1,1)," ")} | C97: {=IFERROR(INDEX('Sale Rollup'!$B$2:$AA$240,SMALL(IF('Sale Rollup'!$O$2:$O$240=$B$73,ROW('Sale Rollup'!$L$2:$L$240)),ROW(3:3))-1,2)," ")} | D97: {=IFERROR(INDEX('Sale Rollup'!$B$2:$AA$240,SMALL(IF('Sale Rollup'!$O$2:$O$240=$B$73,ROW('Sale Rollup'!$L$2:$L$240)),ROW(3:3))-1,5)," ")} | E97: {=IFERROR( INDEX('Sale Rollup'!$B$2:$AA$240,SMALL(IF('Sale Rollup'!$O$2:$O$240=$B$73,ROW('Sale Rollup'!$L$2:$L$240)),ROW(3:3))-1,6)," ")} | F97: {=IFERROR(INDEX('Sale Rollup'!$B$2:$AA$240,SMALL(IF('Sale Rollup'!$O$2:$O$240=$B$73,ROW('Sale Rollup'!$L$2:$L$240)),ROW(3:3))-1,7)," ")} | G97: {=IFERROR(INDEX('Sale Rollup'!$B$2:$AA$240,SMALL(IF('Sale Rollup'!$O$2:$O$240=$B$73,ROW('Sale Rollup'!$L$2:$L$240)),ROW(3:3))-1,3)," ")} | H97: {=IFERROR(INDEX('Sale Rollup'!$B$2:$AA$240,SMALL(IF('Sale Rollup'!$O$2:$O$240=$B$73,ROW('Sale Rollup'!$L$2:$L$240)),ROW(3:3))-1,8)," ")} | I97: {=IFERROR(INDEX('Sale Rollup'!$B$2:$AA$240,SMALL(IF('Sale Rollup'!$O$2:$O$240=$B$73,ROW('Sale Rollup'!$L$2:$L$240)),ROW(3:3))-1,15)," ")} | K97: {=IFERROR(INDEX('Sale Rollup'!$B$2:$AA$240,SMALL(IF('Sale Rollup'!$O$2:$O$240=$B$73,ROW('Sale Rollup'!$L$2:$L$240)),ROW(3:3))-1,16)," ")}
A98: {=IFERROR(SMALL(IF('Sale Rollup'!$O$2:$O$240=$B$73,ROW('Sale Rollup'!$L$2:$L$240)),ROW(4:4))," ")} | B98: {=IFERROR(INDEX('Sale Rollup'!$B$2:$AA$240,SMALL(IF('Sale Rollup'!$O$2:$O$240=$B$73,ROW('Sale Rollup'!$L$2:$L$240)),ROW(4:4))-1,1)," ")} | C98: {=IFERROR(INDEX('Sale Rollup'!$B$2:$AA$240,SMALL(IF('Sale Rollup'!$O$2:$O$240=$B$73,ROW('Sale Rollup'!$L$2:$L$240)),ROW(4:4))-1,2)," ")} | D98: {=IFERROR(INDEX('Sale Rollup'!$B$2:$AA$240,SMALL(IF('Sale Rollup'!$O$2:$O$240=$B$73,ROW('Sale Rollup'!$L$2:$L$240)),ROW(4:4))-1,5)," ")} | E98: {=IFERROR( INDEX('Sale Rollup'!$B$2:$AA$240,SMALL(IF('Sale Rollup'!$O$2:$O$240=$B$73,ROW('Sale Rollup'!$L$2:$L$240)),ROW(4:4))-1,6)," ")} | F98: {=IFERROR(INDEX('Sale Rollup'!$B$2:$AA$240,SMALL(IF('Sale Rollup'!$O$2:$O$240=$B$73,ROW('Sale Rollup'!$L$2:$L$240)),ROW(4:4))-1,7)," ")} | G98: {=IFERROR(INDEX('Sale Rollup'!$B$2:$AA$240,SMALL(IF('Sale Rollup'!$O$2:$O$240=$B$73,ROW('Sale Rollup'!$L$2:$L$240)),ROW(4:4))-1,3)," ")} | H98: {=IFERROR(INDEX('Sale Rollup'!$B$2:$AA$240,SMALL(IF('Sale Rollup'!$O$2:$O$240=$B$73,ROW('Sale Rollup'!$L$2:$L$240)),ROW(4:4))-1,8)," ")} | I98: {=IFERROR(INDEX('Sale Rollup'!$B$2:$AA$240,SMALL(IF('Sale Rollup'!$O$2:$O$240=$B$73,ROW('Sale Rollup'!$L$2:$L$240)),ROW(4:4))-1,15)," ")} | K98: {=IFERROR(INDEX('Sale Rollup'!$B$2:$AA$240,SMALL(IF('Sale Rollup'!$O$2:$O$240=$B$73,ROW('Sale Rollup'!$L$2:$L$240)),ROW(4:4))-1,16)," ")}
A99: {=IFERROR(SMALL(IF('Sale Rollup'!$O$2:$O$240=$B$73,ROW('Sale Rollup'!$L$2:$L$240)),ROW(5:5))," ")} | B99: {=IFERROR(INDEX('Sale Rollup'!$B$2:$AA$240,SMALL(IF('Sale Rollup'!$O$2:$O$240=$B$73,ROW('Sale Rollup'!$L$2:$L$240)),ROW(5:5))-1,1)," ")} | C99: {=IFERROR(INDEX('Sale Rollup'!$B$2:$AA$240,SMALL(IF('Sale Rollup'!$O$2:$O$240=$B$73,ROW('Sale Rollup'!$L$2:$L$240)),ROW(5:5))-1,2)," ")} | D99: {=IFERROR(INDEX('Sale Rollup'!$B$2:$AA$240,SMALL(IF('Sale Rollup'!$O$2:$O$240=$B$73,ROW('Sale Rollup'!$L$2:$L$240)),ROW(5:5))-1,5)," ")} | E99: {=IFERROR( INDEX('Sale Rollup'!$B$2:$AA$240,SMALL(IF('Sale Rollup'!$O$2:$O$240=$B$73,ROW('Sale Rollup'!$L$2:$L$240)),ROW(5:5))-1,6)," ")} | F99: {=IFERROR(INDEX('Sale Rollup'!$B$2:$AA$240,SMALL(IF('Sale Rollup'!$O$2:$O$240=$B$73,ROW('Sale Rollup'!$L$2:$L$240)),ROW(5:5))-1,7)," ")} | G99: {=IFERROR(INDEX('Sale Rollup'!$B$2:$AA$240,SMALL(IF('Sale Rollup'!$O$2:$O$240=$B$73,ROW('Sale Rollup'!$L$2:$L$240)),ROW(5:5))-1,3)," ")} | H99: {=IFERROR(INDEX('Sale Rollup'!$B$2:$AA$240,SMALL(IF('Sale Rollup'!$O$2:$O$240=$B$73,ROW('Sale Rollup'!$L$2:$L$240)),ROW(5:5))-1,8)," ")} | I99: {=IFERROR(INDEX('Sale Rollup'!$B$2:$AA$240,SMALL(IF('Sale Rollup'!$O$2:$O$240=$B$73,ROW('Sale Rollup'!$L$2:$L$240)),ROW(5:5))-1,15)," ")} | K99: {=IFERROR(INDEX('Sale Rollup'!$B$2:$AA$240,SMALL(IF('Sale Rollup'!$O$2:$O$240=$B$73,ROW('Sale Rollup'!$L$2:$L$240)),ROW(5:5))-1,16)," ")}
A100: {=IFERROR(SMALL(IF('Sale Rollup'!$O$2:$O$240=$B$73,ROW('Sale Rollup'!$L$2:$L$240)),ROW(6:6))," ")} | B100: {=IFERROR(INDEX('Sale Rollup'!$B$2:$AA$240,SMALL(IF('Sale Rollup'!$O$2:$O$240=$B$73,ROW('Sale Rollup'!$L$2:$L$240)),ROW(6:6))-1,1)," ")} | C100: {=IFERROR(INDEX('Sale Rollup'!$B$2:$AA$240,SMALL(IF('Sale Rollup'!$O$2:$O$240=$B$73,ROW('Sale Rollup'!$L$2:$L$240)),ROW(6:6))-1,2)," ")} | D100: {=IFERROR(INDEX('Sale Rollup'!$B$2:$AA$240,SMALL(IF('Sale Rollup'!$O$2:$O$240=$B$73,ROW('Sale Rollup'!$L$2:$L$240)),ROW(6:6))-1,5)," ")} | E100: {=IFERROR( INDEX('Sale Rollup'!$B$2:$AA$240,SMALL(IF('Sale Rollup'!$O$2:$O$240=$B$73,ROW('Sale Rollup'!$L$2:$L$240)),ROW(6:6))-1,6)," ")} | F100: {=IFERROR(INDEX('Sale Rollup'!$B$2:$AA$240,SMALL(IF('Sale Rollup'!$O$2:$O$240=$B$73,ROW('Sale Rollup'!$L$2:$L$240)),ROW(6:6))-1,7)," ")} | G100: {=IFERROR(INDEX('Sale Rollup'!$B$2:$AA$240,SMALL(IF('Sale Rollup'!$O$2:$O$240=$B$73,ROW('Sale Rollup'!$L$2:$L$240)),ROW(6:6))-1,3)," ")} | H100: {=IFERROR(INDEX('Sale Rollup'!$B$2:$AA$240,SMALL(IF('Sale Rollup'!$O$2:$O$240=$B$73,ROW('Sale Rollup'!$L$2:$L$240)),ROW(6:6))-1,8)," ")} | I100: {=IFERROR(INDEX('Sale Rollup'!$B$2:$AA$240,SMALL(IF('Sale Rollup'!$O$2:$O$240=$B$73,ROW('Sale Rollup'!$L$2:$L$240)),ROW(6:6))-1,15)," ")} | K100: {=IFERROR(INDEX('Sale Rollup'!$B$2:$AA$240,SMALL(IF('Sale Rollup'!$O$2:$O$240=$B$73,ROW('Sale Rollup'!$L$2:$L$240)),ROW(6:6))-1,16)," ")}
A101: {=IFERROR(SMALL(IF('Sale Rollup'!$O$2:$O$240=$B$73,ROW('Sale Rollup'!$L$2:$L$240)),ROW(7:7))," ")} | B101: {=IFERROR(INDEX('Sale Rollup'!$B$2:$AA$240,SMALL(IF('Sale Rollup'!$O$2:$O$240=$B$73,ROW('Sale Rollup'!$L$2:$L$240)),ROW(7:7))-1,1)," ")} | C101: {=IFERROR(INDEX('Sale Rollup'!$B$2:$AA$240,SMALL(IF('Sale Rollup'!$O$2:$O$240=$B$73,ROW('Sale Rollup'!$L$2:$L$240)),ROW(7:7))-1,2)," ")} | D101: {=IFERROR(INDEX('Sale Rollup'!$B$2:$AA$240,SMALL(IF('Sale Rollup'!$O$2:$O$240=$B$73,ROW('Sale Rollup'!$L$2:$L$240)),ROW(7:7))-1,5)," ")} | E101: {=IFERROR( INDEX('Sale Rollup'!$B$2:$AA$240,SMALL(IF('Sale Rollup'!$O$2:$O$240=$B$73,ROW('Sale Rollup'!$L$2:$L$240)),ROW(7:7))-1,6)," ")} | F101: {=IFERROR(INDEX('Sale Rollup'!$B$2:$AA$240,SMALL(IF('Sale Rollup'!$O$2:$O$240=$B$73,ROW('Sale Rollup'!$L$2:$L$240)),ROW(7:7))-1,7)," ")} | G101: {=IFERROR(INDEX('Sale Rollup'!$B$2:$AA$240,SMALL(IF('Sale Rollup'!$O$2:$O$240=$B$73,ROW('Sale Rollup'!$L$2:$L$240)),ROW(7:7))-1,3)," ")} | H101: {=IFERROR(INDEX('Sale Rollup'!$B$2:$AA$240,SMALL(IF('Sale Rollup'!$O$2:$O$240=$B$73,ROW('Sale Rollup'!$L$2:$L$240)),ROW(7:7))-1,8)," ")} | I101: {=IFERROR(INDEX('Sale Rollup'!$B$2:$AA$240,SMALL(IF('Sale Rollup'!$O$2:$O$240=$B$73,ROW('Sale Rollup'!$L$2:$L$240)),ROW(7:7))-1,15)," ")} | K101: {=IFERROR(INDEX('Sale Rollup'!$B$2:$AA$240,SMALL(IF('Sale Rollup'!$O$2:$O$240=$B$73,ROW('Sale Rollup'!$L$2:$L$240)),ROW(7:7))-1,16)," ")}
A102: {=IFERROR(SMALL(IF('Sale Rollup'!$O$2:$O$240=$B$73,ROW('Sale Rollup'!$L$2:$L$240)),ROW(8:8))," ")} | B102: {=IFERROR(INDEX('Sale Rollup'!$B$2:$AA$240,SMALL(IF('Sale Rollup'!$O$2:$O$240=$B$73,ROW('Sale Rollup'!$L$2:$L$240)),ROW(8:8))-1,1)," ")} | C102: {=IFERROR(INDEX('Sale Rollup'!$B$2:$AA$240,SMALL(IF('Sale Rollup'!$O$2:$O$240=$B$73,ROW('Sale Rollup'!$L$2:$L$240)),ROW(8:8))-1,2)," ")} | D102: {=IFERROR(INDEX('Sale Rollup'!$B$2:$AA$240,SMALL(IF('Sale Rollup'!$O$2:$O$240=$B$73,ROW('Sale Rollup'!$L$2:$L$240)),ROW(8:8))-1,5)," ")} | E102: {=IFERROR( INDEX('Sale Rollup'!$B$2:$AA$240,SMALL(IF('Sale Rollup'!$O$2:$O$240=$B$73,ROW('Sale Rollup'!$L$2:$L$240)),ROW(8:8))-1,6)," ")} | F102: {=IFERROR(INDEX('Sale Rollup'!$B$2:$AA$240,SMALL(IF('Sale Rollup'!$O$2:$O$240=$B$73,ROW('Sale Rollup'!$L$2:$L$240)),ROW(8:8))-1,7)," ")} | G102: {=IFERROR(INDEX('Sale Rollup'!$B$2:$AA$240,SMALL(IF('Sale Rollup'!$O$2:$O$240=$B$73,ROW('Sale Rollup'!$L$2:$L$240)),ROW(8:8))-1,3)," ")} | H102: {=IFERROR(INDEX('Sale Rollup'!$B$2:$AA$240,SMALL(IF('Sale Rollup'!$O$2:$O$240=$B$73,ROW('Sale Rollup'!$L$2:$L$240)),ROW(8:8))-1,8)," ")} | I102: {=IFERROR(INDEX('Sale Rollup'!$B$2:$AA$240,SMALL(IF('Sale Rollup'!$O$2:$O$240=$B$73,ROW('Sale Rollup'!$L$2:$L$240)),ROW(8:8))-1,15)," ")} | K102: {=IFERROR(INDEX('Sale Rollup'!$B$2:$AA$240,SMALL(IF('Sale Rollup'!$O$2:$O$240=$B$73,ROW('Sale Rollup'!$L$2:$L$240)),ROW(8:8))-1,16)," ")}
A103: {=IFERROR(SMALL(IF('Sale Rollup'!$O$2:$O$240=$B$73,ROW('Sale Rollup'!$L$2:$L$240)),ROW(9:9))," ")} | B103: {=IFERROR(INDEX('Sale Rollup'!$B$2:$AA$240,SMALL(IF('Sale Rollup'!$O$2:$O$240=$B$73,ROW('Sale Rollup'!$L$2:$L$240)),ROW(9:9))-1,1)," ")} | C103: {=IFERROR(INDEX('Sale Rollup'!$B$2:$AA$240,SMALL(IF('Sale Rollup'!$O$2:$O$240=$B$73,ROW('Sale Rollup'!$L$2:$L$240)),ROW(9:9))-1,2)," ")} | D103: {=IFERROR(INDEX('Sale Rollup'!$B$2:$AA$240,SMALL(IF('Sale Rollup'!$O$2:$O$240=$B$73,ROW('Sale Rollup'!$L$2:$L$240)),ROW(9:9))-1,5)," ")} | E103: {=IFERROR( INDEX('Sale Rollup'!$B$2:$AA$240,SMALL(IF('Sale Rollup'!$O$2:$O$240=$B$73,ROW('Sale Rollup'!$L$2:$L$240)),ROW(9:9))-1,6)," ")} | F103: {=IFERROR(INDEX('Sale Rollup'!$B$2:$AA$240,SMALL(IF('Sale Rollup'!$O$2:$O$240=$B$73,ROW('Sale Rollup'!$L$2:$L$240)),ROW(9:9))-1,7)," ")} | G103: {=IFERROR(INDEX('Sale Rollup'!$B$2:$AA$240,SMALL(IF('Sale Rollup'!$O$2:$O$240=$B$73,ROW('Sale Rollup'!$L$2:$L$240)),ROW(9:9))-1,3)," ")} | H103: {=IFERROR(INDEX('Sale Rollup'!$B$2:$AA$240,SMALL(IF('Sale Rollup'!$O$2:$O$240=$B$73,ROW('Sale Rollup'!$L$2:$L$240)),ROW(9:9))-1,8)," ")} | I103: {=IFERROR(INDEX('Sale Rollup'!$B$2:$AA$240,SMALL(IF('Sale Rollup'!$O$2:$O$240=$B$73,ROW('Sale Rollup'!$L$2:$L$240)),ROW(9:9))-1,15)," ")} | K103: {=IFERROR(INDEX('Sale Rollup'!$B$2:$AA$240,SMALL(IF('Sale Rollup'!$O$2:$O$240=$B$73,ROW('Sale Rollup'!$L$2:$L$240)),ROW(9:9))-1,16)," ")}
A104: {=IFERROR(SMALL(IF('Sale Rollup'!$O$2:$O$240=$B$73,ROW('Sale Rollup'!$L$2:$L$240)),ROW(10:10))," ")} | B104: {=IFERROR(INDEX('Sale Rollup'!$B$2:$AA$240,SMALL(IF('Sale Rollup'!$O$2:$O$240=$B$73,ROW('Sale Rollup'!$L$2:$L$240)),ROW(10:10))-1,1)," ")} | C104: {=IFERROR(INDEX('Sale Rollup'!$B$2:$AA$240,SMALL(IF('Sale Rollup'!$O$2:$O$240=$B$73,ROW('Sale Rollup'!$L$2:$L$240)),ROW(10:10))-1,2)," ")} | D104: {=IFERROR(INDEX('Sale Rollup'!$B$2:$AA$240,SMALL(IF('Sale Rollup'!$O$2:$O$240=$B$73,ROW('Sale Rollup'!$L$2:$L$240)),ROW(10:10))-1,5)," ")} | E104: {=IFERROR( INDEX('Sale Rollup'!$B$2:$AA$240,SMALL(IF('Sale Rollup'!$O$2:$O$240=$B$73,ROW('Sale Rollup'!$L$2:$L$240)),ROW(10:10))-1,6)," ")} | F104: {=IFERROR(INDEX('Sale Rollup'!$B$2:$AA$240,SMALL(IF('Sale Rollup'!$O$2:$O$240=$B$73,ROW('Sale Rollup'!$L$2:$L$240)),ROW(10:10))-1,7)," ")} | G104: {=IFERROR(INDEX('Sale Rollup'!$B$2:$AA$240,SMALL(IF('Sale Rollup'!$O$2:$O$240=$B$73,ROW('Sale Rollup'!$L$2:$L$240)),ROW(10:10))-1,3)," ")} | H104: {=IFERROR(INDEX('Sale Rollup'!$B$2:$AA$240,SMALL(IF('Sale Rollup'!$O$2:$O$240=$B$73,ROW('Sale Rollup'!$L$2:$L$240)),ROW(10:10))-1,8)," ")} | I104: {=IFERROR(INDEX('Sale Rollup'!$B$2:$AA$240,SMALL(IF('Sale Rollup'!$O$2:$O$240=$B$73,ROW('Sale Rollup'!$L$2:$L$240)),ROW(10:10))-1,15)," ")} | K104: {=IFERROR(INDEX('Sale Rollup'!$B$2:$AA$240,SMALL(IF('Sale Rollup'!$O$2:$O$240=$B$73,ROW('Sale Rollup'!$L$2:$L$240)),ROW(10:10))-1,16)," ")}
A105: Deals | B105: =COUNT(B75:B99) -> 0 | K105: =SUM(K75:K94) -> 0
A106: =IF('Roster & Tables'!J29=0,"","Pack") | B106: Full | C106: =COUNTIFS('Sale Rollup'!L73:L312,B73,'Sale Rollup'!K73:K312,"No") -> 0 | E106: Split | F106: =COUNTIF('Sale Rollup'!O73:O312,B73)+COUNTIFS('Sale Rollup'!L73:L312,B73,'Sale Rollup'!K73:K312,"Yes") -> 0 | K106: =IF('Roster & Tables'!J29=0,"",((C106*'Roster & Tables'!J29)+(F106*('Roster & Tables'!J29/2))))
...

Sheet Pay Calc.
A1: Customer Last | D1: Customer Last | G1: Customer Last | J1: Customer Last | M1: Customer Last | P1: Customer Last | S1: Customer Last
A2: Stock# | D2: Stock# | G2: Stock# | J2: Stock# | M2: Stock# | P2: Stock# | S2: Stock#
A3: Vehicle Sales Price | B3: 32915 | D3: Vehicle Sales Price | E3: 0 | G3: Vehicle Sales Price | H3: 0 | J3: Vehicle Sales Price | K3: 0 | M3: Vehicle Sales Price | N3: 0 | P3: Vehicle Sales Price | Q3: 0 | S3: Vehicle Sales Price | T3: 0
A4: State Sales Tax Rate | B4: 0.06 | D4: State Sales Tax Rate | E4: 0 | G4: State Sales Tax Rate | H4: 0 | J4: State Sales Tax Rate | K4: 0 | M4: State Sales Tax Rate | N4: 0 | P4: State Sales Tax Rate | Q4: 0 | S4: State Sales Tax Rate | T4: 0
A5: State Sales Tax | B5: =SUM(B3-B17)*B4 -> 924.9 | D5: State Sales Tax | E5: =E3*E4 -> 0 | G5: State Sales Tax | H5: =H3*H4 -> 0 | J5: State Sales Tax | K5: =K3*K4 -> 0 | M5: State Sales Tax | N5: =N3*N4 -> 0 | P5: State Sales Tax | Q5: =Q3*Q4 -> 0 | S5: State Sales Tax | T5: =T3*T4 -> 0
A6: IRS Luxury Tax | B6: =IF(B3>55000,(B3-55000)*0.05,0) -> 0 | D6: IRS Luxury Tax | E6: =IF(E3>55000,(E3-55000)*0.05,0) -> 0 | G6: IRS Luxury Tax | H6: =IF(H3>55000,(H3-55000)*0.05,0) -> 0 | J6: IRS Luxury Tax | K6: =IF(K3>55000,(K3-55000)*0.05,0) -> 0 | M6: IRS Luxury Tax | N6: =IF(N3>55000,(N3-55000)*0.05,0) -> 0 | P6: IRS Luxury Tax | Q6: =IF(Q3>55000,(Q3-55000)*0.05,0) -> 0 | S6: IRS Luxury Tax | T6: =IF(T3>55000,(T3-55000)*0.05,0) -> 0
A7: State Inspection Fee | B7: 0 | D7: State Inspection Fee | E7: 0 | G7: State Inspection Fee | H7: 0 | J7: State Inspection Fee | K7: 0 | M7: State Inspection Fee | N7: 0 | P7: State Inspection Fee | Q7: 0 | S7: State Inspection Fee | T7: 0
A8: Documentary Fee | B8: 399 | D8: Documentary Fee | E8: 0 | G8: Documentary Fee | H8: 0 | J8: Documentary Fee | K8: 0 | M8: Documentary Fee | N8: 0 | P8: Documentary Fee | Q8: 0 | S8: Documentary Fee | T8: 0
A9: License Fee | B9: 34 | D9: License Fee | E9: 0 | G9: License Fee | H9: 0 | J9: License Fee | K9: 0 | M9: License Fee | N9: 0 | P9: License Fee | Q9: 0 | S9: License Fee | T9: 0
A10: Warranty | B10: 0 | D10: Warranty | E10: 0 | G10: Warranty | H10: 0 | J10: Warranty | K10: 0 | M10: Warranty | N10: 0 | P10: Warranty | Q10: 0 | S10: Warranty | T10: 0
A11: Gap Insurance | B11: 0 | D11: Gap Insurance | E11: 0 | G11: Gap Insurance | H11: 0 | J11: Gap Insurance | K11: 0 | M11: Gap Insurance | N11: 0 | P11: Gap Insurance | Q11: 0 | S11: Gap Insurance | T11: 0
A12: After Market | B12: 0 | D12: After Market | E12: 0 | G12: After Market | H12: 0 | J12: After Market | K12: 0 | M12: After Market | N12: 0 | P12: After Market | Q12: 0 | S12: After Market | T12: 0
A13: SUB TOTAL | B13: =SUM(B3:B12) -> 34272.96 | D13: SUB TOTAL | E13: =SUM(E3,E5,E6,E7,E8,E9,E9,E10,E11,E12) -> 0 | G13: SUB TOTAL | H13: =SUM(H3,H5,H6,H7,H8,H9,H9,H10,H11,H12) -> 0 | J13: SUB TOTAL | K13: =SUM(K3,K5,K6,K7,K8,K9,K9,K10,K11,K12) -> 0 | M13: SUB TOTAL | N13: =SUM(N3,N5,N6,N7,N8,N9,N9,N10,N11,N12) -> 0 | P13: SUB TOTAL | Q13: =SUM(Q3,Q5,Q6,Q7,Q8,Q9,Q9,Q10,Q11,Q12) -> 0 | S13: SUB TOTAL | T13: =SUM(T3,T5,T6,T7,T8,T9,T9,T10,T11,T12) -> 0
A15: Down Payment | B15: 0 | D15: Down Payment | E15: 0 | G15: Down Payment | H15: 0 | J15: Down Payment | K15: 0 | M15: Down Payment | N15: 0 | P15: Down Payment | Q15: 0 | S15: Down Payment | T15: 0
A16: Manufacturer Rebate | B16: 0 | D16: Manufacturer Rebate | E16: 0 | G16: Manufacturer Rebate | H16: 0 | J16: Manufacturer Rebate | K16: 0 | M16: Manufacturer Rebate | N16: 0 | P16: Manufacturer Rebate | Q16: 0 | S16: Manufacturer Rebate | T16: 0
A17: Trade-in Allowance | B17: 17500 | D17: Trade-in Allowance | E17: 0 | G17: Trade-in Allowance | H17: 0 | J17: Trade-in Allowance | K17: 0 | M17: Trade-in Allowance | N17: 0 | P17: Trade-in Allowance | Q17: 0 | S17: Trade-in Allowance | T17: 0
A18: Owed on Trade | B18: 21750 | D18: Owed on Trade | E18: 0 | G18: Owed on Trade | H18: 0 | J18: Owed on Trade | K18: 0 | M18: Owed on Trade | N18: 0 | P18: Owed on Trade | Q18: 0 | S18: Owed on Trade | T18: 0
A19: Trade Equity | B19: =B17-B18 -> -4250 | D19: Trade Equity | E19: =E17-E18 -> 0 | G19: Trade Equity | H19: =H17-H18 -> 0 | J19: Trade Equity | K19: =K17-K18 -> 0 | M19: Trade Equity | N19: =N17-N18 -> 0 | P19: Trade Equity | Q19: =Q17-Q18 -> 0 | S19: Trade Equity | T19: =T17-T18 -> 0
A20: Total Equity | B20: =B15+B16+B19 -> -4250 | D20: Total Equity | E20: =E15+E16+E19 -> 0 | G20: Total Equity | H20: =H15+H16+H19 -> 0 | J20: Total Equity | K20: =K15+K16+K19 -> 0 | M20: Total Equity | N20: =N15+N16+N19 -> 0 | P20: Total Equity | Q20: =Q15+Q16+Q19 -> 0 | S20: Total Equity | T20: =T15+T16+T19 -> 0
A22: Total Cost | B22: =B13 -> 34272.96 | D22: Total Cost | E22: =E13 -> 0 | G22: Total Cost | H22: =H13 -> 0 | J22: Total Cost | K22: =K13 -> 0 | M22: Total Cost | N22: =N13 -> 0 | P22: Total Cost | Q22: =Q13 -> 0 | S22: Total Cost | T22: =T13 -> 0
A23: Total Equity | B23: =B20 -> -4250 | D23: Total Equity | E23: =E20 -> 0 | G23: Total Equity | H23: =H20 -> 0 | J23: Total Equity | K23: =K20 -> 0 | M23: Total Equity | N23: =N20 -> 0 | P23: Total Equity | Q23: =Q20 -> 0 | S23: Total Equity | T23: =T20 -> 0
A24: Total Amount Financed | B24: =B22-B33 -> 34272.96 | D24: Total Amount Financed | G24: Total Amount Financed | H24: =H22-H23 -> 0 | J24: Total Amount Financed | K24: =K22-K23 -> 0 | M24: Total Amount Financed | N24: =N22-N23 -> 0 | P24: Total Amount Financed | Q24: =Q22-Q23 -> 0 | S24: Total Amount Financed | T24: =T22-T23 -> 0
A26: Annual % Rate (APR) | B26: 0.0599 | D26: Annual % Rate (APR) | G26: Annual % Rate (APR) | J26: Annual % Rate (APR) | M26: Annual % Rate (APR) | P26: Annual % Rate (APR) | S26: Annual % Rate (APR)
A27: # of Monthly Payments | B27: 75 | D27: # of Monthly Payments | G27: # of Monthly Payments | J27: # of Monthly Payments | M27: # of Monthly Payments | P27: # of Monthly Payments | S27: # of Monthly Payments
A28: Monthly Payment | B28: =-PMT(B26/12,B27,B24) -> 548.96368 | D28: Monthly Payment | G28: Monthly Payment | H28: =-PMT(H26/12,H27,H24) -> #NUM! | J28: Monthly Payment | K28: =-PMT(K26/12,K27,K24) -> #NUM! | M28: Monthly Payment | N28: =-PMT(N26/12,N27,N24) -> #NUM! | P28: Monthly Payment | Q28: =-PMT(Q26/12,Q27,Q24) -> #NUM! | S28: Monthly Payment | T28: =-PMT(T26/12,T27,T24) -> #NUM!
A30: Bank: | D30: Bank: | G30: Bank: | J30: Bank: | M30: Bank: | P30: Bank: | S30: Bank:
A31: COST | B31: 29500 | D31: Cost | E31: 0 | G31: Cost | H31: 0 | J31: Cost | K31: 0 | M31: Cost | N31: 0 | P31: Cost | Q31: 0 | S31: Cost | T31: 0
A32: Pack | B32: 0 | D32: Pack | E32: 0 | G32: Pack | H32: 0 | J32: Pack | K32: 0 | M32: Pack | N32: 0 | P32: Pack | Q32: 0 | S32: Pack | T32: 0
A33: ACV | B33: 0 | D33: ACV | E33: 0 | G33: ACV | H33: 0 | J33: ACV | K33: 0 | M33: ACV | N33: 0 | P33: ACV | Q33: 0 | S33: ACV | T33: 0
A34: Bank Fee % | B34: 0 | D34: Bank Fee % | E34: 0 | G34: Bank Fee % | H34: 0 | J34: Bank Fee % | K34: 0 | M34: Bank Fee % | N34: 0 | P34: Bank Fee % | Q34: 0 | S34: Bank Fee % | T34: 0
A35: Bank Fee | B35: =B34*B24 -> 0 | D35: Bank Fee | E35: =E34*E24 -> 0 | G35: Bank Fee | H35: =H34*H24 -> 0 | J35: Bank Fee | K35: =K34*K24 -> 0 | M35: Bank Fee | N35: =N34*N24 -> 0 | P35: Bank Fee | Q35: =Q34*Q24 -> 0 | S35: Bank Fee | T35: =T34*T24 -> 0
A36: Acq. Fee | B36: 0 | D36: Acq. Fee | E36: 0 | G36: Acq. Fee | H36: 0 | J36: Acq. Fee | K36: 0 | M36: Acq. Fee | N36: 0 | P36: Acq. Fee | Q36: 0 | S36: Acq. Fee | T36: 0
A37: Warranty Cost | B37: 0 | D37: Warranty Cost | E37: 0 | G37: Warranty Cost | H37: 0 | J37: Warranty Cost | K37: 0 | M37: Warranty Cost | N37: 0 | P37: Warranty Cost | Q37: 0 | S37: Warranty Cost | T37: 0
A38: Gap Cost | B38: 0 | D38: Gap Cost | E38: 0 | G38: Gap Cost | H38: 0 | J38: Gap Cost | K38: 0 | M38: Gap Cost | N38: 0 | P38: Gap Cost | Q38: 0 | S38: Gap Cost | T38: 0
A39: Buy Rate | B39: 0 | D39: Buy Rate | E39: 0 | G39: Buy Rate | H39: 0 | J39: Buy Rate | K39: 0 | M39: Buy Rate | N39: 0 | P39: Buy Rate | Q39: 0 | S39: Buy Rate | T39: 0
A40: Book Value | B40: 29500 | D40: Book Value | E40: 0 | G40: Book Value | H40: 0 | J40: Book Value | K40: 0 | M40: Book Value | N40: 0 | P40: Book Value | Q40: 0 | S40: Book Value | T40: 0
A42: Line 3 | B42: =B24/B40 -> 1.1617953 | D42: Line 3 | E42: =(E3-E20)/E31 -> #DIV/0! | G42: Line 3 | H42: =(H3-H20)/H31 -> #DIV/0! | J42: Line 3 | K42: =(K3-K20)/K31 -> #DIV/0! | M42: Line 3 | N42: =(N3-N20)/N31 -> #DIV/0! | P42: Line 3 | Q42: =(Q3-Q20)/Q31 -> #DIV/0! | S42: Line 3 | T42: =(T3-T20)/T31 -> #DIV/0!
A43: Line 5 | B43: =B24/B40 -> 1.1617953 | D43: Line 5 | E43: =E24/E40 -> #DIV/0! | G43: Line 5 | H43: =H24/H40 -> #DIV/0! | J43: Line 5 | K43: =K24/K40 -> #DIV/0! | M43: Line 5 | N43: =N24/N40 -> #DIV/0! | P43: Line 5 | Q43: =Q24/Q40 -> #DIV/0! | S43: Line 5 | T43: =T24/T40 -> #DIV/0!
A45: PRODUCT | B45: =SUM(B10-B37)+(B11-B38) -> 0 | D45: PRODUCT | E45: =SUM(E10-E37)+(E11-E38) -> 0 | G45: PRODUCT | H45: =SUM(H10-H37)+(H11-H38) -> 0 | J45: PRODUCT | K45: =SUM(K10-K37)+(K11-K38) -> 0 | M45: PRODUCT | N45: =SUM(N10-N37)+(N11-N38) -> 0 | P45: PRODUCT | Q45: =SUM(Q10-Q37)+(Q11-Q38) -> 0 | S45: PRODUCT | T45: =SUM(T10-T37)+(T11-T38) -> 0
A46: RESERVE | B46: =-((B27*B28)-((PMT(B39/12,B27,B24)*-1)*B27))*(-0.75) -> 5174.4871 | D46: RESERVE | E46: =-((E27*E28)-((PMT(E39/12,E27,E24)*-1)*E27))*(-0.75) -> #NUM! | G46: RESERVE | H46: =-((H27*H28)-((PMT(H39/12,H27,H24)*-1)*H27))*(-0.75) -> #NUM! | J46: RESERVE | K46: =-((K27*K28)-((PMT(K39/12,K27,K24)*-1)*K27))*(-0.75) -> #NUM! | M46: RESERVE | N46: =-((N27*N28)-((PMT(N39/12,N27,N24)*-1)*N27))*(-0.75) -> #NUM! | P46: RESERVE | Q46: =-((Q27*Q28)-((PMT(Q39/12,Q27,Q24)*-1)*Q27))*(-0.75) -> #NUM! | S46: RESERVE | T46: =-((T27*T28)-((PMT(T39/12,T27,T24)*-1)*T27))*(-0.75) -> #NUM!
A47: FRONT | B47: =SUM((B3-B17)-(B31-B33))-B32-B35-B36 -> -14085 | D47: FRONT | E47: =SUM((E3-E17)-(E31-E33))-E32-E35-E36 -> 0 | G47: FRONT | H47: =SUM((H3-H17)-(H31-H33))-H32-H35-H36 -> 0 | J47: FRONT | K47: =SUM((K3-K17)-(K31-K33))-K32-K35-K36 -> 0 | M47: FRONT | N47: =SUM((N3-N17)-(N31-N33))-N32-N35-N36 -> 0 | P47: FRONT | Q47: =SUM((Q3-Q17)-(Q31-Q33))-Q32-Q35-Q36 -> 0 | S47: FRONT | T47: =SUM((T3-T17)-(T31-T33))-T32-T35-T36 -> 0
A48: TOTAL | B48: =B45+B47 -> -14085 | D48: TOTAL | E48: =E45+E47 -> 0 | G48: TOTAL | H48: =H45+H47 -> 0 | J48: TOTAL | K48: =K45+K47 -> 0 | M48: TOTAL | N48: =N45+N47 -> 0 | P48: TOTAL | Q48: =Q45+Q47 -> 0 | S48: TOTAL | T48: =T45+T47 -> 0

Sheet Sale Rollup
B1: Deal # | C1: Customer Last Name | D1: Source | E1: New, Used, Trade | F1: Year | G1: Make | H1: Model | I1: Front Gross | J1: Total Commission | K1: Split | L1: Salesperson | M1: Percent A | N1: Commission Saleperson 1 | O1: 2nd Salesperson | P1: Percent B | Q1: Commission Saleperson 2
A2: 1 | B2: =IF('DEAL LOG'!H9=ISBLANK(TRUE),"",'DEAL LOG'!H9) | C2: =IF('DEAL LOG'!$I$9=ISBLANK(TRUE),"",'DEAL LOG'!I9) | D2: =IF(#REF!=ISBLANK(TRUE),"",#REF!) -> #REF! | E2: =IF('DEAL LOG'!K9=ISBLANK(TRUE),"",'DEAL LOG'!K9) | F2: =IF('DEAL LOG'!L9=ISBLANK(TRUE),"",'DEAL LOG'!L9) | G2: =IF('DEAL LOG'!M9=ISBLANK(TRUE),"",'DEAL LOG'!M9) | H2: =IF('DEAL LOG'!N9=ISBLANK(TRUE),"",'DEAL LOG'!N9) | I2: =IF('DEAL LOG'!Y9=ISBLANK(TRUE),"",'DEAL LOG'!Y9) | J2: =I2*0.25 -> 0 | K2: =IF(M2<1,"Yes","No") -> No | L2: =IF('DEAL LOG'!W9=ISBLANK(TRUE),"",'DEAL LOG'!W9) | M2: 1 | N2: =J2*M2 -> 0 | O2: =IF('DEAL LOG'!X9=ISBLANK(TRUE),"",'DEAL LOG'!X9) | P2: =IF(#REF!=ISBLANK(TRUE),"",#REF!) -> #REF! | Q2: =J2*P2 -> #REF!
A3: 1 | B3: =IF('DEAL LOG'!H10=ISBLANK(TRUE),"",'DEAL LOG'!H10) -> C20931A | C3: =IF('DEAL LOG'!$I$9=ISBLANK(TRUE),"",'DEAL LOG'!I10) | D3: =IF(#REF!=ISBLANK(TRUE),"",#REF!) -> #REF! | E3: =IF('DEAL LOG'!K10=ISBLANK(TRUE),"",'DEAL LOG'!K10) -> Used | F3: =IF('DEAL LOG'!L10=ISBLANK(TRUE),"",'DEAL LOG'!L10) -> 2025 | G3: =IF('DEAL LOG'!M10=ISBLANK(TRUE),"",'DEAL LOG'!M10) -> HONDA | H3: =IF('DEAL LOG'!N10=ISBLANK(TRUE),"",'DEAL LOG'!N10) -> HR-V | I3: =IF('DEAL LOG'!Y10=ISBLANK(TRUE),"",'DEAL LOG'!Y10) -> 5113.2 | J3: =I3*0.25 -> 1278.3 | K3: =IF(M3<1,"Yes","No") -> Yes | L3: =IF('DEAL LOG'!W10=ISBLANK(TRUE),"",'DEAL LOG'!W10) -> BRYAN ROGERS | M3: 0.5 | N3: =J3*M3 -> 639.15 | O3: =IF('DEAL LOG'!X10=ISBLANK(TRUE),"",'DEAL LOG'!X10) -> NICK WILEY | P3: 0.5 | Q3: =J3*P3 -> 639.15
A4: 1 | B4: =IF('DEAL LOG'!H13=ISBLANK(TRUE),"",'DEAL LOG'!H13) | C4: =IF('DEAL LOG'!$I$9=ISBLANK(TRUE),"",'DEAL LOG'!I13) | D4: =IF(#REF!=ISBLANK(TRUE),"",#REF!) -> #REF! | E4: =IF('DEAL LOG'!K13=ISBLANK(TRUE),"",'DEAL LOG'!K13) | F4: =IF('DEAL LOG'!L13=ISBLANK(TRUE),"",'DEAL LOG'!L13) | G4: =IF('DEAL LOG'!M13=ISBLANK(TRUE),"",'DEAL LOG'!M13) | H4: =IF('DEAL LOG'!N13=ISBLANK(TRUE),"",'DEAL LOG'!N13) | I4: =IF('DEAL LOG'!Y13=ISBLANK(TRUE),"",'DEAL LOG'!Y13) | J4: =I4*0.25 -> 0 | K4: =IF(M4<1,"Yes","No") -> Yes | L4: =IF('DEAL LOG'!W13=ISBLANK(TRUE),"",'DEAL LOG'!W13) | M4: 0.5 | N4: =J4*M4 -> 0 | O4: =IF('DEAL LOG'!X13=ISBLANK(TRUE),"",'DEAL LOG'!X13) | P4: 0.5 | Q4: =J4*P4 -> 0
A5: 1 | B5: =IF(#REF!=ISBLANK(TRUE),"",#REF!) -> #REF! | C5: =IF('DEAL LOG'!$I$9=ISBLANK(TRUE),"",#REF!) | D5: =IF(#REF!=ISBLANK(TRUE),"",#REF!) -> #REF! | E5: =IF(#REF!=ISBLANK(TRUE),"",#REF!) -> #REF! | F5: =IF(#REF!=ISBLANK(TRUE),"",#REF!) -> #REF! | G5: =IF(#REF!=ISBLANK(TRUE),"",#REF!) -> #REF! | H5: =IF(#REF!=ISBLANK(TRUE),"",#REF!) -> #REF! | I5: =IF(#REF!=ISBLANK(TRUE),"",#REF!) -> #REF! | J5: =I5*0.25 -> #REF! | K5: =IF(M5<1,"Yes","No") -> No | L5: =IF(#REF!=ISBLANK(TRUE),"",#REF!) -> #REF! | M5: 1 | N5: =J5*M5 -> #REF! | O5: =IF(#REF!=ISBLANK(TRUE),"",#REF!) -> #REF! | P5: =IF(#REF!=ISBLANK(TRUE),"",#REF!) -> #REF! | Q5: =J5*P5 -> #REF!
A6: 1 | B6: =IF(#REF!=ISBLANK(TRUE),"",#REF!) -> #REF! | C6: =IF('DEAL LOG'!$I$9=ISBLANK(TRUE),"",#REF!) | D6: =IF(#REF!=ISBLANK(TRUE),"",#REF!) -> #REF! | E6: =IF(#REF!=ISBLANK(TRUE),"",#REF!) -> #REF! | F6: =IF(#REF!=ISBLANK(TRUE),"",#REF!) -> #REF! | G6: =IF(#REF!=ISBLANK(TRUE),"",#REF!) -> #REF! | H6: =IF(#REF!=ISBLANK(TRUE),"",#REF!) -> #REF! | I6: =IF(#REF!=ISBLANK(TRUE),"",#REF!) -> #REF! | J6: =I6*0.25 -> #REF! | K6: =IF(M6<1,"Yes","No") -> No | L6: =IF(#REF!=ISBLANK(TRUE),"",#REF!) -> #REF! | M6: 1 | N6: =J6*M6 -> #REF! | O6: =IF(#REF!=ISBLANK(TRUE),"",#REF!) -> #REF! | P6: =IF(#REF!=ISBLANK(TRUE),"",#REF!) -> #REF! | Q6: =J6*P6 -> #REF!
A7: 1 | B7: =IF('DEAL LOG'!H16=ISBLANK(TRUE),"",'DEAL LOG'!H16) -> DC20851 | C7: =IF('DEAL LOG'!$I$9=ISBLANK(TRUE),"",'DEAL LOG'!I16) | D7: =IF(#REF!=ISBLANK(TRUE),"",#REF!) -> #REF! | E7: =IF('DEAL LOG'!K16=ISBLANK(TRUE),"",'DEAL LOG'!K16) -> New | F7: =IF('DEAL LOG'!L16=ISBLANK(TRUE),"",'DEAL LOG'!L16) -> 2026 | G7: =IF('DEAL LOG'!M16=ISBLANK(TRUE),"",'DEAL LOG'!M16) -> HONDA | H7: =IF('DEAL LOG'!N16=ISBLANK(TRUE),"",'DEAL LOG'!N16) -> HR-V | I7: =IF('DEAL LOG'!Y16=ISBLANK(TRUE),"",'DEAL LOG'!Y16) -> 0 | J7: =I7*0.25 -> 0 | K7: =IF(M7<1,"Yes","No") -> Yes | L7: =IF('DEAL LOG'!W16=ISBLANK(TRUE),"",'DEAL LOG'!W16) -> MAYCON MIKE GUIMARAES | M7: 0.5 | N7: =J7*M7 -> 0 | O7: =IF('DEAL LOG'!X16=ISBLANK(TRUE),"",'DEAL LOG'!X16) | P7: 0.5 | Q7: =J7*P7 -> 0
A8: 1 | B8: =IF('DEAL LOG'!H15=ISBLANK(TRUE),"",'DEAL LOG'!H15) -> C20879 | C8: =IF('DEAL LOG'!$I$9=ISBLANK(TRUE),"",'DEAL LOG'!I15) | D8: =IF(#REF!=ISBLANK(TRUE),"",#REF!) -> #REF! | E8: =IF('DEAL LOG'!K15=ISBLANK(TRUE),"",'DEAL LOG'!K15) -> New | F8: =IF('DEAL LOG'!L15=ISBLANK(TRUE),"",'DEAL LOG'!L15) -> 2026 | G8: =IF('DEAL LOG'!M15=ISBLANK(TRUE),"",'DEAL LOG'!M15) -> HONDA | H8: =IF('DEAL LOG'!N15=ISBLANK(TRUE),"",'DEAL LOG'!N15) -> CIVIC | I8: =IF('DEAL LOG'!Y15=ISBLANK(TRUE),"",'DEAL LOG'!Y15) -> 5723.22 | J8: =I8*0.25 -> 1430.805 | K8: =IF(M8<1,"Yes","No") -> No | L8: =IF('DEAL LOG'!W15=ISBLANK(TRUE),"",'DEAL LOG'!W15) -> JOSE TORRES | M8: 1 | N8: =J8*M8 -> 1430.805 | O8: =IF('DEAL LOG'!X15=ISBLANK(TRUE),"",'DEAL LOG'!X15) | P8: =IF(#REF!=ISBLANK(TRUE),"",#REF!) -> #REF! | Q8: =J8*P8 -> #REF!
A9: 1 | B9: =IF(#REF!=ISBLANK(TRUE),"",#REF!) -> #REF! | C9: =IF('DEAL LOG'!$I$9=ISBLANK(TRUE),"",#REF!) | D9: =IF(#REF!=ISBLANK(TRUE),"",#REF!) -> #REF! | E9: =IF(#REF!=ISBLANK(TRUE),"",#REF!) -> #REF! | F9: =IF(#REF!=ISBLANK(TRUE),"",#REF!) -> #REF! | G9: =IF(#REF!=ISBLANK(TRUE),"",#REF!) -> #REF! | H9: =IF(#REF!=ISBLANK(TRUE),"",#REF!) -> #REF! | I9: =IF(#REF!=ISBLANK(TRUE),"",#REF!) -> #REF! | J9: =I9*0.25 -> #REF! | K9: =IF(M9<1,"Yes","No") -> No | L9: =IF(#REF!=ISBLANK(TRUE),"",#REF!) -> #REF! | M9: 1 | N9: =J9*M9 -> #REF! | O9: =IF(#REF!=ISBLANK(TRUE),"",#REF!) -> #REF! | P9: =IF(#REF!=ISBLANK(TRUE),"",#REF!) -> #REF! | Q9: =J9*P9 -> #REF!
A10: 1 | B10: =IF(#REF!=ISBLANK(TRUE),"",#REF!) -> #REF! | C10: =IF('DEAL LOG'!$I$9=ISBLANK(TRUE),"",#REF!) | D10: =IF(#REF!=ISBLANK(TRUE),"",#REF!) -> #REF! | E10: =IF(#REF!=ISBLANK(TRUE),"",#REF!) -> #REF! | F10: =IF(#REF!=ISBLANK(TRUE),"",#REF!) -> #REF! | G10: =IF(#REF!=ISBLANK(TRUE),"",#REF!) -> #REF! | H10: =IF(#REF!=ISBLANK(TRUE),"",#REF!) -> #REF! | I10: =IF(#REF!=ISBLANK(TRUE),"",#REF!) -> #REF! | J10: =I10*0.25 -> #REF! | K10: =IF(M10<1,"Yes","No") -> No | L10: =IF(#REF!=ISBLANK(TRUE),"",#REF!) -> #REF! | M10: 1 | N10: =J10*M10 -> #REF! | O10: =IF(#REF!=ISBLANK(TRUE),"",#REF!) -> #REF! | P10: =IF(#REF!=ISBLANK(TRUE),"",#REF!) -> #REF! | Q10: =J10*P10 -> #REF!
A11: 1 | B11: =IF(#REF!=ISBLANK(TRUE),"",#REF!) -> #REF! | C11: =IF('DEAL LOG'!$I$9=ISBLANK(TRUE),"",#REF!) | D11: =IF(#REF!=ISBLANK(TRUE),"",#REF!) -> #REF! | E11: =IF(#REF!=ISBLANK(TRUE),"",#REF!) -> #REF! | F11: =IF(#REF!=ISBLANK(TRUE),"",#REF!) -> #REF! | G11: =IF(#REF!=ISBLANK(TRUE),"",#REF!) -> #REF! | H11: =IF(#REF!=ISBLANK(TRUE),"",#REF!) -> #REF! | I11: =IF(#REF!=ISBLANK(TRUE),"",#REF!) -> #REF! | J11: =I11*0.25 -> #REF! | K11: =IF(M11<1,"Yes","No") -> Yes | L11: =IF(#REF!=ISBLANK(TRUE),"",#REF!) -> #REF! | M11: 0.5 | N11: =J11*M11 -> #REF! | O11: =IF(#REF!=ISBLANK(TRUE),"",#REF!) -> #REF! | P11: 0.5 | Q11: =J11*P11 -> #REF!
A12: 1 | B12: =IF(#REF!=ISBLANK(TRUE),"",#REF!) -> #REF! | C12: =IF('DEAL LOG'!$I$9=ISBLANK(TRUE),"",#REF!) | D12: =IF(#REF!=ISBLANK(TRUE),"",#REF!) -> #REF! | E12: =IF(#REF!=ISBLANK(TRUE),"",#REF!) -> #REF! | F12: =IF(#REF!=ISBLANK(TRUE),"",#REF!) -> #REF! | G12: =IF(#REF!=ISBLANK(TRUE),"",#REF!) -> #REF! | H12: =IF(#REF!=ISBLANK(TRUE),"",#REF!) -> #REF! | I12: =IF(#REF!=ISBLANK(TRUE),"",#REF!) -> #REF! | J12: =I12*0.25 -> #REF! | K12: =IF(M12<1,"Yes","No") -> No | L12: =IF(#REF!=ISBLANK(TRUE),"",#REF!) -> #REF! | M12: 1 | N12: =J12*M12 -> #REF! | O12: =IF(#REF!=ISBLANK(TRUE),"",#REF!) -> #REF! | P12: =IF(#REF!=ISBLANK(TRUE),"",#REF!) -> #REF! | Q12: =J12*P12 -> #REF!
A13: 1 | B13: =IF('DEAL LOG'!H20=ISBLANK(TRUE),"",'DEAL LOG'!H20) -> XP6290 | C13: =IF('DEAL LOG'!$I$9=ISBLANK(TRUE),"",'DEAL LOG'!I20) | D13: =IF(#REF!=ISBLANK(TRUE),"",#REF!) -> #REF! | E13: =IF('DEAL LOG'!K20=ISBLANK(TRUE),"",'DEAL LOG'!K20) -> Used | F13: =IF('DEAL LOG'!L20=ISBLANK(TRUE),"",'DEAL LOG'!L20) -> 2021 | G13: =IF('DEAL LOG'!M20=ISBLANK(TRUE),"",'DEAL LOG'!M20) -> HYUNDAI | H13: =IF('DEAL LOG'!N20=ISBLANK(TRUE),"",'DEAL LOG'!N20) -> TUCSON | I13: =IF('DEAL LOG'!Y20=ISBLANK(TRUE),"",'DEAL LOG'!Y20) -> 2000 | J13: =I13*0.25 -> 500 | L13: =IF('DEAL LOG'!W20=ISBLANK(TRUE),"",'DEAL LOG'!W20) -> MIKE LASHLEY | N13: =J13*M13 -> 0 | O13: =IF('DEAL LOG'!X20=ISBLANK(TRUE),"",'DEAL LOG'!X20) | P13: =IF(#REF!=ISBLANK(TRUE),"",#REF!) -> #REF! | Q13: =J13*P13 -> #REF!
A14: 1 | B14: =IF('DEAL LOG'!H21=ISBLANK(TRUE),"",'DEAL LOG'!H21) -> C20944 | C14: =IF('DEAL LOG'!$I$9=ISBLANK(TRUE),"",'DEAL LOG'!I21) | D14: =IF(#REF!=ISBLANK(TRUE),"",#REF!) -> #REF! | E14: =IF('DEAL LOG'!K21=ISBLANK(TRUE),"",'DEAL LOG'!K21) -> New | F14: =IF('DEAL LOG'!L21=ISBLANK(TRUE),"",'DEAL LOG'!L21) -> 2026 | G14: =IF('DEAL LOG'!M21=ISBLANK(TRUE),"",'DEAL LOG'!M21) -> HONDA | H14: =IF('DEAL LOG'!N21=ISBLANK(TRUE),"",'DEAL LOG'!N21) -> CIVIC | I14: =IF('DEAL LOG'!Y21=ISBLANK(TRUE),"",'DEAL LOG'!Y21) -> 5562.42 | J14: =I14*0.25 -> 1390.605 | K14: =IF(M14<1,"Yes","No") -> #REF! | L14: =IF('DEAL LOG'!W21=ISBLANK(TRUE),"",'DEAL LOG'!W21) -> HOUSE | M14: =IF(#REF!=ISBLANK(TRUE),"",#REF!) -> #REF! | N14: =J14*M14 -> #REF! | O14: =IF('DEAL LOG'!X21=ISBLANK(TRUE),"",'DEAL LOG'!X21) | P14: =IF(#REF!=ISBLANK(TRUE),"",#REF!) -> #REF! | Q14: =J14*P14 -> #REF!
A15: 1 | B15: =IF('DEAL LOG'!H22=ISBLANK(TRUE),"",'DEAL LOG'!H22) -> C20699 | C15: =IF('DEAL LOG'!$I$9=ISBLANK(TRUE),"",'DEAL LOG'!I22) | D15: =IF(#REF!=ISBLANK(TRUE),"",#REF!) -> #REF! | E15: =IF('DEAL LOG'!K22=ISBLANK(TRUE),"",'DEAL LOG'!K22) -> New | F15: =IF('DEAL LOG'!L22=ISBLANK(TRUE),"",'DEAL LOG'!L22) -> 2025 | G15: =IF('DEAL LOG'!M22=ISBLANK(TRUE),"",'DEAL LOG'!M22) -> HONDA | H15: =IF('DEAL LOG'!N22=ISBLANK(TRUE),"",'DEAL LOG'!N22) -> PILOT | I15: =IF('DEAL LOG'!Y22=ISBLANK(TRUE),"",'DEAL LOG'!Y22) -> 9464.81 | J15: =I15*0.25 -> 2366.2025 | K15: =IF(M15<1,"Yes","No") -> #REF! | L15: =IF('DEAL LOG'!W22=ISBLANK(TRUE),"",'DEAL LOG'!W22) -> BRYAN ROGERS | M15: =IF(#REF!=ISBLANK(TRUE),"",#REF!) -> #REF! | N15: =J15*M15 -> #REF! | O15: =IF('DEAL LOG'!X22=ISBLANK(TRUE),"",'DEAL LOG'!X22) | P15: =IF(#REF!=ISBLANK(TRUE),"",#REF!) -> #REF! | Q15: =J15*P15 -> #REF!
A16: 1 | B16: =IF('DEAL LOG'!H23=ISBLANK(TRUE),"",'DEAL LOG'!H23) -> C20911 | C16: =IF('DEAL LOG'!$I$9=ISBLANK(TRUE),"",'DEAL LOG'!I23) | D16: =IF(#REF!=ISBLANK(TRUE),"",#REF!) -> #REF! | E16: =IF('DEAL LOG'!K23=ISBLANK(TRUE),"",'DEAL LOG'!K23) -> New | F16: =IF('DEAL LOG'!L23=ISBLANK(TRUE),"",'DEAL LOG'!L23) -> 2026 | G16: =IF('DEAL LOG'!M23=ISBLANK(TRUE),"",'DEAL LOG'!M23) -> HONDA | H16: =IF('DEAL LOG'!N23=ISBLANK(TRUE),"",'DEAL LOG'!N23) -> HR-V | I16: =IF('DEAL LOG'!Y23=ISBLANK(TRUE),"",'DEAL LOG'!Y23) -> 0 | J16: =I16*0.25 -> 0 | K16: =IF(M16<1,"Yes","No") -> #REF! | L16: =IF('DEAL LOG'!W23=ISBLANK(TRUE),"",'DEAL LOG'!W23) -> ABDUL AL TABBAH | M16: =IF(#REF!=ISBLANK(TRUE),"",#REF!) -> #REF! | N16: =J16*M16 -> #REF! | O16: =IF('DEAL LOG'!X23=ISBLANK(TRUE),"",'DEAL LOG'!X23) | P16: =IF(#REF!=ISBLANK(TRUE),"",#REF!) -> #REF! | Q16: =J16*P16 -> #REF!
A17: 1 | B17: =IF('DEAL LOG'!H25=ISBLANK(TRUE),"",'DEAL LOG'!H25) -> C20976 | C17: =IF('DEAL LOG'!$I$9=ISBLANK(TRUE),"",'DEAL LOG'!I25) | D17: =IF(#REF!=ISBLANK(TRUE),"",#REF!) -> #REF! | E17: =IF('DEAL LOG'!K25=ISBLANK(TRUE),"",'DEAL LOG'!K25) -> New | F17: =IF('DEAL LOG'!L25=ISBLANK(TRUE),"",'DEAL LOG'!L25) -> 2026 | G17: =IF('DEAL LOG'!M25=ISBLANK(TRUE),"",'DEAL LOG'!M25) -> HONDA | H17: =IF('DEAL LOG'!N25=ISBLANK(TRUE),"",'DEAL LOG'!N25) -> CR-V | I17: =IF('DEAL LOG'!Y25=ISBLANK(TRUE),"",'DEAL LOG'!Y25) -> 4589.8 | J17: =I17*0.25 -> 1147.45 | K17: =IF(M17<1,"Yes","No") -> #REF! | L17: =IF('DEAL LOG'!W25=ISBLANK(TRUE),"",'DEAL LOG'!W25) -> NICK WILEY | M17: =IF(#REF!=ISBLANK(TRUE),"",#REF!) -> #REF! | N17: =J17*M17 -> #REF! | O17: =IF('DEAL LOG'!X25=ISBLANK(TRUE),"",'DEAL LOG'!X25) -> JOSE TORRES | P17: =IF(#REF!=ISBLANK(TRUE),"",#REF!) -> #REF! | Q17: =J17*P17 -> #REF!
A18: 1 | B18: =IF('DEAL LOG'!H28=ISBLANK(TRUE),"",'DEAL LOG'!H28) -> C20935 | C18: =IF('DEAL LOG'!$I$9=ISBLANK(TRUE),"",'DEAL LOG'!I28) | D18: =IF(#REF!=ISBLANK(TRUE),"",#REF!) -> #REF! | E18: =IF('DEAL LOG'!K28=ISBLANK(TRUE),"",'DEAL LOG'!K28) -> New | F18: =IF('DEAL LOG'!L28=ISBLANK(TRUE),"",'DEAL LOG'!L28) -> 2026 | G18: =IF('DEAL LOG'!M28=ISBLANK(TRUE),"",'DEAL LOG'!M28) -> HONDA | H18: =IF('DEAL LOG'!N28=ISBLANK(TRUE),"",'DEAL LOG'!N28) -> CIVIC | I18: =IF('DEAL LOG'!Y28=ISBLANK(TRUE),"",'DEAL LOG'!Y28) -> 3826.42 | J18: =I18*0.25 -> 956.605 | K18: =IF(M18<1,"Yes","No") -> #REF! | L18: =IF('DEAL LOG'!W28=ISBLANK(TRUE),"",'DEAL LOG'!W28) -> HOUSE | M18: =IF(#REF!=ISBLANK(TRUE),"",#REF!) -> #REF! | N18: =J18*M18 -> #REF! | O18: =IF('DEAL LOG'!X28=ISBLANK(TRUE),"",'DEAL LOG'!X28) | P18: =IF(#REF!=ISBLANK(TRUE),"",#REF!) -> #REF! | Q18: =J18*P18 -> #REF!
A19: 1 | B19: =IF(#REF!=ISBLANK(TRUE),"",#REF!) -> #REF! | C19: =IF('DEAL LOG'!$I$9=ISBLANK(TRUE),"",#REF!) | D19: =IF(#REF!=ISBLANK(TRUE),"",#REF!) -> #REF! | E19: =IF(#REF!=ISBLANK(TRUE),"",#REF!) -> #REF! | F19: =IF(#REF!=ISBLANK(TRUE),"",#REF!) -> #REF! | G19: =IF(#REF!=ISBLANK(TRUE),"",#REF!) -> #REF! | H19: =IF(#REF!=ISBLANK(TRUE),"",#REF!) -> #REF! | I19: =IF(#REF!=ISBLANK(TRUE),"",#REF!) -> #REF! | J19: =I19*0.25 -> #REF! | K19: =IF(M19<1,"Yes","No") -> #REF! | L19: =IF(#REF!=ISBLANK(TRUE),"",#REF!) -> #REF! | M19: =IF(#REF!=ISBLANK(TRUE),"",#REF!) -> #REF! | N19: =J19*M19 -> #REF! | O19: =IF(#REF!=ISBLANK(TRUE),"",#REF!) -> #REF! | P19: =IF(#REF!=ISBLANK(TRUE),"",#REF!) -> #REF! | Q19: =J19*P19 -> #REF!
A20: 1 | B20: =IF(#REF!=ISBLANK(TRUE),"",#REF!) -> #REF! | C20: =IF('DEAL LOG'!$I$9=ISBLANK(TRUE),"",#REF!) | D20: =IF(#REF!=ISBLANK(TRUE),"",#REF!) -> #REF! | E20: =IF(#REF!=ISBLANK(TRUE),"",#REF!) -> #REF! | F20: =IF(#REF!=ISBLANK(TRUE),"",#REF!) -> #REF! | G20: =IF(#REF!=ISBLANK(TRUE),"",#REF!) -> #REF! | H20: =IF(#REF!=ISBLANK(TRUE),"",#REF!) -> #REF! | I20: =IF(#REF!=ISBLANK(TRUE),"",#REF!) -> #REF! | J20: =I20*0.25 -> #REF! | K20: =IF(M20<1,"Yes","No") -> #REF! | L20: =IF(#REF!=ISBLANK(TRUE),"",#REF!) -> #REF! | M20: =IF(#REF!=ISBLANK(TRUE),"",#REF!) -> #REF! | N20: =J20*M20 -> #REF! | O20: =IF(#REF!=ISBLANK(TRUE),"",#REF!) -> #REF! | P20: =IF(#REF!=ISBLANK(TRUE),"",#REF!) -> #REF! | Q20: =J20*P20 -> #REF!
A21: 1 | B21: =IF(#REF!=ISBLANK(TRUE),"",#REF!) -> #REF! | C21: =IF('DEAL LOG'!$I$9=ISBLANK(TRUE),"",#REF!) | D21: =IF(#REF!=ISBLANK(TRUE),"",#REF!) -> #REF! | E21: =IF(#REF!=ISBLANK(TRUE),"",#REF!) -> #REF! | F21: =IF(#REF!=ISBLANK(TRUE),"",#REF!) -> #REF! | G21: =IF(#REF!=ISBLANK(TRUE),"",#REF!) -> #REF! | H21: =IF(#REF!=ISBLANK(TRUE),"",#REF!) -> #REF! | I21: =IF(#REF!=ISBLANK(TRUE),"",#REF!) -> #REF! | J21: =I21*0.25 -> #REF! | K21: =IF(M21<1,"Yes","No") -> #REF! | L21: =IF(#REF!=ISBLANK(TRUE),"",#REF!) -> #REF! | M21: =IF(#REF!=ISBLANK(TRUE),"",#REF!) -> #REF! | N21: =J21*M21 -> #REF! | O21: =IF(#REF!=ISBLANK(TRUE),"",#REF!) -> #REF! | P21: =IF(#REF!=ISBLANK(TRUE),"",#REF!) -> #REF! | Q21: =J21*P21 -> #REF!
A22: 2 | B22: =IF('Day 2'!C10=ISBLANK(TRUE),"",'Day 2'!C10) | C22: ISHAM | D22: Flier | E22: =IF('Day 2'!G10=ISBLANK(TRUE),"",'Day 2'!G10) | F22: =IF('Day 2'!H10=ISBLANK(TRUE),"",'Day 2'!H10) | G22: =IF('Day 2'!I10=ISBLANK(TRUE),"",'Day 2'!I10) | H22: =IF('Day 2'!J10=ISBLANK(TRUE),"",'Day 2'!J10) | I22: =IF('Day 2'!W10=ISBLANK(TRUE),"",'Day 2'!W10) | J22: =I22*0.25 -> 0 | K22: =IF(M22<1,"Yes","No") -> No | L22: =IF('Day 2'!S10=ISBLANK(TRUE),"",'Day 2'!S10) | M22: 1 | N22: =J22*M22 -> 0 | O22: =IF('Day 2'!U10=ISBLANK(TRUE),"",'Day 2'!U10) | P22: =IF('Day 2'!V10=ISBLANK(TRUE),"",'Day 2'!V10) | Q22: =J22*P22 -> 0
A23: 2 | B23: =IF('Day 2'!C11=ISBLANK(TRUE),"",'Day 2'!C11) | C23: LAMP | D23: Flier | E23: =IF('Day 2'!G11=ISBLANK(TRUE),"",'Day 2'!G11) | F23: =IF('Day 2'!H11=ISBLANK(TRUE),"",'Day 2'!H11) | G23: =IF('Day 2'!I11=ISBLANK(TRUE),"",'Day 2'!I11) | H23: =IF('Day 2'!J11=ISBLANK(TRUE),"",'Day 2'!J11) | I23: =IF('Day 2'!W11=ISBLANK(TRUE),"",'Day 2'!W11) | J23: =I23*0.25 -> 0 | K23: =IF(M23<1,"Yes","No") -> No | L23: =IF('Day 2'!S11=ISBLANK(TRUE),"",'Day 2'!S11) | M23: 1 | N23: =J23*M23 -> 0 | O23: =IF('Day 2'!U11=ISBLANK(TRUE),"",'Day 2'!U11) | P23: =IF('Day 2'!V11=ISBLANK(TRUE),"",'Day 2'!V11) | Q23: =J23*P23 -> 0
A24: 2 | B24: =IF('Day 2'!C7=ISBLANK(TRUE),"",'Day 2'!C7) | C24: LATOUR | D24: Flier | E24: =IF('Day 2'!G7=ISBLANK(TRUE),"",'Day 2'!G7) | F24: =IF('Day 2'!H7=ISBLANK(TRUE),"",'Day 2'!H7) | G24: =IF('Day 2'!I7=ISBLANK(TRUE),"",'Day 2'!I7) | H24: =IF('Day 2'!J7=ISBLANK(TRUE),"",'Day 2'!J7) | I24: =IF('Day 2'!W7=ISBLANK(TRUE),"",'Day 2'!W7) | J24: =I24*0.25 -> 0 | K24: =IF(M24<1,"Yes","No") -> No | L24: =IF('Day 2'!S7=ISBLANK(TRUE),"",'Day 2'!S7) | M24: 1 | N24: =J24*M24 -> 0 | O24: =IF('Day 2'!U7=ISBLANK(TRUE),"",'Day 2'!U7) | P24: =IF('Day 2'!V7=ISBLANK(TRUE),"",'Day 2'!V7) | Q24: =J24*P24 -> 0
A25: 2 | B25: =IF('Day 2'!C14=ISBLANK(TRUE),"",'Day 2'!C14) | C25: HILL/LYOA | D25: Flier | E25: =IF('Day 2'!G14=ISBLANK(TRUE),"",'Day 2'!G14) | F25: =IF('Day 2'!H14=ISBLANK(TRUE),"",'Day 2'!H14) | G25: =IF('Day 2'!I14=ISBLANK(TRUE),"",'Day 2'!I14) | H25: =IF('Day 2'!J14=ISBLANK(TRUE),"",'Day 2'!J14) | I25: =IF('Day 2'!W14=ISBLANK(TRUE),"",'Day 2'!W14) | J25: =I25*0.25 -> 0 | K25: =IF(M25<1,"Yes","No") -> No | L25: =IF('Day 2'!S14=ISBLANK(TRUE),"",'Day 2'!S14) | M25: 1 | N25: =J25*M25 -> 0 | O25: =IF('Day 2'!U14=ISBLANK(TRUE),"",'Day 2'!U14) | P25: =IF('Day 2'!V14=ISBLANK(TRUE),"",'Day 2'!V14) | Q25: =J25*P25 -> 0
A26: 2 | B26: =IF('Day 2'!C6=ISBLANK(TRUE),"",'Day 2'!C6) | C26: YOUNT | D26: Flier | E26: =IF('Day 2'!G6=ISBLANK(TRUE),"",'Day 2'!G6) | F26: =IF('Day 2'!H6=ISBLANK(TRUE),"",'Day 2'!H6) | G26: =IF('Day 2'!I6=ISBLANK(TRUE),"",'Day 2'!I6) | H26: =IF('Day 2'!J6=ISBLANK(TRUE),"",'Day 2'!J6) | I26: =IF('Day 2'!W6=ISBLANK(TRUE),"",'Day 2'!W6) | J26: =I26*0.25 -> 0 | K26: =IF(M26<1,"Yes","No") -> No | L26: =IF('Day 2'!S6=ISBLANK(TRUE),"",'Day 2'!S6) | M26: 1 | N26: =J26*M26 -> 0 | O26: =IF('Day 2'!U6=ISBLANK(TRUE),"",'Day 2'!U6) | P26: =IF('Day 2'!V6=ISBLANK(TRUE),"",'Day 2'!V6) | Q26: =J26*P26 -> 0
A27: 2 | B27: =IF('Day 2'!C9=ISBLANK(TRUE),"",'Day 2'!C9) | C27: WOOD | D27: Flier | E27: =IF('Day 2'!G9=ISBLANK(TRUE),"",'Day 2'!G9) | F27: =IF('Day 2'!H9=ISBLANK(TRUE),"",'Day 2'!H9) | G27: =IF('Day 2'!I9=ISBLANK(TRUE),"",'Day 2'!I9) | H27: =IF('Day 2'!J9=ISBLANK(TRUE),"",'Day 2'!J9) | I27: =IF('Day 2'!W9=ISBLANK(TRUE),"",'Day 2'!W9) | J27: =I27*0.25 -> 0 | K27: =IF(M27<1,"Yes","No") -> No | L27: =IF('Day 2'!S9=ISBLANK(TRUE),"",'Day 2'!S9) | M27: 1 | N27: =J27*M27 -> 0 | O27: =IF('Day 2'!U9=ISBLANK(TRUE),"",'Day 2'!U9) | Q27: =J27*P27 -> 0
A28: 2 | B28: =IF('Day 2'!C8=ISBLANK(TRUE),"",'Day 2'!C8) | C28: LAFORCE | D28: Flier | E28: =IF('Day 2'!G8=ISBLANK(TRUE),"",'Day 2'!G8) | F28: =IF('Day 2'!H8=ISBLANK(TRUE),"",'Day 2'!H8) | G28: =IF('Day 2'!I8=ISBLANK(TRUE),"",'Day 2'!I8) | H28: =IF('Day 2'!J8=ISBLANK(TRUE),"",'Day 2'!J8) | I28: =IF('Day 2'!W8=ISBLANK(TRUE),"",'Day 2'!W8) | J28: =I28*0.25 -> 0 | K28: =IF(M28<1,"Yes","No") -> No | L28: =IF('Day 2'!S8=ISBLANK(TRUE),"",'Day 2'!S8) | M28: 1 | N28: =J28*M28 -> 0 | O28: =IF('Day 2'!U8=ISBLANK(TRUE),"",'Day 2'!U8) | P28: =IF('Day 2'!V8=ISBLANK(TRUE),"",'Day 2'!V8) | Q28: =J28*P28 -> 0
A29: 2 | B29: =IF('Day 2'!C12=ISBLANK(TRUE),"",'Day 2'!C12) | C29: LUSSIER | D29: Flier | E29: =IF('Day 2'!G12=ISBLANK(TRUE),"",'Day 2'!G12) | F29: =IF('Day 2'!H12=ISBLANK(TRUE),"",'Day 2'!H12) | G29: =IF('Day 2'!I12=ISBLANK(TRUE),"",'Day 2'!I12) | H29: =IF('Day 2'!J12=ISBLANK(TRUE),"",'Day 2'!J12) | I29: =IF('Day 2'!W12=ISBLANK(TRUE),"",'Day 2'!W12) | J29: =I29*0.25 -> 0 | K29: =IF(M29<1,"Yes","No") -> No | L29: =IF('Day 2'!S12=ISBLANK(TRUE),"",'Day 2'!S12) | M29: 1 | N29: =J29*M29 -> 0 | O29: =IF('Day 2'!U12=ISBLANK(TRUE),"",'Day 2'!U12) | P29: =IF('Day 2'!V12=ISBLANK(TRUE),"",'Day 2'!V12) | Q29: =J29*P29 -> 0
A30: 2 | B30: =IF('Day 2'!C13=ISBLANK(TRUE),"",'Day 2'!C13) | C30: =IF('Day 2'!$D$10=ISBLANK(TRUE),"",'Day 2'!D34) | D30: =IF('Day 2'!F13=ISBLANK(TRUE),"",'Day 2'!F13) | E30: =IF('Day 2'!G13=ISBLANK(TRUE),"",'Day 2'!G13) | F30: =IF('Day 2'!H13=ISBLANK(TRUE),"",'Day 2'!H13) | G30: =IF('Day 2'!I13=ISBLANK(TRUE),"",'Day 2'!I13) | H30: =IF('Day 2'!J13=ISBLANK(TRUE),"",'Day 2'!J13) | I30: =IF('Day 2'!W13=ISBLANK(TRUE),"",'Day 2'!W13) | J30: =I30*0.25 -> 0 | K30: =IF(M30<1,"Yes","No") -> No | L30: =IF('Day 2'!S13=ISBLANK(TRUE),"",'Day 2'!S13) | M30: =IF('Day 2'!T13=ISBLANK(TRUE),"",'Day 2'!T13) | N30: =J30*M30 -> 0 | O30: =IF('Day 2'!U13=ISBLANK(TRUE),"",'Day 2'!U13) | P30: =IF('Day 2'!V13=ISBLANK(TRUE),"",'Day 2'!V13) | Q30: =J30*P30 -> 0
A31: 2 | B31: =IF('Day 2'!C15=ISBLANK(TRUE),"",'Day 2'!C15) | C31: =IF('Day 2'!$D$10=ISBLANK(TRUE),"",'Day 2'!D35) | D31: =IF('Day 2'!F15=ISBLANK(TRUE),"",'Day 2'!F15) | E31: =IF('Day 2'!G15=ISBLANK(TRUE),"",'Day 2'!G15) | F31: =IF('Day 2'!H15=ISBLANK(TRUE),"",'Day 2'!H15) | G31: =IF('Day 2'!I15=ISBLANK(TRUE),"",'Day 2'!I15) | H31: =IF('Day 2'!J15=ISBLANK(TRUE),"",'Day 2'!J15) | I31: =IF('Day 2'!W15=ISBLANK(TRUE),"",'Day 2'!W15) | J31: =I31*0.25 -> 0 | K31: =IF(M31<1,"Yes","No") -> No | L31: =IF('Day 2'!S15=ISBLANK(TRUE),"",'Day 2'!S15) | M31: =IF('Day 2'!T15=ISBLANK(TRUE),"",'Day 2'!T15) | N31: =J31*M31 -> 0 | O31: =IF('Day 2'!U15=ISBLANK(TRUE),"",'Day 2'!U15) | P31: =IF('Day 2'!V15=ISBLANK(TRUE),"",'Day 2'!V15) | Q31: =J31*P31 -> 0
A32: 2 | B32: =IF('Day 2'!C16=ISBLANK(TRUE),"",'Day 2'!C16) | C32: =IF('Day 2'!$D$10=ISBLANK(TRUE),"",'Day 2'!D36) | D32: =IF('Day 2'!F16=ISBLANK(TRUE),"",'Day 2'!F16) | E32: =IF('Day 2'!G16=ISBLANK(TRUE),"",'Day 2'!G16) | F32: =IF('Day 2'!H16=ISBLANK(TRUE),"",'Day 2'!H16) | G32: =IF('Day 2'!I16=ISBLANK(TRUE),"",'Day 2'!I16) | H32: =IF('Day 2'!J16=ISBLANK(TRUE),"",'Day 2'!J16) | I32: =IF('Day 2'!W16=ISBLANK(TRUE),"",'Day 2'!W16) | J32: =I32*0.25 -> 0 | K32: =IF(M32<1,"Yes","No") -> No | L32: =IF('Day 2'!S16=ISBLANK(TRUE),"",'Day 2'!S16) | M32: =IF('Day 2'!T16=ISBLANK(TRUE),"",'Day 2'!T16) | N32: =J32*M32 -> 0 | O32: =IF('Day 2'!U16=ISBLANK(TRUE),"",'Day 2'!U16) | P32: =IF('Day 2'!V16=ISBLANK(TRUE),"",'Day 2'!V16) | Q32: =J32*P32 -> 0
A33: 2 | B33: =IF('Day 2'!C17=ISBLANK(TRUE),"",'Day 2'!C17) | C33: =IF('Day 2'!$D$10=ISBLANK(TRUE),"",'Day 2'!D37) | D33: =IF('Day 2'!F17=ISBLANK(TRUE),"",'Day 2'!F17) | E33: =IF('Day 2'!G17=ISBLANK(TRUE),"",'Day 2'!G17) | F33: =IF('Day 2'!H17=ISBLANK(TRUE),"",'Day 2'!H17) | G33: =IF('Day 2'!I17=ISBLANK(TRUE),"",'Day 2'!I17) | H33: =IF('Day 2'!J17=ISBLANK(TRUE),"",'Day 2'!J17) | I33: =IF('Day 2'!W17=ISBLANK(TRUE),"",'Day 2'!W17) | J33: =I33*0.25 -> 0 | K33: =IF(M33<1,"Yes","No") -> No | L33: =IF('Day 2'!S17=ISBLANK(TRUE),"",'Day 2'!S17) | M33: =IF('Day 2'!T17=ISBLANK(TRUE),"",'Day 2'!T17) | N33: =J33*M33 -> 0 | O33: =IF('Day 2'!U17=ISBLANK(TRUE),"",'Day 2'!U17) | P33: =IF('Day 2'!V17=ISBLANK(TRUE),"",'Day 2'!V17) | Q33: =J33*P33 -> 0
A34: 2 | B34: =IF('Day 2'!C18=ISBLANK(TRUE),"",'Day 2'!C18) | C34: =IF('Day 2'!$D$10=ISBLANK(TRUE),"",'Day 2'!D38) | D34: =IF('Day 2'!F18=ISBLANK(TRUE),"",'Day 2'!F18) | E34: =IF('Day 2'!G18=ISBLANK(TRUE),"",'Day 2'!G18) | F34: =IF('Day 2'!H18=ISBLANK(TRUE),"",'Day 2'!H18) | G34: =IF('Day 2'!I18=ISBLANK(TRUE),"",'Day 2'!I18) | H34: =IF('Day 2'!J18=ISBLANK(TRUE),"",'Day 2'!J18) | I34: =IF('Day 2'!W18=ISBLANK(TRUE),"",'Day 2'!W18) | J34: =I34*0.25 -> 0 | K34: =IF(M34<1,"Yes","No") -> No | L34: =IF('Day 2'!S18=ISBLANK(TRUE),"",'Day 2'!S18) | M34: =IF('Day 2'!T18=ISBLANK(TRUE),"",'Day 2'!T18) | N34: =J34*M34 -> 0 | O34: =IF('Day 2'!U18=ISBLANK(TRUE),"",'Day 2'!U18) | P34: =IF('Day 2'!V18=ISBLANK(TRUE),"",'Day 2'!V18) | Q34: =J34*P34 -> 0
A35: 2 | B35: =IF('Day 2'!C19=ISBLANK(TRUE),"",'Day 2'!C19) | C35: =IF('Day 2'!$D$10=ISBLANK(TRUE),"",'Day 2'!D39) | D35: =IF('Day 2'!F19=ISBLANK(TRUE),"",'Day 2'!F19) | E35: =IF('Day 2'!G19=ISBLANK(TRUE),"",'Day 2'!G19) | F35: =IF('Day 2'!H19=ISBLANK(TRUE),"",'Day 2'!H19) | G35: =IF('Day 2'!I19=ISBLANK(TRUE),"",'Day 2'!I19) | H35: =IF('Day 2'!J19=ISBLANK(TRUE),"",'Day 2'!J19) | I35: =IF('Day 2'!W19=ISBLANK(TRUE),"",'Day 2'!W19) | J35: =I35*0.25 -> 0 | K35: =IF(M35<1,"Yes","No") -> No | L35: =IF('Day 2'!S19=ISBLANK(TRUE),"",'Day 2'!S19) | M35: =IF('Day 2'!T19=ISBLANK(TRUE),"",'Day 2'!T19) | N35: =J35*M35 -> 0 | O35: =IF('Day 2'!U19=ISBLANK(TRUE),"",'Day 2'!U19) | P35: =IF('Day 2'!V19=ISBLANK(TRUE),"",'Day 2'!V19) | Q35: =J35*P35 -> 0
A36: 2 | B36: =IF('Day 2'!C20=ISBLANK(TRUE),"",'Day 2'!C20) | C36: =IF('Day 2'!$D$10=ISBLANK(TRUE),"",'Day 2'!D40) | D36: =IF('Day 2'!F20=ISBLANK(TRUE),"",'Day 2'!F20) | E36: =IF('Day 2'!G20=ISBLANK(TRUE),"",'Day 2'!G20) | F36: =IF('Day 2'!H20=ISBLANK(TRUE),"",'Day 2'!H20) | G36: =IF('Day 2'!I20=ISBLANK(TRUE),"",'Day 2'!I20) | H36: =IF('Day 2'!J20=ISBLANK(TRUE),"",'Day 2'!J20) | I36: =IF('Day 2'!W20=ISBLANK(TRUE),"",'Day 2'!W20) | J36: =I36*0.25 -> 0 | K36: =IF(M36<1,"Yes","No") -> No | L36: =IF('Day 2'!S20=ISBLANK(TRUE),"",'Day 2'!S20) | M36: =IF('Day 2'!T20=ISBLANK(TRUE),"",'Day 2'!T20) | N36: =J36*M36 -> 0 | O36: =IF('Day 2'!U20=ISBLANK(TRUE),"",'Day 2'!U20) | P36: =IF('Day 2'!V20=ISBLANK(TRUE),"",'Day 2'!V20) -> 0 | Q36: =J36*P36 -> 0
A37: 2 | B37: =IF('Day 2'!C21=ISBLANK(TRUE),"",'Day 2'!C21) | C37: =IF('Day 2'!$D$10=ISBLANK(TRUE),"",'Day 2'!D41) | D37: =IF('Day 2'!F21=ISBLANK(TRUE),"",'Day 2'!F21) | E37: =IF('Day 2'!G21=ISBLANK(TRUE),"",'Day 2'!G21) | F37: =IF('Day 2'!H21=ISBLANK(TRUE),"",'Day 2'!H21) | G37: =IF('Day 2'!I21=ISBLANK(TRUE),"",'Day 2'!I21) | H37: =IF('Day 2'!J21=ISBLANK(TRUE),"",'Day 2'!J21) | I37: =IF('Day 2'!W21=ISBLANK(TRUE),"",'Day 2'!W21) | J37: =I37*0.25 -> 0 | K37: =IF(M37<1,"Yes","No") -> No | L37: =IF('Day 2'!S21=ISBLANK(TRUE),"",'Day 2'!S21) | M37: =IF('Day 2'!T21=ISBLANK(TRUE),"",'Day 2'!T21) | N37: =J37*M37 -> 0 | O37: =IF('Day 2'!U21=ISBLANK(TRUE),"",'Day 2'!U21) | P37: =IF('Day 2'!V21=ISBLANK(TRUE),"",'Day 2'!V21) -> 0 | Q37: =J37*P37 -> 0
A38: 2 | B38: =IF('Day 2'!C22=ISBLANK(TRUE),"",'Day 2'!C22) | C38: =IF('Day 2'!$D$10=ISBLANK(TRUE),"",'Day 2'!D42) | D38: =IF('Day 2'!F22=ISBLANK(TRUE),"",'Day 2'!F22) | E38: =IF('Day 2'!G22=ISBLANK(TRUE),"",'Day 2'!G22) | F38: =IF('Day 2'!H22=ISBLANK(TRUE),"",'Day 2'!H22) | G38: =IF('Day 2'!I22=ISBLANK(TRUE),"",'Day 2'!I22) | H38: =IF('Day 2'!J22=ISBLANK(TRUE),"",'Day 2'!J22) | I38: =IF('Day 2'!W22=ISBLANK(TRUE),"",'Day 2'!W22) | J38: =I38*0.25 -> 0 | K38: =IF(M38<1,"Yes","No") -> No | L38: =IF('Day 2'!S22=ISBLANK(TRUE),"",'Day 2'!S22) | M38: =IF('Day 2'!T22=ISBLANK(TRUE),"",'Day 2'!T22) | N38: =J38*M38 -> 0 | O38: =IF('Day 2'!U22=ISBLANK(TRUE),"",'Day 2'!U22) | P38: =IF('Day 2'!V22=ISBLANK(TRUE),"",'Day 2'!V22) -> 0 | Q38: =J38*P38 -> 0
A39: 2 | B39: =IF('Day 2'!C23=ISBLANK(TRUE),"",'Day 2'!C23) | C39: =IF('Day 2'!$D$10=ISBLANK(TRUE),"",'Day 2'!D39) | D39: =IF('Day 2'!F23=ISBLANK(TRUE),"",'Day 2'!F23) | E39: =IF('Day 2'!G23=ISBLANK(TRUE),"",'Day 2'!G23) | F39: =IF('Day 2'!H23=ISBLANK(TRUE),"",'Day 2'!H23) | G39: =IF('Day 2'!I23=ISBLANK(TRUE),"",'Day 2'!I23) | H39: =IF('Day 2'!J23=ISBLANK(TRUE),"",'Day 2'!J23) | I39: =IF('Day 2'!W23=ISBLANK(TRUE),"",'Day 2'!W23) | J39: =I39*0.25 -> 0 | K39: =IF(M39<1,"Yes","No") -> No | L39: =IF('Day 2'!S23=ISBLANK(TRUE),"",'Day 2'!S23) | M39: =IF('Day 2'!T23=ISBLANK(TRUE),"",'Day 2'!T23) | N39: =J39*M39 -> 0 | O39: =IF('Day 2'!U23=ISBLANK(TRUE),"",'Day 2'!U23) | P39: =IF('Day 2'!V23=ISBLANK(TRUE),"",'Day 2'!V23) -> 0 | Q39: =J39*P39 -> 0
A40: 2 | B40: =IF('Day 2'!C24=ISBLANK(TRUE),"",'Day 2'!C24) | C40: =IF('Day 2'!$D$10=ISBLANK(TRUE),"",'Day 2'!D40) | D40: =IF('Day 2'!F24=ISBLANK(TRUE),"",'Day 2'!F24) | E40: =IF('Day 2'!G24=ISBLANK(TRUE),"",'Day 2'!G24) | F40: =IF('Day 2'!H24=ISBLANK(TRUE),"",'Day 2'!H24) | G40: =IF('Day 2'!I24=ISBLANK(TRUE),"",'Day 2'!I24) | H40: =IF('Day 2'!J24=ISBLANK(TRUE),"",'Day 2'!J24) | I40: =IF('Day 2'!W24=ISBLANK(TRUE),"",'Day 2'!W24) | J40: =I40*0.25 -> 0 | K40: =IF(M40<1,"Yes","No") -> No | L40: =IF('Day 2'!S24=ISBLANK(TRUE),"",'Day 2'!S24) | M40: =IF('Day 2'!T24=ISBLANK(TRUE),"",'Day 2'!T24) | N40: =J40*M40 -> 0 | O40: =IF('Day 2'!U24=ISBLANK(TRUE),"",'Day 2'!U24) | P40: =IF('Day 2'!V24=ISBLANK(TRUE),"",'Day 2'!V24) -> 0 | Q40: =J40*P40 -> 0
A41: 2 | B41: =IF('Day 2'!C25=ISBLANK(TRUE),"",'Day 2'!C25) | C41: =IF('Day 2'!$D$10=ISBLANK(TRUE),"",'Day 2'!D41) | D41: =IF('Day 2'!F25=ISBLANK(TRUE),"",'Day 2'!F25) | E41: =IF('Day 2'!G25=ISBLANK(TRUE),"",'Day 2'!G25) | F41: =IF('Day 2'!H25=ISBLANK(TRUE),"",'Day 2'!H25) | G41: =IF('Day 2'!I25=ISBLANK(TRUE),"",'Day 2'!I25) | H41: =IF('Day 2'!J25=ISBLANK(TRUE),"",'Day 2'!J25) | I41: =IF('Day 2'!W25=ISBLANK(TRUE),"",'Day 2'!W25) | J41: =I41*0.25 -> 0 | K41: =IF(M41<1,"Yes","No") -> No | L41: =IF('Day 2'!S25=ISBLANK(TRUE),"",'Day 2'!S25) | M41: =IF('Day 2'!T25=ISBLANK(TRUE),"",'Day 2'!T25) | N41: =J41*M41 -> 0 | O41: =IF('Day 2'!U25=ISBLANK(TRUE),"",'Day 2'!U25) | P41: =IF('Day 2'!V25=ISBLANK(TRUE),"",'Day 2'!V25) -> 0 | Q41: =J41*P41 -> 0
A42: 3 | B42: =IF('Day 3'!C6=ISBLANK(TRUE),"",'Day 3'!C6) | C42: =IF('Day 3'!$D$6=ISBLANK(TRUE),"",'Day 3'!D6) | D42: =IF('Day 3'!F6=ISBLANK(TRUE),"",'Day 3'!F6) | E42: =IF('Day 3'!G6=ISBLANK(TRUE),"",'Day 3'!G6) | F42: =IF('Day 3'!H6=ISBLANK(TRUE),"",'Day 3'!H6) | G42: =IF('Day 3'!I6=ISBLANK(TRUE),"",'Day 3'!I6) | H42: =IF('Day 3'!J6=ISBLANK(TRUE),"",'Day 3'!J6) | I42: =IF('Day 3'!W6=ISBLANK(TRUE),"",'Day 3'!W6) | J42: =I42*0.25 -> 0 | K42: =IF(M42<1,"Yes","No") -> No | L42: =IF('Day 3'!S6=ISBLANK(TRUE),"",'Day 3'!S6) | M42: 1 | N42: =J42*M42 -> 0 | O42: =IF('Day 3'!U6=ISBLANK(TRUE),"",'Day 3'!U6) | P42: =IF('Day 3'!V6=ISBLANK(TRUE),"",'Day 3'!V6) | Q42: =J42*P42 -> 0
A43: 3 | B43: =IF('Day 3'!C7=ISBLANK(TRUE),"",'Day 3'!C7) | C43: =IF('Day 3'!$D$6=ISBLANK(TRUE),"",'Day 3'!D7) | D43: =IF('Day 3'!F7=ISBLANK(TRUE),"",'Day 3'!F7) | E43: =IF('Day 3'!G7=ISBLANK(TRUE),"",'Day 3'!G7) | F43: =IF('Day 3'!H7=ISBLANK(TRUE),"",'Day 3'!H7) | G43: =IF('Day 3'!I7=ISBLANK(TRUE),"",'Day 3'!I7) | H43: =IF('Day 3'!J7=ISBLANK(TRUE),"",'Day 3'!J7) | I43: =IF('Day 3'!W7=ISBLANK(TRUE),"",'Day 3'!W7) | J43: =I43*0.25 -> 0 | K43: =IF(M43<1,"Yes","No") -> No | L43: =IF('Day 3'!S7=ISBLANK(TRUE),"",'Day 3'!S7) | M43: 1 | N43: =J43*M43 -> 0 | O43: =IF('Day 3'!U7=ISBLANK(TRUE),"",'Day 3'!U7) | P43: =IF('Day 3'!V7=ISBLANK(TRUE),"",'Day 3'!V7) | Q43: =J43*P43 -> 0
A44: 3 | B44: =IF('Day 3'!C8=ISBLANK(TRUE),"",'Day 3'!C8) | C44: =IF('Day 3'!$D$6=ISBLANK(TRUE),"",'Day 3'!D8) | D44: =IF('Day 3'!F8=ISBLANK(TRUE),"",'Day 3'!F8) | E44: =IF('Day 3'!G8=ISBLANK(TRUE),"",'Day 3'!G8) | F44: =IF('Day 3'!H8=ISBLANK(TRUE),"",'Day 3'!H8) | G44: =IF('Day 3'!I8=ISBLANK(TRUE),"",'Day 3'!I8) | H44: =IF('Day 3'!J8=ISBLANK(TRUE),"",'Day 3'!J8) | I44: =IF('Day 3'!W8=ISBLANK(TRUE),"",'Day 3'!W8) | J44: =I44*0.25 -> 0 | K44: =IF(M44<1,"Yes","No") -> No | L44: =IF('Day 3'!S8=ISBLANK(TRUE),"",'Day 3'!S8) | M44: 1 | N44: =J44*M44 -> 0 | O44: =IF('Day 3'!U8=ISBLANK(TRUE),"",'Day 3'!U8) | P44: =IF('Day 3'!V8=ISBLANK(TRUE),"",'Day 3'!V8) | Q44: =J44*P44 -> 0
A45: 3 | B45: =IF('Day 3'!C9=ISBLANK(TRUE),"",'Day 3'!C9) | C45: =IF('Day 3'!$D$6=ISBLANK(TRUE),"",'Day 3'!D9) | D45: =IF('Day 3'!F9=ISBLANK(TRUE),"",'Day 3'!F9) | E45: =IF('Day 3'!G9=ISBLANK(TRUE),"",'Day 3'!G9) | F45: =IF('Day 3'!H9=ISBLANK(TRUE),"",'Day 3'!H9) | G45: =IF('Day 3'!I9=ISBLANK(TRUE),"",'Day 3'!I9) | H45: =IF('Day 3'!J9=ISBLANK(TRUE),"",'Day 3'!J9) | I45: =IF('Day 3'!W9=ISBLANK(TRUE),"",'Day 3'!W9) | J45: =I45*0.25 -> 0 | K45: =IF(M45<1,"Yes","No") -> No | L45: =IF('Day 3'!S9=ISBLANK(TRUE),"",'Day 3'!S9) | M45: 1 | N45: =J45*M45 -> 0 | O45: =IF('Day 3'!U9=ISBLANK(TRUE),"",'Day 3'!U9) | P45: =IF('Day 3'!V9=ISBLANK(TRUE),"",'Day 3'!V9) | Q45: =J45*P45 -> 0
A46: 3 | B46: =IF('Day 3'!C10=ISBLANK(TRUE),"",'Day 3'!C10) | C46: =IF('Day 3'!$D$6=ISBLANK(TRUE),"",'Day 3'!D10) | D46: =IF('Day 3'!F10=ISBLANK(TRUE),"",'Day 3'!F10) | E46: =IF('Day 3'!G10=ISBLANK(TRUE),"",'Day 3'!G10) | F46: =IF('Day 3'!H10=ISBLANK(TRUE),"",'Day 3'!H10) | G46: =IF('Day 3'!I10=ISBLANK(TRUE),"",'Day 3'!I10) | H46: =IF('Day 3'!J10=ISBLANK(TRUE),"",'Day 3'!J10) | I46: =IF('Day 3'!W10=ISBLANK(TRUE),"",'Day 3'!W10) | J46: =I46*0.25 -> 0 | K46: =IF(M46<1,"Yes","No") -> No | L46: =IF('Day 3'!S10=ISBLANK(TRUE),"",'Day 3'!S10) | M46: 1 | N46: =J46*M46 -> 0 | O46: =IF('Day 3'!U10=ISBLANK(TRUE),"",'Day 3'!U10) | P46: =IF('Day 3'!V10=ISBLANK(TRUE),"",'Day 3'!V10) | Q46: =J46*P46 -> 0
A47: 3 | B47: =IF('Day 3'!C11=ISBLANK(TRUE),"",'Day 3'!C11) | C47: =IF('Day 3'!$D$6=ISBLANK(TRUE),"",'Day 3'!D11) | D47: =IF('Day 3'!F11=ISBLANK(TRUE),"",'Day 3'!F11) | E47: =IF('Day 3'!G11=ISBLANK(TRUE),"",'Day 3'!G11) | F47: =IF('Day 3'!H11=ISBLANK(TRUE),"",'Day 3'!H11) | G47: =IF('Day 3'!I11=ISBLANK(TRUE),"",'Day 3'!I11) | H47: =IF('Day 3'!J11=ISBLANK(TRUE),"",'Day 3'!J11) | I47: =IF('Day 3'!W11=ISBLANK(TRUE),"",'Day 3'!W11) | J47: =I47*0.25 -> 0 | K47: =IF(M47<1,"Yes","No") -> No | L47: =IF('Day 3'!S11=ISBLANK(TRUE),"",'Day 3'!S11) | M47: 1 | N47: =J47*M47 -> 0 | O47: =IF('Day 3'!U11=ISBLANK(TRUE),"",'Day 3'!U11) | P47: =IF('Day 3'!V11=ISBLANK(TRUE),"",'Day 3'!V11) | Q47: =J47*P47 -> 0
A48: 3 | B48: =IF('Day 3'!C12=ISBLANK(TRUE),"",'Day 3'!C12) | C48: =IF('Day 3'!$D$6=ISBLANK(TRUE),"",'Day 3'!D12) | D48: =IF('Day 3'!F12=ISBLANK(TRUE),"",'Day 3'!F12) | E48: =IF('Day 3'!G12=ISBLANK(TRUE),"",'Day 3'!G12) | F48: =IF('Day 3'!H12=ISBLANK(TRUE),"",'Day 3'!H12) | G48: =IF('Day 3'!I12=ISBLANK(TRUE),"",'Day 3'!I12) | H48: =IF('Day 3'!J12=ISBLANK(TRUE),"",'Day 3'!J12) | I48: =IF('Day 3'!W12=ISBLANK(TRUE),"",'Day 3'!W12) | J48: =I48*0.25 -> 0 | K48: =IF(M48<1,"Yes","No") -> No | L48: =IF('Day 3'!S12=ISBLANK(TRUE),"",'Day 3'!S12) | M48: 1 | N48: =J48*M48 -> 0 | O48: =IF('Day 3'!U12=ISBLANK(TRUE),"",'Day 3'!U12) | P48: =IF('Day 3'!V12=ISBLANK(TRUE),"",'Day 3'!V12) | Q48: =J48*P48 -> 0
A49: 3 | B49: =IF('Day 3'!C14=ISBLANK(TRUE),"",'Day 3'!C14) | C49: =IF('Day 3'!$D$6=ISBLANK(TRUE),"",'Day 3'!D14) | D49: =IF('Day 3'!F14=ISBLANK(TRUE),"",'Day 3'!F14) | E49: =IF('Day 3'!G14=ISBLANK(TRUE),"",'Day 3'!G14) | F49: =IF('Day 3'!H14=ISBLANK(TRUE),"",'Day 3'!H14) | G49: =IF('Day 3'!I14=ISBLANK(TRUE),"",'Day 3'!I14) | H49: =IF('Day 3'!J14=ISBLANK(TRUE),"",'Day 3'!J14) | I49: =IF('Day 3'!W14=ISBLANK(TRUE),"",'Day 3'!W14) | J49: =I49*0.25 -> 0 | K49: =IF(M49<1,"Yes","No") -> No | L49: =IF('Day 3'!S14=ISBLANK(TRUE),"",'Day 3'!S14) | M49: 1 | N49: =J49*M49 -> 0 | O49: =IF('Day 3'!U14=ISBLANK(TRUE),"",'Day 3'!U14) | P49: =IF('Day 3'!V14=ISBLANK(TRUE),"",'Day 3'!V14) | Q49: =J49*P49 -> 0
A50: 3 | B50: =IF('Day 3'!C15=ISBLANK(TRUE),"",'Day 3'!C15) | C50: =IF('Day 3'!$D$6=ISBLANK(TRUE),"",'Day 3'!D15) | D50: =IF('Day 3'!F15=ISBLANK(TRUE),"",'Day 3'!F15) | E50: =IF('Day 3'!G15=ISBLANK(TRUE),"",'Day 3'!G15) | F50: =IF('Day 3'!H15=ISBLANK(TRUE),"",'Day 3'!H15) | G50: =IF('Day 3'!I15=ISBLANK(TRUE),"",'Day 3'!I15) | H50: =IF('Day 3'!J15=ISBLANK(TRUE),"",'Day 3'!J15) | I50: =IF('Day 3'!W15=ISBLANK(TRUE),"",'Day 3'!W15) | J50: =I50*0.25 -> 0 | K50: =IF(M50<1,"Yes","No") -> No | L50: =IF('Day 3'!S15=ISBLANK(TRUE),"",'Day 3'!S15) | M50: 1 | N50: =J50*M50 -> 0 | O50: =IF('Day 3'!U15=ISBLANK(TRUE),"",'Day 3'!U15) | P50: =IF('Day 3'!V15=ISBLANK(TRUE),"",'Day 3'!V15) | Q50: =J50*P50 -> 0
A51: 3 | B51: =IF('Day 3'!C16=ISBLANK(TRUE),"",'Day 3'!C16) | C51: =IF('Day 3'!$D$6=ISBLANK(TRUE),"",'Day 3'!D16) | D51: =IF('Day 3'!F16=ISBLANK(TRUE),"",'Day 3'!F16) | E51: =IF('Day 3'!G16=ISBLANK(TRUE),"",'Day 3'!G16) | F51: =IF('Day 3'!H16=ISBLANK(TRUE),"",'Day 3'!H16) | G51: =IF('Day 3'!I16=ISBLANK(TRUE),"",'Day 3'!I16) | H51: =IF('Day 3'!J16=ISBLANK(TRUE),"",'Day 3'!J16) | I51: =IF('Day 3'!W16=ISBLANK(TRUE),"",'Day 3'!W16) | J51: =I51*0.25 -> 0 | K51: =IF(M51<1,"Yes","No") -> No | L51: =IF('Day 3'!S16=ISBLANK(TRUE),"",'Day 3'!S16) | M51: 1 | N51: =J51*M51 -> 0 | O51: =IF('Day 3'!U16=ISBLANK(TRUE),"",'Day 3'!U16) | P51: =IF('Day 3'!V16=ISBLANK(TRUE),"",'Day 3'!V16) | Q51: =J51*P51 -> 0
A52: 3 | B52: =IF('Day 3'!C17=ISBLANK(TRUE),"",'Day 3'!C17) | C52: =IF('Day 3'!$D$6=ISBLANK(TRUE),"",'Day 3'!D17) | D52: =IF('Day 3'!F17=ISBLANK(TRUE),"",'Day 3'!F17) | E52: =IF('Day 3'!G17=ISBLANK(TRUE),"",'Day 3'!G17) | F52: =IF('Day 3'!H17=ISBLANK(TRUE),"",'Day 3'!H17) | G52: =IF('Day 3'!I17=ISBLANK(TRUE),"",'Day 3'!I17) | H52: =IF('Day 3'!J17=ISBLANK(TRUE),"",'Day 3'!J17) | I52: =IF('Day 3'!W17=ISBLANK(TRUE),"",'Day 3'!W17) | J52: =I52*0.25 -> 0 | K52: =IF(M52<1,"Yes","No") -> No | L52: =IF('Day 3'!S17=ISBLANK(TRUE),"",'Day 3'!S17) | M52: 1 | N52: =J52*M52 -> 0 | O52: =IF('Day 3'!U17=ISBLANK(TRUE),"",'Day 3'!U17) | P52: =IF('Day 3'!V17=ISBLANK(TRUE),"",'Day 3'!V17) | Q52: =J52*P52 -> 0
A53: 3 | B53: =IF('Day 3'!C18=ISBLANK(TRUE),"",'Day 3'!C18) | C53: =IF('Day 3'!$D$6=ISBLANK(TRUE),"",'Day 3'!D18) | D53: =IF('Day 3'!F18=ISBLANK(TRUE),"",'Day 3'!F18) | E53: =IF('Day 3'!G18=ISBLANK(TRUE),"",'Day 3'!G18) | F53: =IF('Day 3'!H18=ISBLANK(TRUE),"",'Day 3'!H18) | G53: =IF('Day 3'!I18=ISBLANK(TRUE),"",'Day 3'!I18) | H53: =IF('Day 3'!J18=ISBLANK(TRUE),"",'Day 3'!J18) | I53: =IF('Day 3'!W18=ISBLANK(TRUE),"",'Day 3'!W18) | J53: =I53*0.25 -> 0 | K53: =IF(M53<1,"Yes","No") -> No | L53: =IF('Day 3'!S18=ISBLANK(TRUE),"",'Day 3'!S18) | M53: 1 | N53: =J53*M53 -> 0 | O53: =IF('Day 3'!U18=ISBLANK(TRUE),"",'Day 3'!U18) | P53: =IF('Day 3'!V18=ISBLANK(TRUE),"",'Day 3'!V18) | Q53: =J53*P53 -> 0
A54: 3 | B54: =IF('Day 3'!C19=ISBLANK(TRUE),"",'Day 3'!C19) | C54: =IF('Day 3'!$D$6=ISBLANK(TRUE),"",'Day 3'!D19) | D54: =IF('Day 3'!F19=ISBLANK(TRUE),"",'Day 3'!F19) | E54: =IF('Day 3'!G19=ISBLANK(TRUE),"",'Day 3'!G19) | F54: =IF('Day 3'!H19=ISBLANK(TRUE),"",'Day 3'!H19) | G54: =IF('Day 3'!I19=ISBLANK(TRUE),"",'Day 3'!I19) | H54: =IF('Day 3'!J19=ISBLANK(TRUE),"",'Day 3'!J19) | I54: =IF('Day 3'!W19=ISBLANK(TRUE),"",'Day 3'!W19) | J54: =I54*0.25 -> 0 | K54: =IF(M54<1,"Yes","No") -> No | L54: =IF('Day 3'!S19=ISBLANK(TRUE),"",'Day 3'!S19) | M54: =IF('Day 3'!T19=ISBLANK(TRUE),"",'Day 3'!T19) | N54: =J54*M54 -> 0 | O54: =IF('Day 3'!U19=ISBLANK(TRUE),"",'Day 3'!U19) | P54: =IF('Day 3'!V19=ISBLANK(TRUE),"",'Day 3'!V19) -> 0 | Q54: =J54*P54 -> 0
A55: 3 | B55: =IF('Day 3'!C20=ISBLANK(TRUE),"",'Day 3'!C20) | C55: =IF('Day 3'!$D$6=ISBLANK(TRUE),"",'Day 3'!D20) | D55: =IF('Day 3'!F20=ISBLANK(TRUE),"",'Day 3'!F20) | E55: =IF('Day 3'!G20=ISBLANK(TRUE),"",'Day 3'!G20) | F55: =IF('Day 3'!H20=ISBLANK(TRUE),"",'Day 3'!H20) | G55: =IF('Day 3'!I20=ISBLANK(TRUE),"",'Day 3'!I20) | H55: =IF('Day 3'!J20=ISBLANK(TRUE),"",'Day 3'!J20) | I55: =IF('Day 3'!W20=ISBLANK(TRUE),"",'Day 3'!W20) | J55: =I55*0.25 -> 0 | K55: =IF(M55<1,"Yes","No") -> No | L55: =IF('Day 3'!S20=ISBLANK(TRUE),"",'Day 3'!S20) | M55: =IF('Day 3'!T20=ISBLANK(TRUE),"",'Day 3'!T20) | N55: =J55*M55 -> 0 | O55: =IF('Day 3'!U20=ISBLANK(TRUE),"",'Day 3'!U20) | P55: =IF('Day 3'!V20=ISBLANK(TRUE),"",'Day 3'!V20) -> 0 | Q55: =J55*P55 -> 0
A56: 3 | B56: =IF('Day 3'!C21=ISBLANK(TRUE),"",'Day 3'!C21) | C56: =IF('Day 3'!$D$6=ISBLANK(TRUE),"",'Day 3'!D21) | D56: =IF('Day 3'!F21=ISBLANK(TRUE),"",'Day 3'!F21) | E56: =IF('Day 3'!G21=ISBLANK(TRUE),"",'Day 3'!G21) | F56: =IF('Day 3'!H21=ISBLANK(TRUE),"",'Day 3'!H21) | G56: =IF('Day 3'!I21=ISBLANK(TRUE),"",'Day 3'!I21) | H56: =IF('Day 3'!J21=ISBLANK(TRUE),"",'Day 3'!J21) | I56: =IF('Day 3'!W21=ISBLANK(TRUE),"",'Day 3'!W21) | J56: =I56*0.25 -> 0 | K56: =IF(M56<1,"Yes","No") -> No | L56: =IF('Day 3'!S21=ISBLANK(TRUE),"",'Day 3'!S21) | M56: =IF('Day 3'!T21=ISBLANK(TRUE),"",'Day 3'!T21) | N56: =J56*M56 -> 0 | O56: =IF('Day 3'!U21=ISBLANK(TRUE),"",'Day 3'!U21) | P56: =IF('Day 3'!V21=ISBLANK(TRUE),"",'Day 3'!V21) -> 0 | Q56: =J56*P56 -> 0
A57: 3 | B57: =IF('Day 3'!C22=ISBLANK(TRUE),"",'Day 3'!C22) | C57: =IF('Day 3'!$D$6=ISBLANK(TRUE),"",'Day 3'!D22) | D57: =IF('Day 3'!F22=ISBLANK(TRUE),"",'Day 3'!F22) | E57: =IF('Day 3'!G22=ISBLANK(TRUE),"",'Day 3'!G22) | F57: =IF('Day 3'!H22=ISBLANK(TRUE),"",'Day 3'!H22) | G57: =IF('Day 3'!I22=ISBLANK(TRUE),"",'Day 3'!I22) | H57: =IF('Day 3'!J22=ISBLANK(TRUE),"",'Day 3'!J22) | I57: =IF('Day 3'!W22=ISBLANK(TRUE),"",'Day 3'!W22) | J57: =I57*0.25 -> 0 | K57: =IF(M57<1,"Yes","No") -> No | L57: =IF('Day 3'!S22=ISBLANK(TRUE),"",'Day 3'!S22) | M57: =IF('Day 3'!T22=ISBLANK(TRUE),"",'Day 3'!T22) | N57: =J57*M57 -> 0 | O57: =IF('Day 3'!U22=ISBLANK(TRUE),"",'Day 3'!U22) | P57: =IF('Day 3'!V22=ISBLANK(TRUE),"",'Day 3'!V22) -> 0 | Q57: =J57*P57 -> 0
A58: 3 | B58: =IF('Day 3'!C23=ISBLANK(TRUE),"",'Day 3'!C23) | C58: =IF('Day 3'!$D$6=ISBLANK(TRUE),"",'Day 3'!D23) | D58: =IF('Day 3'!F23=ISBLANK(TRUE),"",'Day 3'!F23) | E58: =IF('Day 3'!G23=ISBLANK(TRUE),"",'Day 3'!G23) | F58: =IF('Day 3'!H23=ISBLANK(TRUE),"",'Day 3'!H23) | G58: =IF('Day 3'!I23=ISBLANK(TRUE),"",'Day 3'!I23) | H58: =IF('Day 3'!J23=ISBLANK(TRUE),"",'Day 3'!J23) | I58: =IF('Day 3'!W23=ISBLANK(TRUE),"",'Day 3'!W23) | J58: =I58*0.25 -> 0 | K58: =IF(M58<1,"Yes","No") -> No | L58: =IF('Day 3'!S23=ISBLANK(TRUE),"",'Day 3'!S23) | M58: =IF('Day 3'!T23=ISBLANK(TRUE),"",'Day 3'!T23) | N58: =J58*M58 -> 0 | O58: =IF('Day 3'!U23=ISBLANK(TRUE),"",'Day 3'!U23) | P58: =IF('Day 3'!V23=ISBLANK(TRUE),"",'Day 3'!V23) -> 0 | Q58: =J58*P58 -> 0
A59: 3 | B59: =IF('Day 3'!C24=ISBLANK(TRUE),"",'Day 3'!C24) | C59: =IF('Day 3'!$D$6=ISBLANK(TRUE),"",'Day 3'!D24) | D59: =IF('Day 3'!F24=ISBLANK(TRUE),"",'Day 3'!F24) | E59: =IF('Day 3'!G24=ISBLANK(TRUE),"",'Day 3'!G24) | F59: =IF('Day 3'!H24=ISBLANK(TRUE),"",'Day 3'!H24) | G59: =IF('Day 3'!I24=ISBLANK(TRUE),"",'Day 3'!I24) | H59: =IF('Day 3'!J24=ISBLANK(TRUE),"",'Day 3'!J24) | I59: =IF('Day 3'!W24=ISBLANK(TRUE),"",'Day 3'!W24) | J59: =I59*0.25 -> 0 | K59: =IF(M59<1,"Yes","No") -> No | L59: =IF('Day 3'!S24=ISBLANK(TRUE),"",'Day 3'!S24) | M59: =IF('Day 3'!T24=ISBLANK(TRUE),"",'Day 3'!T24) | N59: =J59*M59 -> 0 | O59: =IF('Day 3'!U24=ISBLANK(TRUE),"",'Day 3'!U24) | P59: =IF('Day 3'!V24=ISBLANK(TRUE),"",'Day 3'!V24) -> 0 | Q59: =J59*P59 -> 0
A60: 3 | B60: =IF('Day 3'!C25=ISBLANK(TRUE),"",'Day 3'!C25) | C60: =IF('Day 3'!$D$6=ISBLANK(TRUE),"",'Day 3'!D25) | D60: =IF('Day 3'!F25=ISBLANK(TRUE),"",'Day 3'!F25) | E60: =IF('Day 3'!G25=ISBLANK(TRUE),"",'Day 3'!G25) | F60: =IF('Day 3'!H25=ISBLANK(TRUE),"",'Day 3'!H25) | G60: =IF('Day 3'!I25=ISBLANK(TRUE),"",'Day 3'!I25) | H60: =IF('Day 3'!J25=ISBLANK(TRUE),"",'Day 3'!J25) | I60: =IF('Day 3'!W25=ISBLANK(TRUE),"",'Day 3'!W25) | J60: =I60*0.25 -> 0 | K60: =IF(M60<1,"Yes","No") -> No | L60: =IF('Day 3'!S25=ISBLANK(TRUE),"",'Day 3'!S25) | M60: =IF('Day 3'!T25=ISBLANK(TRUE),"",'Day 3'!T25) | N60: =J60*M60 -> 0 | O60: =IF('Day 3'!U25=ISBLANK(TRUE),"",'Day 3'!U25) | P60: =IF('Day 3'!V25=ISBLANK(TRUE),"",'Day 3'!V25) -> 0 | Q60: =J60*P60 -> 0
A61: 4 | B61: =IF('Day 4'!C6=ISBLANK(TRUE),"",'Day 4'!C6) | C61: =IF('Day 4'!D6=ISBLANK(TRUE),"",'Day 4'!D6) | D61: Flier | E61: =IF('Day 4'!G6=ISBLANK(TRUE),"",'Day 4'!G6) | F61: 2017 | G61: =IF('Day 4'!I6=ISBLANK(TRUE),"",'Day 4'!I6) | H61: =IF('Day 4'!J6=ISBLANK(TRUE),"",'Day 4'!J6) | I61: =IF('Day 4'!W6=ISBLANK(TRUE),"",'Day 4'!W6) | J61: =I61*0.25 -> 0 | K61: =IF(M61<1,"Yes","No") -> No | L61: =IF('Day 4'!S6=ISBLANK(TRUE),"",'Day 4'!S6) | M61: 1 | N61: 200 | O61: =IF('Day 4'!U6=ISBLANK(TRUE),"",'Day 4'!U6) | P61: =IF('Day 4'!V6=ISBLANK(TRUE),"",'Day 4'!V6) | Q61: =J61*P61 -> 0
A62: 4 | B62: =IF('Day 4'!C7=ISBLANK(TRUE),"",'Day 4'!C7) | C62: =IF('Day 4'!D7=ISBLANK(TRUE),"",'Day 4'!D7) | D62: Flier | E62: =IF('Day 4'!G7=ISBLANK(TRUE),"",'Day 4'!G7) | F62: 2014 | G62: =IF('Day 4'!I7=ISBLANK(TRUE),"",'Day 4'!I7) | H62: =IF('Day 4'!J7=ISBLANK(TRUE),"",'Day 4'!J7) | I62: =IF('Day 4'!W7=ISBLANK(TRUE),"",'Day 4'!W7) | J62: =I62*0.25 -> 0 | K62: =IF(M62<1,"Yes","No") -> No | L62: =IF('Day 4'!S7=ISBLANK(TRUE),"",'Day 4'!S7) | M62: 1 | N62: =J62*M62 -> 0 | O62: =IF('Day 4'!U7=ISBLANK(TRUE),"",'Day 4'!U7) | P62: =IF('Day 4'!V7=ISBLANK(TRUE),"",'Day 4'!V7) | Q62: =J62*P62 -> 0
A63: 4 | B63: =IF('Day 4'!C8=ISBLANK(TRUE),"",'Day 4'!C8) | C63: =IF('Day 4'!D8=ISBLANK(TRUE),"",'Day 4'!D8) | D63: Flier | E63: =IF('Day 4'!G8=ISBLANK(TRUE),"",'Day 4'!G8) | F63: 2017 | G63: =IF('Day 4'!I8=ISBLANK(TRUE),"",'Day 4'!I8) | H63: =IF('Day 4'!J8=ISBLANK(TRUE),"",'Day 4'!J8) | I63: =IF('Day 4'!W8=ISBLANK(TRUE),"",'Day 4'!W8) | J63: =I63*0.25 -> 0 | K63: =IF(M63<1,"Yes","No") -> No | L63: =IF('Day 4'!S8=ISBLANK(TRUE),"",'Day 4'!S8) | M63: 1 | N63: =J63*M63 -> 0 | O63: =IF('Day 4'!U8=ISBLANK(TRUE),"",'Day 4'!U8) | P63: =IF('Day 4'!V8=ISBLANK(TRUE),"",'Day 4'!V8) | Q63: =J63*P63 -> 0
A64: 4 | B64: =IF('Day 4'!C9=ISBLANK(TRUE),"",'Day 4'!C9) | C64: =IF('Day 4'!D9=ISBLANK(TRUE),"",'Day 4'!D9) | D64: Flier | E64: =IF('Day 4'!G9=ISBLANK(TRUE),"",'Day 4'!G9) | F64: 2014 | G64: =IF('Day 4'!I9=ISBLANK(TRUE),"",'Day 4'!I9) | H64: =IF('Day 4'!J9=ISBLANK(TRUE),"",'Day 4'!J9) | I64: =IF('Day 4'!W9=ISBLANK(TRUE),"",'Day 4'!W9) | J64: =I64*0.25 -> 0 | K64: =IF(M64<1,"Yes","No") -> Yes | L64: =IF('Day 4'!S9=ISBLANK(TRUE),"",'Day 4'!S9) | M64: 0.5 | N64: =J64*M64 -> 0 | O64: =IF('Day 4'!U9=ISBLANK(TRUE),"",'Day 4'!U9) | P64: 0.5 | Q64: =J64*P64 -> 0
A65: 4 | B65: =IF('Day 4'!C10=ISBLANK(TRUE),"",'Day 4'!C10) | C65: =IF('Day 4'!D10=ISBLANK(TRUE),"",'Day 4'!D10) | D65: Flier | E65: =IF('Day 4'!G10=ISBLANK(TRUE),"",'Day 4'!G10) | F65: 2017 | G65: =IF('Day 4'!I10=ISBLANK(TRUE),"",'Day 4'!I10) | H65: =IF('Day 4'!J10=ISBLANK(TRUE),"",'Day 4'!J10) | I65: =IF('Day 4'!W10=ISBLANK(TRUE),"",'Day 4'!W10) | J65: =I65*0.25 -> 0 | K65: =IF(M65<1,"Yes","No") -> No | L65: =IF('Day 4'!S10=ISBLANK(TRUE),"",'Day 4'!S10) | M65: 1 | N65: 200 | O65: =IF('Day 4'!U10=ISBLANK(TRUE),"",'Day 4'!U10) | P65: =IF('Day 4'!V10=ISBLANK(TRUE),"",'Day 4'!V10) | Q65: =J65*P65 -> 0
A66: 4 | B66: =IF('Day 4'!C11=ISBLANK(TRUE),"",'Day 4'!C11) | C66: =IF('Day 4'!D11=ISBLANK(TRUE),"",'Day 4'!D11) | D66: Flier | E66: =IF('Day 4'!G11=ISBLANK(TRUE),"",'Day 4'!G11) | F66: 2017 | G66: =IF('Day 4'!I11=ISBLANK(TRUE),"",'Day 4'!I11) | H66: =IF('Day 4'!J11=ISBLANK(TRUE),"",'Day 4'!J11) | I66: =IF('Day 4'!W11=ISBLANK(TRUE),"",'Day 4'!W11) | J66: =I66*0.25 -> 0 | K66: =IF(M66<1,"Yes","No") -> No | L66: =IF('Day 4'!S11=ISBLANK(TRUE),"",'Day 4'!S11) | M66: 1 | N66: 200 | O66: =IF('Day 4'!U11=ISBLANK(TRUE),"",'Day 4'!U11) | P66: =IF('Day 4'!V11=ISBLANK(TRUE),"",'Day 4'!V11) | Q66: =J66*P66 -> 0
A67: 4 | B67: =IF('Day 4'!C12=ISBLANK(TRUE),"",'Day 4'!C12) | C67: =IF('Day 4'!D12=ISBLANK(TRUE),"",'Day 4'!D12) | D67: Flier | E67: =IF('Day 4'!G12=ISBLANK(TRUE),"",'Day 4'!G12) | F67: 2015 | G67: =IF('Day 4'!I12=ISBLANK(TRUE),"",'Day 4'!I12) | H67: =IF('Day 4'!J12=ISBLANK(TRUE),"",'Day 4'!J12) | I67: =IF('Day 4'!W12=ISBLANK(TRUE),"",'Day 4'!W12) | J67: =I67*0.25 -> 0 | K67: =IF(M67<1,"Yes","No") -> Yes | L67: =IF('Day 4'!S12=ISBLANK(TRUE),"",'Day 4'!S12) | M67: 0.5 | N67: =J67*M67 -> 0 | O67: =IF('Day 4'!U12=ISBLANK(TRUE),"",'Day 4'!U12) | P67: 0.5 | Q67: =J67*P67 -> 0
A68: 4 | B68: =IF('Day 4'!C13=ISBLANK(TRUE),"",'Day 4'!C13) | C68: =IF('Day 4'!D13=ISBLANK(TRUE),"",'Day 4'!D13) | D68: Flier | E68: =IF('Day 4'!G13=ISBLANK(TRUE),"",'Day 4'!G13) | F68: 2017 | G68: =IF('Day 4'!I13=ISBLANK(TRUE),"",'Day 4'!I13) | H68: =IF('Day 4'!J13=ISBLANK(TRUE),"",'Day 4'!J13) | I68: =IF('Day 4'!W13=ISBLANK(TRUE),"",'Day 4'!W13) | J68: =I68*0.25 -> 0 | K68: =IF(M68<1,"Yes","No") -> No | L68: =IF('Day 4'!S13=ISBLANK(TRUE),"",'Day 4'!S13) | M68: 1 | N68: =J68*M68 -> 0 | O68: =IF('Day 4'!U13=ISBLANK(TRUE),"",'Day 4'!U13) | P68: =IF('Day 4'!V13=ISBLANK(TRUE),"",'Day 4'!V13) | Q68: =J68*P68 -> 0
A69: 4 | B69: =IF('Day 4'!C14=ISBLANK(TRUE),"",'Day 4'!C14) | C69: =IF('Day 4'!D14=ISBLANK(TRUE),"",'Day 4'!D14) | D69: Flier | E69: =IF('Day 4'!G14=ISBLANK(TRUE),"",'Day 4'!G14) | F69: 2017 | G69: =IF('Day 4'!I14=ISBLANK(TRUE),"",'Day 4'!I14) | H69: =IF('Day 4'!J14=ISBLANK(TRUE),"",'Day 4'!J14) | I69: =IF('Day 4'!W14=ISBLANK(TRUE),"",'Day 4'!W14) | J69: =I69*0.25 -> 0 | K69: =IF(M69<1,"Yes","No") -> No | L69: =IF('Day 4'!S14=ISBLANK(TRUE),"",'Day 4'!S14) | M69: 1 | N69: =J69*M69 -> 0 | O69: =IF('Day 4'!U14=ISBLANK(TRUE),"",'Day 4'!U14) | P69: =IF('Day 4'!V14=ISBLANK(TRUE),"",'Day 4'!V14) | Q69: =J69*P69 -> 0
A70: 4 | B70: =IF('Day 4'!C15=ISBLANK(TRUE),"",'Day 4'!C15) | C70: =IF('Day 4'!D15=ISBLANK(TRUE),"",'Day 4'!D15) | D70: Flier | E70: =IF('Day 4'!G15=ISBLANK(TRUE),"",'Day 4'!G15) | F70: 2014 | G70: =IF('Day 4'!I15=ISBLANK(TRUE),"",'Day 4'!I15) | H70: =IF('Day 4'!J15=ISBLANK(TRUE),"",'Day 4'!J15) | I70: =IF('Day 4'!W15=ISBLANK(TRUE),"",'Day 4'!W15) | J70: =I70*0.25 -> 0 | K70: =IF(M70<1,"Yes","No") -> No | L70: =IF('Day 4'!S15=ISBLANK(TRUE),"",'Day 4'!S15) | M70: 1 | N70: =J70*M70 -> 0 | O70: =IF('Day 4'!U15=ISBLANK(TRUE),"",'Day 4'!U15) | P70: =IF('Day 4'!V15=ISBLANK(TRUE),"",'Day 4'!V15) | Q70: =J70*P70 -> 0
A71: 4 | B71: =IF('Day 4'!C16=ISBLANK(TRUE),"",'Day 4'!C16) | C71: =IF('Day 4'!D16=ISBLANK(TRUE),"",'Day 4'!D16) | D71: =IF('Day 4'!F16=ISBLANK(TRUE),"",'Day 4'!F16) | E71: =IF('Day 4'!G16=ISBLANK(TRUE),"",'Day 4'!G16) | F71: =IF('Day 4'!H16=ISBLANK(TRUE),"",'Day 4'!H56) | G71: =IF('Day 4'!I16=ISBLANK(TRUE),"",'Day 4'!I16) | H71: =IF('Day 4'!J16=ISBLANK(TRUE),"",'Day 4'!J16) | I71: =IF('Day 4'!W16=ISBLANK(TRUE),"",'Day 4'!W16) | J71: =I71*0.25 -> 0 | K71: =IF(M71<1,"Yes","No") -> No | L71: =IF('Day 4'!S16=ISBLANK(TRUE),"",'Day 4'!S16) | M71: =IF('Day 4'!T16=ISBLANK(TRUE),"",'Day 4'!T16) | N71: =J71*M71 -> 0 | O71: =IF('Day 4'!U16=ISBLANK(TRUE),"",'Day 4'!U16) | P71: =IF('Day 4'!V16=ISBLANK(TRUE),"",'Day 4'!V16) | Q71: =J71*P71 -> 0
A72: 4 | B72: =IF('Day 4'!C17=ISBLANK(TRUE),"",'Day 4'!C17) | C72: =IF('Day 4'!D17=ISBLANK(TRUE),"",'Day 4'!D17) | D72: =IF('Day 4'!F17=ISBLANK(TRUE),"",'Day 4'!F17) | E72: =IF('Day 4'!G17=ISBLANK(TRUE),"",'Day 4'!G17) | F72: =IF('Day 4'!H17=ISBLANK(TRUE),"",'Day 4'!H57) | G72: =IF('Day 4'!I17=ISBLANK(TRUE),"",'Day 4'!I17) | H72: =IF('Day 4'!J17=ISBLANK(TRUE),"",'Day 4'!J17) | I72: =IF('Day 4'!W17=ISBLANK(TRUE),"",'Day 4'!W17) | J72: =I72*0.25 -> 0 | K72: =IF(M72<1,"Yes","No") -> No | L72: =IF('Day 4'!S17=ISBLANK(TRUE),"",'Day 4'!S17) | M72: =IF('Day 4'!T17=ISBLANK(TRUE),"",'Day 4'!T17) | N72: =J72*M72 -> 0 | O72: =IF('Day 4'!U17=ISBLANK(TRUE),"",'Day 4'!U17) | P72: =IF('Day 4'!V17=ISBLANK(TRUE),"",'Day 4'!V17) | Q72: =J72*P72 -> 0
A73: 4 | B73: =IF('Day 4'!C18=ISBLANK(TRUE),"",'Day 4'!C18) | C73: =IF('Day 4'!D18=ISBLANK(TRUE),"",'Day 4'!D18) | D73: =IF('Day 4'!F18=ISBLANK(TRUE),"",'Day 4'!F18) | E73: =IF('Day 4'!G18=ISBLANK(TRUE),"",'Day 4'!G18) | F73: =IF('Day 4'!H18=ISBLANK(TRUE),"",'Day 4'!H58) | G73: =IF('Day 4'!I18=ISBLANK(TRUE),"",'Day 4'!I18) | H73: =IF('Day 4'!J18=ISBLANK(TRUE),"",'Day 4'!J18) | I73: =IF('Day 4'!W18=ISBLANK(TRUE),"",'Day 4'!W18) | J73: =I73*0.25 -> 0 | K73: =IF(M73<1,"Yes","No") -> No | L73: =IF('Day 4'!S18=ISBLANK(TRUE),"",'Day 4'!S18) | M73: =IF('Day 4'!T18=ISBLANK(TRUE),"",'Day 4'!T18) | N73: =J73*M73 -> 0 | O73: =IF('Day 4'!U18=ISBLANK(TRUE),"",'Day 4'!U18) | P73: =IF('Day 4'!V18=ISBLANK(TRUE),"",'Day 4'!V18) | Q73: =J73*P73 -> 0
A74: 4 | B74: =IF('Day 4'!C19=ISBLANK(TRUE),"",'Day 4'!C19) | C74: =IF('Day 4'!D19=ISBLANK(TRUE),"",'Day 4'!D19) | D74: =IF('Day 4'!F19=ISBLANK(TRUE),"",'Day 4'!F19) | E74: =IF('Day 4'!G19=ISBLANK(TRUE),"",'Day 4'!G19) | F74: =IF('Day 4'!H19=ISBLANK(TRUE),"",'Day 4'!H59) | G74: =IF('Day 4'!I19=ISBLANK(TRUE),"",'Day 4'!I19) | H74: =IF('Day 4'!J19=ISBLANK(TRUE),"",'Day 4'!J19) | I74: =IF('Day 4'!W19=ISBLANK(TRUE),"",'Day 4'!W19) | J74: =I74*0.25 -> 0 | K74: =IF(M74<1,"Yes","No") -> No | L74: =IF('Day 4'!S19=ISBLANK(TRUE),"",'Day 4'!S19) | M74: =IF('Day 4'!T19=ISBLANK(TRUE),"",'Day 4'!T19) | N74: =J74*M74 -> 0 | O74: =IF('Day 4'!U19=ISBLANK(TRUE),"",'Day 4'!U19) | P74: =IF('Day 4'!V19=ISBLANK(TRUE),"",'Day 4'!V19) | Q74: =J74*P74 -> 0
A75: 4 | B75: =IF('Day 4'!C20=ISBLANK(TRUE),"",'Day 4'!C20) | C75: =IF('Day 4'!D20=ISBLANK(TRUE),"",'Day 4'!D20) | D75: =IF('Day 4'!F20=ISBLANK(TRUE),"",'Day 4'!F20) | E75: =IF('Day 4'!G20=ISBLANK(TRUE),"",'Day 4'!G20) | F75: =IF('Day 4'!H20=ISBLANK(TRUE),"",'Day 4'!H60) | G75: =IF('Day 4'!I20=ISBLANK(TRUE),"",'Day 4'!I20) | H75: =IF('Day 4'!J20=ISBLANK(TRUE),"",'Day 4'!J20) | I75: =IF('Day 4'!W20=ISBLANK(TRUE),"",'Day 4'!W20) | J75: =I75*0.25 -> 0 | K75: =IF(M75<1,"Yes","No") -> No | L75: =IF('Day 4'!S20=ISBLANK(TRUE),"",'Day 4'!S20) | M75: =IF('Day 4'!T20=ISBLANK(TRUE),"",'Day 4'!T20) | N75: =J75*M75 -> 0 | O75: =IF('Day 4'!U20=ISBLANK(TRUE),"",'Day 4'!U20) | P75: =IF('Day 4'!V20=ISBLANK(TRUE),"",'Day 4'!V20) | Q75: =J75*P75 -> 0
A76: 4 | B76: =IF('Day 4'!C21=ISBLANK(TRUE),"",'Day 4'!C21) | C76: =IF('Day 4'!D21=ISBLANK(TRUE),"",'Day 4'!D21) | D76: =IF('Day 4'!F21=ISBLANK(TRUE),"",'Day 4'!F21) | E76: =IF('Day 4'!G21=ISBLANK(TRUE),"",'Day 4'!G21) | F76: =IF('Day 4'!H21=ISBLANK(TRUE),"",'Day 4'!H61) | G76: =IF('Day 4'!I21=ISBLANK(TRUE),"",'Day 4'!I21) | H76: =IF('Day 4'!J21=ISBLANK(TRUE),"",'Day 4'!J21) | I76: =IF('Day 4'!W21=ISBLANK(TRUE),"",'Day 4'!W21) | J76: =I76*0.25 -> 0 | K76: =IF(M76<1,"Yes","No") -> No | L76: =IF('Day 4'!S21=ISBLANK(TRUE),"",'Day 4'!S21) | M76: =IF('Day 4'!T21=ISBLANK(TRUE),"",'Day 4'!T21) | N76: =J76*M76 -> 0 | O76: =IF('Day 4'!U21=ISBLANK(TRUE),"",'Day 4'!U21) | P76: =IF('Day 4'!V21=ISBLANK(TRUE),"",'Day 4'!V21) | Q76: =J76*P76 -> 0
A77: 4 | B77: =IF('Day 4'!C22=ISBLANK(TRUE),"",'Day 4'!C22) | C77: =IF('Day 4'!D22=ISBLANK(TRUE),"",'Day 4'!D22) | D77: =IF('Day 4'!F22=ISBLANK(TRUE),"",'Day 4'!F22) | E77: =IF('Day 4'!G22=ISBLANK(TRUE),"",'Day 4'!G22) | F77: =IF('Day 4'!H22=ISBLANK(TRUE),"",'Day 4'!H62) | G77: =IF('Day 4'!I22=ISBLANK(TRUE),"",'Day 4'!I22) | H77: =IF('Day 4'!J22=ISBLANK(TRUE),"",'Day 4'!J22) | I77: =IF('Day 4'!W22=ISBLANK(TRUE),"",'Day 4'!W22) | J77: =I77*0.25 -> 0 | K77: =IF(M77<1,"Yes","No") -> No | L77: =IF('Day 4'!S22=ISBLANK(TRUE),"",'Day 4'!S22) | M77: =IF('Day 4'!T22=ISBLANK(TRUE),"",'Day 4'!T22) | N77: =J77*M77 -> 0 | O77: =IF('Day 4'!U22=ISBLANK(TRUE),"",'Day 4'!U22) | P77: =IF('Day 4'!V22=ISBLANK(TRUE),"",'Day 4'!V22) | Q77: =J77*P77 -> 0
A78: 4 | B78: =IF('Day 4'!C23=ISBLANK(TRUE),"",'Day 4'!C23) | C78: =IF('Day 4'!D23=ISBLANK(TRUE),"",'Day 4'!D23) | D78: =IF('Day 4'!F23=ISBLANK(TRUE),"",'Day 4'!F23) | E78: =IF('Day 4'!G23=ISBLANK(TRUE),"",'Day 4'!G23) | F78: =IF('Day 4'!H23=ISBLANK(TRUE),"",'Day 4'!H63) | G78: =IF('Day 4'!I23=ISBLANK(TRUE),"",'Day 4'!I23) | H78: =IF('Day 4'!J23=ISBLANK(TRUE),"",'Day 4'!J23) | I78: =IF('Day 4'!W23=ISBLANK(TRUE),"",'Day 4'!W23) | J78: =I78*0.25 -> 0 | K78: =IF(M78<1,"Yes","No") -> No | L78: =IF('Day 4'!S23=ISBLANK(TRUE),"",'Day 4'!S23) | M78: =IF('Day 4'!T23=ISBLANK(TRUE),"",'Day 4'!T23) | N78: =J78*M78 -> 0 | O78: =IF('Day 4'!U23=ISBLANK(TRUE),"",'Day 4'!U23) | P78: =IF('Day 4'!V23=ISBLANK(TRUE),"",'Day 4'!V23) | Q78: =J78*P78 -> 0
A79: 4 | B79: =IF('Day 4'!C24=ISBLANK(TRUE),"",'Day 4'!C24) | C79: =IF('Day 4'!D24=ISBLANK(TRUE),"",'Day 4'!D24) | D79: =IF('Day 4'!F24=ISBLANK(TRUE),"",'Day 4'!F24) | E79: =IF('Day 4'!G24=ISBLANK(TRUE),"",'Day 4'!G24) | F79: =IF('Day 4'!H24=ISBLANK(TRUE),"",'Day 4'!H64) | G79: =IF('Day 4'!I24=ISBLANK(TRUE),"",'Day 4'!I24) | H79: =IF('Day 4'!J24=ISBLANK(TRUE),"",'Day 4'!J24) | I79: =IF('Day 4'!W24=ISBLANK(TRUE),"",'Day 4'!W24) | J79: =I79*0.25 -> 0 | K79: =IF(M79<1,"Yes","No") -> No | L79: =IF('Day 4'!S24=ISBLANK(TRUE),"",'Day 4'!S24) | M79: =IF('Day 4'!T24=ISBLANK(TRUE),"",'Day 4'!T24) | N79: =J79*M79 -> 0 | O79: =IF('Day 4'!U24=ISBLANK(TRUE),"",'Day 4'!U24) | P79: =IF('Day 4'!V24=ISBLANK(TRUE),"",'Day 4'!V24) | Q79: =J79*P79 -> 0
A80: 4 | B80: =IF('Day 4'!C25=ISBLANK(TRUE),"",'Day 4'!C25) | C80: =IF('Day 4'!D25=ISBLANK(TRUE),"",'Day 4'!D25) | D80: =IF('Day 4'!F25=ISBLANK(TRUE),"",'Day 4'!F25) | E80: =IF('Day 4'!G25=ISBLANK(TRUE),"",'Day 4'!G25) | F80: =IF('Day 4'!H25=ISBLANK(TRUE),"",'Day 4'!H65) | G80: =IF('Day 4'!I25=ISBLANK(TRUE),"",'Day 4'!I25) | H80: =IF('Day 4'!J25=ISBLANK(TRUE),"",'Day 4'!J25) | I80: =IF('Day 4'!W25=ISBLANK(TRUE),"",'Day 4'!W25) | J80: =I80*0.25 -> 0 | K80: =IF(M80<1,"Yes","No") -> No | L80: =IF('Day 4'!S25=ISBLANK(TRUE),"",'Day 4'!S25) | M80: =IF('Day 4'!T25=ISBLANK(TRUE),"",'Day 4'!T25) | N80: =J80*M80 -> 0 | O80: =IF('Day 4'!U25=ISBLANK(TRUE),"",'Day 4'!U25) | P80: =IF('Day 4'!V25=ISBLANK(TRUE),"",'Day 4'!V25) | Q80: =J80*P80 -> 0
A81: 5 | B81: =IF('Day 5'!B6=ISBLANK(TRUE),"",'Day 5'!B6) | C81: =IF('Day 5'!C6=ISBLANK(TRUE),"",'Day 5'!C6) | D81: =IF('Day 5'!E6=ISBLANK(TRUE),"",'Day 5'!E6) | E81: =IF('Day 5'!F6=ISBLANK(TRUE),"",'Day 5'!F6) | F81: =IF('Day 5'!G6=ISBLANK(TRUE),"",'Day 5'!G6) | G81: =IF('Day 5'!H6=ISBLANK(TRUE),"",'Day 5'!H6) | H81: =IF('Day 5'!I6=ISBLANK(TRUE),"",'Day 5'!I6) | I81: =IF('Day 5'!V6=ISBLANK(TRUE),"",'Day 5'!V6) | J81: =I81*0.25 -> 0 | K81: =IF(M81<1,"Yes","No") -> No | L81: =IF('Day 5'!R6=ISBLANK(TRUE),"",'Day 5'!R6) | M81: 1 | N81: =J81*M81 -> 0 | O81: =IF('Day 5'!T6=ISBLANK(TRUE),"",'Day 5'!T6) | P81: =IF('Day 5'!U6=ISBLANK(TRUE),"",'Day 5'!U6) | Q81: =J81*P81 -> 0
A82: 5 | B82: =IF('Day 5'!B7=ISBLANK(TRUE),"",'Day 5'!B7) | C82: =IF('Day 5'!C7=ISBLANK(TRUE),"",'Day 5'!C7) | D82: =IF('Day 5'!E7=ISBLANK(TRUE),"",'Day 5'!E7) | E82: =IF('Day 5'!F7=ISBLANK(TRUE),"",'Day 5'!F7) | F82: =IF('Day 5'!G7=ISBLANK(TRUE),"",'Day 5'!G7) | G82: =IF('Day 5'!H7=ISBLANK(TRUE),"",'Day 5'!H7) | H82: =IF('Day 5'!I7=ISBLANK(TRUE),"",'Day 5'!I7) | I82: =IF('Day 5'!V7=ISBLANK(TRUE),"",'Day 5'!V7) | J82: =I82*0.25 -> 0 | K82: =IF(M82<1,"Yes","No") -> No | L82: =IF('Day 5'!R7=ISBLANK(TRUE),"",'Day 5'!R7) | M82: 1 | N82: =J82*M82 -> 0 | O82: =IF('Day 5'!T7=ISBLANK(TRUE),"",'Day 5'!T7) | P82: =IF('Day 5'!U7=ISBLANK(TRUE),"",'Day 5'!U7) | Q82: =J82*P82 -> 0
A83: 5 | B83: =IF('Day 5'!B8=ISBLANK(TRUE),"",'Day 5'!B8) | C83: =IF('Day 5'!C8=ISBLANK(TRUE),"",'Day 5'!C8) | D83: =IF('Day 5'!E8=ISBLANK(TRUE),"",'Day 5'!E8) | E83: =IF('Day 5'!F8=ISBLANK(TRUE),"",'Day 5'!F8) | F83: =IF('Day 5'!G8=ISBLANK(TRUE),"",'Day 5'!G8) | G83: =IF('Day 5'!H8=ISBLANK(TRUE),"",'Day 5'!H8) | H83: =IF('Day 5'!I8=ISBLANK(TRUE),"",'Day 5'!I8) | I83: =IF('Day 5'!V8=ISBLANK(TRUE),"",'Day 5'!V8) | J83: =I83*0.25 -> 0 | K83: =IF(M83<1,"Yes","No") -> No | L83: =IF('Day 5'!R8=ISBLANK(TRUE),"",'Day 5'!R8) | M83: 1 | N83: =J83*M83 -> 0 | O83: =IF('Day 5'!T8=ISBLANK(TRUE),"",'Day 5'!T8) | P83: =IF('Day 5'!U8=ISBLANK(TRUE),"",'Day 5'!U8) | Q83: =J83*P83 -> 0
A84: 5 | B84: =IF('Day 5'!B9=ISBLANK(TRUE),"",'Day 5'!B9) | C84: =IF('Day 5'!C10=ISBLANK(TRUE),"",'Day 5'!C10) | D84: =IF('Day 5'!E9=ISBLANK(TRUE),"",'Day 5'!E9) | E84: =IF('Day 5'!F9=ISBLANK(TRUE),"",'Day 5'!F9) | F84: =IF('Day 5'!G9=ISBLANK(TRUE),"",'Day 5'!G9) | G84: =IF('Day 5'!H9=ISBLANK(TRUE),"",'Day 5'!H9) | H84: =IF('Day 5'!I9=ISBLANK(TRUE),"",'Day 5'!I9) | I84: =IF('Day 5'!V9=ISBLANK(TRUE),"",'Day 5'!V9) | J84: =I84*0.25 -> 0 | K84: =IF(M84<1,"Yes","No") -> No | L84: =IF('Day 5'!R9=ISBLANK(TRUE),"",'Day 5'!R9) | M84: 1 | N84: =J84*M84 -> 0 | O84: =IF('Day 5'!T9=ISBLANK(TRUE),"",'Day 5'!T9) | P84: =IF('Day 5'!U9=ISBLANK(TRUE),"",'Day 5'!U9) | Q84: =J84*P84 -> 0
A85: 5 | B85: =IF('Day 5'!B10=ISBLANK(TRUE),"",'Day 5'!B10) | C85: =IF(#REF!=ISBLANK(TRUE),"",#REF!) -> #REF! | D85: =IF('Day 5'!E10=ISBLANK(TRUE),"",'Day 5'!E10) | E85: =IF('Day 5'!F10=ISBLANK(TRUE),"",'Day 5'!F10) | F85: =IF('Day 5'!G10=ISBLANK(TRUE),"",'Day 5'!G10) | G85: =IF('Day 5'!H10=ISBLANK(TRUE),"",'Day 5'!H10) | H85: =IF('Day 5'!I10=ISBLANK(TRUE),"",'Day 5'!I10) | I85: =IF('Day 5'!V10=ISBLANK(TRUE),"",'Day 5'!V10) | J85: =I85*0.25 -> 0 | K85: =IF(M85<1,"Yes","No") -> Yes | L85: =IF('Day 5'!R10=ISBLANK(TRUE),"",'Day 5'!R10) | M85: 0.5 | N85: =J85*M85 -> 0 | O85: =IF('Day 5'!T10=ISBLANK(TRUE),"",'Day 5'!T10) | P85: 0.5 | Q85: =J85*P85 -> 0
A86: 5 | B86: =IF('Day 5'!B11=ISBLANK(TRUE),"",'Day 5'!B11) | C86: =IF('Day 5'!C11=ISBLANK(TRUE),"",'Day 5'!C11) | D86: =IF('Day 5'!E11=ISBLANK(TRUE),"",'Day 5'!E11) | E86: =IF('Day 5'!F11=ISBLANK(TRUE),"",'Day 5'!F11) | F86: =IF('Day 5'!G11=ISBLANK(TRUE),"",'Day 5'!G11) | G86: =IF('Day 5'!H11=ISBLANK(TRUE),"",'Day 5'!H11) | H86: =IF('Day 5'!I11=ISBLANK(TRUE),"",'Day 5'!I11) | I86: =IF('Day 5'!V11=ISBLANK(TRUE),"",'Day 5'!V11) | J86: =I86*0.25 -> 0 | K86: =IF(M86<1,"Yes","No") -> No | L86: =IF('Day 5'!R11=ISBLANK(TRUE),"",'Day 5'!R11) | M86: 1 | N86: =J86*M86 -> 0 | O86: =IF('Day 5'!T11=ISBLANK(TRUE),"",'Day 5'!T11) | P86: =IF('Day 5'!U11=ISBLANK(TRUE),"",'Day 5'!U11) | Q86: =J86*P86 -> 0
A87: 5 | B87: =IF('Day 5'!B12=ISBLANK(TRUE),"",'Day 5'!B12) | C87: =IF('Day 5'!C12=ISBLANK(TRUE),"",'Day 5'!C12) | D87: =IF('Day 5'!E12=ISBLANK(TRUE),"",'Day 5'!E12) | E87: =IF('Day 5'!F12=ISBLANK(TRUE),"",'Day 5'!F12) | F87: =IF('Day 5'!G12=ISBLANK(TRUE),"",'Day 5'!G12) | G87: =IF('Day 5'!H12=ISBLANK(TRUE),"",'Day 5'!H12) | H87: =IF('Day 5'!I12=ISBLANK(TRUE),"",'Day 5'!I12) | I87: =IF('Day 5'!V12=ISBLANK(TRUE),"",'Day 5'!V12) | J87: =I87*0.25 -> 0 | K87: =IF(M87<1,"Yes","No") -> Yes | L87: =IF('Day 5'!R12=ISBLANK(TRUE),"",'Day 5'!R12) | M87: 0.5 | N87: =J87*M87 -> 0 | O87: =IF('Day 5'!T12=ISBLANK(TRUE),"",'Day 5'!T12) | P87: 0.5 | Q87: =J87*P87 -> 0
A88: 5 | B88: =IF('Day 5'!B13=ISBLANK(TRUE),"",'Day 5'!B13) | C88: =IF('Day 5'!C13=ISBLANK(TRUE),"",'Day 5'!C13) | D88: =IF('Day 5'!E13=ISBLANK(TRUE),"",'Day 5'!E13) | E88: =IF('Day 5'!F13=ISBLANK(TRUE),"",'Day 5'!F13) | F88: =IF('Day 5'!G13=ISBLANK(TRUE),"",'Day 5'!G13) | G88: =IF('Day 5'!H13=ISBLANK(TRUE),"",'Day 5'!H13) | H88: =IF('Day 5'!I13=ISBLANK(TRUE),"",'Day 5'!I13) | I88: =IF('Day 5'!V13=ISBLANK(TRUE),"",'Day 5'!V13) | J88: =I88*0.25 -> 0 | K88: =IF(M88<1,"Yes","No") -> No | L88: =IF('Day 5'!R13=ISBLANK(TRUE),"",'Day 5'!R13) | M88: =IF('Day 5'!S13=ISBLANK(TRUE),"",'Day 5'!S13) | N88: =J88*M88 -> 0 | O88: =IF('Day 5'!T13=ISBLANK(TRUE),"",'Day 5'!T13) | P88: =IF('Day 5'!U13=ISBLANK(TRUE),"",'Day 5'!U13) | Q88: =J88*P88 -> 0
A89: 5 | B89: =IF('Day 5'!B14=ISBLANK(TRUE),"",'Day 5'!B14) | C89: =IF('Day 5'!C14=ISBLANK(TRUE),"",'Day 5'!C14) | D89: =IF('Day 5'!E14=ISBLANK(TRUE),"",'Day 5'!E14) | E89: =IF('Day 5'!F14=ISBLANK(TRUE),"",'Day 5'!F14) | F89: =IF('Day 5'!G14=ISBLANK(TRUE),"",'Day 5'!G14) | G89: =IF('Day 5'!H14=ISBLANK(TRUE),"",'Day 5'!H14) | H89: =IF('Day 5'!I14=ISBLANK(TRUE),"",'Day 5'!I14) | I89: =IF('Day 5'!V14=ISBLANK(TRUE),"",'Day 5'!V14) | J89: =I89*0.25 -> 0 | K89: =IF(M89<1,"Yes","No") -> No | L89: =IF('Day 5'!R14=ISBLANK(TRUE),"",'Day 5'!R14) | M89: =IF('Day 5'!S14=ISBLANK(TRUE),"",'Day 5'!S14) | N89: =J89*M89 -> 0 | O89: =IF('Day 5'!T14=ISBLANK(TRUE),"",'Day 5'!T14) | P89: =IF('Day 5'!U14=ISBLANK(TRUE),"",'Day 5'!U14) | Q89: =J89*P89 -> 0
A90: 5 | B90: =IF('Day 5'!B15=ISBLANK(TRUE),"",'Day 5'!B15) | C90: =IF('Day 5'!C15=ISBLANK(TRUE),"",'Day 5'!C15) | D90: =IF('Day 5'!E15=ISBLANK(TRUE),"",'Day 5'!E15) | E90: =IF('Day 5'!F15=ISBLANK(TRUE),"",'Day 5'!F15) | F90: =IF('Day 5'!G15=ISBLANK(TRUE),"",'Day 5'!G15) | G90: =IF('Day 5'!H15=ISBLANK(TRUE),"",'Day 5'!H15) | H90: =IF('Day 5'!I15=ISBLANK(TRUE),"",'Day 5'!I15) | I90: =IF('Day 5'!V15=ISBLANK(TRUE),"",'Day 5'!V15) | J90: =I90*0.25 -> 0 | K90: =IF(M90<1,"Yes","No") -> No | L90: =IF('Day 5'!R15=ISBLANK(TRUE),"",'Day 5'!R15) | M90: =IF('Day 5'!S15=ISBLANK(TRUE),"",'Day 5'!S15) | N90: =J90*M90 -> 0 | O90: =IF('Day 5'!T15=ISBLANK(TRUE),"",'Day 5'!T15) | P90: =IF('Day 5'!U15=ISBLANK(TRUE),"",'Day 5'!U15) | Q90: =J90*P90 -> 0
A91: 5 | B91: =IF('Day 5'!B16=ISBLANK(TRUE),"",'Day 5'!B16) | C91: =IF('Day 5'!C16=ISBLANK(TRUE),"",'Day 5'!C16) | D91: =IF('Day 5'!E16=ISBLANK(TRUE),"",'Day 5'!E16) | E91: =IF('Day 5'!F16=ISBLANK(TRUE),"",'Day 5'!F16) | F91: =IF('Day 5'!G16=ISBLANK(TRUE),"",'Day 5'!G16) | G91: =IF('Day 5'!H16=ISBLANK(TRUE),"",'Day 5'!H16) | H91: =IF('Day 5'!I16=ISBLANK(TRUE),"",'Day 5'!I16) | I91: =IF('Day 5'!V16=ISBLANK(TRUE),"",'Day 5'!V16) | J91: =I91*0.25 -> 0 | K91: =IF(M91<1,"Yes","No") -> No | L91: =IF('Day 5'!R16=ISBLANK(TRUE),"",'Day 5'!R16) | M91: =IF('Day 5'!S16=ISBLANK(TRUE),"",'Day 5'!S16) | N91: =J91*M91 -> 0 | O91: =IF('Day 5'!T16=ISBLANK(TRUE),"",'Day 5'!T16) | P91: =IF('Day 5'!U16=ISBLANK(TRUE),"",'Day 5'!U16) | Q91: =J91*P91 -> 0
A92: 5 | B92: =IF('Day 5'!B17=ISBLANK(TRUE),"",'Day 5'!B17) | C92: =IF('Day 5'!C17=ISBLANK(TRUE),"",'Day 5'!C17) | D92: =IF('Day 5'!E17=ISBLANK(TRUE),"",'Day 5'!E17) | E92: =IF('Day 5'!F17=ISBLANK(TRUE),"",'Day 5'!F17) | F92: =IF('Day 5'!G17=ISBLANK(TRUE),"",'Day 5'!G17) | G92: =IF('Day 5'!H17=ISBLANK(TRUE),"",'Day 5'!H17) | H92: =IF('Day 5'!I17=ISBLANK(TRUE),"",'Day 5'!I17) | I92: =IF('Day 5'!V17=ISBLANK(TRUE),"",'Day 5'!V17) | J92: =I92*0.25 -> 0 | K92: =IF(M92<1,"Yes","No") -> No | L92: =IF('Day 5'!R17=ISBLANK(TRUE),"",'Day 5'!R17) | M92: =IF('Day 5'!S17=ISBLANK(TRUE),"",'Day 5'!S17) | N92: =J92*M92 -> 0 | O92: =IF('Day 5'!T17=ISBLANK(TRUE),"",'Day 5'!T17) | P92: =IF('Day 5'!U17=ISBLANK(TRUE),"",'Day 5'!U17) | Q92: =J92*P92 -> 0
